Workbook

Sheet Ahorro BBVA
H2: AHORRO MIKEL
L4: TOTAL | N4: TOTAL BBVA | P4: TOTAL BANKINTER | T4: AHORRO ÚLTIMO MES
L5: {=INDEX(I22:I224,MATCH(TRUE,I22:I224>0,0))} -> 141556.83 | N5: {=INDEX(D22:D224,MATCH(TRUE,D22:D224>0,0))} -> 2556.83 | P5: {=INDEX(H22:H224,MATCH(TRUE,H22:H224>0,0))} -> 139000 | T5: {=INDEX(J22:J224,MATCH(TRUE,J22:J224>0,0))} -> 1696.41
A7: Mes | B7: Cuenta | C7: Ahorro | D7: BBVA | E7: Sant | F7: EVO | G7: B100 | H7: Openbank Cajamar | I7: TOTAL | J7: +/-
A8: 46357 | C8: 0 | D8: =IFERROR(IF(ISBLANK(B8)=FALSE,B8,"")+IF(ISBLANK(C8)=FALSE,C8,""),"") | E8: 0 | F8: 0 | G8: 0 | I8: =IFERROR(IF(ISBLANK(D8)=FALSE,D8,"")+IF(ISBLANK(E8)=FALSE,E8,"")+IF(ISBLANK(F8)=FALSE,F8,"")+IF(ISBLANK(G8)=FALSE,G8,"")+IF(ISBLANK(H8)=FALSE,H8,""),"") | J8: =IFERROR(IF(ISBLANK(I8)=FALSE,I8-I9,""),"")
A9: 46327 | C9: 0 | D9: =IFERROR(IF(ISBLANK(B9)=FALSE,B9,"")+IF(ISBLANK(C9)=FALSE,C9,""),"") | E9: 0 | F9: 0 | G9: 0 | I9: =IFERROR(IF(ISBLANK(D9)=FALSE,D9,"")+IF(ISBLANK(E9)=FALSE,E9,"")+IF(ISBLANK(F9)=FALSE,F9,"")+IF(ISBLANK(G9)=FALSE,G9,"")+IF(ISBLANK(H9)=FALSE,H9,""),"") | J9: =IFERROR(IF(ISBLANK(I9)=FALSE,I9-I10,""),"")
A10: 46296 | C10: 0 | D10: =IFERROR(IF(ISBLANK(B10)=FALSE,B10,"")+IF(ISBLANK(C10)=FALSE,C10,""),"") | E10: 0 | F10: 0 | G10: 0 | I10: =IFERROR(IF(ISBLANK(D10)=FALSE,D10,"")+IF(ISBLANK(E10)=FALSE,E10,"")+IF(ISBLANK(F10)=FALSE,F10,"")+IF(ISBLANK(G10)=FALSE,G10,"")+IF(ISBLANK(H10)=FALSE,H10,""),"") | J10: =IFERROR(IF(ISBLANK(I10)=FALSE,I10-I11,""),"")
A11: 46266 | C11: 0 | D11: =IFERROR(IF(ISBLANK(B11)=FALSE,B11,"")+IF(ISBLANK(C11)=FALSE,C11,""),"") | E11: 0 | F11: 0 | G11: 0 | I11: =IFERROR(IF(ISBLANK(D11)=FALSE,D11,"")+IF(ISBLANK(E11)=FALSE,E11,"")+IF(ISBLANK(F11)=FALSE,F11,"")+IF(ISBLANK(G11)=FALSE,G11,"")+IF(ISBLANK(H11)=FALSE,H11,""),"") | J11: =IFERROR(IF(ISBLANK(I11)=FALSE,I11-I12,""),"")
A12: 46235 | C12: 0 | D12: =IFERROR(IF(ISBLANK(B12)=FALSE,B12,"")+IF(ISBLANK(C12)=FALSE,C12,""),"") | E12: 0 | F12: 0 | G12: 0 | I12: =IFERROR(IF(ISBLANK(D12)=FALSE,D12,"")+IF(ISBLANK(E12)=FALSE,E12,"")+IF(ISBLANK(F12)=FALSE,F12,"")+IF(ISBLANK(G12)=FALSE,G12,"")+IF(ISBLANK(H12)=FALSE,H12,""),"") | J12: =IFERROR(IF(ISBLANK(I12)=FALSE,I12-I13,""),"")
A13: 46204 | C13: 0 | D13: =IFERROR(IF(ISBLANK(B13)=FALSE,B13,"")+IF(ISBLANK(C13)=FALSE,C13,""),"") | E13: 0 | F13: 0 | G13: 0 | I13: =IFERROR(IF(ISBLANK(D13)=FALSE,D13,"")+IF(ISBLANK(E13)=FALSE,E13,"")+IF(ISBLANK(F13)=FALSE,F13,"")+IF(ISBLANK(G13)=FALSE,G13,"")+IF(ISBLANK(H13)=FALSE,H13,""),"") | J13: =IFERROR(IF(ISBLANK(I13)=FALSE,I13-I14,""),"")
A14: 46174 | C14: 0 | D14: =IFERROR(IF(ISBLANK(B14)=FALSE,B14,"")+IF(ISBLANK(C14)=FALSE,C14,""),"") | E14: 0 | F14: 0 | G14: 0 | H14: 126000 | I14: =IFERROR(IF(ISBLANK(D14)=FALSE,D14,"")+IF(ISBLANK(E14)=FALSE,E14,"")+IF(ISBLANK(F14)=FALSE,F14,"")+IF(ISBLANK(G14)=FALSE,G14,"")+IF(ISBLANK(H14)=FALSE,H14,""),"") | J14: =IFERROR(IF(ISBLANK(I14)=FALSE,I14-I15,""),"")
A15: 46143 | B15: 946.69 | C15: 0 | D15: =IFERROR(IF(ISBLANK(B15)=FALSE,B15,"")+IF(ISBLANK(C15)=FALSE,C15,""),"") -> 946.69 | E15: 0 | F15: 0 | G15: 0 | H15: =74000+50000 -> 124000 | I15: =IFERROR(IF(ISBLANK(D15)=FALSE,D15,"")+IF(ISBLANK(E15)=FALSE,E15,"")+IF(ISBLANK(F15)=FALSE,F15,"")+IF(ISBLANK(G15)=FALSE,G15,"")+IF(ISBLANK(H15)=FALSE,H15,""),"") -> 124946.69 | J15: =IFERROR(IF(ISBLANK(I15)=FALSE,I15-I16,""),"") -> 1530.18
A16: 46113 | B16: 416.51 | C16: 0 | D16: =IFERROR(IF(ISBLANK(B16)=FALSE,B16,"")+IF(ISBLANK(C16)=FALSE,C16,""),"") -> 416.51 | E16: 0 | F16: 0 | G16: 0 | H16: =50000+73000 -> 123000 | I16: =IFERROR(IF(ISBLANK(D16)=FALSE,D16,"")+IF(ISBLANK(E16)=FALSE,E16,"")+IF(ISBLANK(F16)=FALSE,F16,"")+IF(ISBLANK(G16)=FALSE,G16,"")+IF(ISBLANK(H16)=FALSE,H16,""),"") -> 123416.51 | J16: =IFERROR(IF(ISBLANK(I16)=FALSE,I16-I17,""),"") -> -27681.12
A17: 46082 | B17: 597.63 | C17: 0 | D17: =IFERROR(IF(ISBLANK(B17)=FALSE,B17,"")+IF(ISBLANK(C17)=FALSE,C17,""),"") -> 597.63 | E17: 0 | F17: 0 | G17: 0 | H17: 150500 | I17: =IFERROR(IF(ISBLANK(D17)=FALSE,D17,"")+IF(ISBLANK(E17)=FALSE,E17,"")+IF(ISBLANK(F17)=FALSE,F17,"")+IF(ISBLANK(G17)=FALSE,G17,"")+IF(ISBLANK(H17)=FALSE,H17,""),"") -> 151097.63 | J17: =IFERROR(IF(ISBLANK(I17)=FALSE,I17-I18,""),"") -> 1968.36
A18: 46054 | B18: 629.27 | C18: 0 | D18: =IFERROR(IF(ISBLANK(B18)=FALSE,B18,"")+IF(ISBLANK(C18)=FALSE,C18,""),"") -> 629.27 | E18: 0 | F18: 0 | G18: 0 | H18: 148500 | I18: =IFERROR(IF(ISBLANK(D18)=FALSE,D18,"")+IF(ISBLANK(E18)=FALSE,E18,"")+IF(ISBLANK(F18)=FALSE,F18,"")+IF(ISBLANK(G18)=FALSE,G18,"")+IF(ISBLANK(H18)=FALSE,H18,""),"") -> 149129.27 | J18: =IFERROR(IF(ISBLANK(I18)=FALSE,I18-I19,""),"") -> 1811.7
A19: 46023 | B19: 317.57 | C19: 0 | D19: =IFERROR(IF(ISBLANK(B19)=FALSE,B19,"")+IF(ISBLANK(C19)=FALSE,C19,""),"") -> 317.57 | E19: 0 | F19: 0 | G19: 0 | H19: 147000 | I19: =IFERROR(IF(ISBLANK(D19)=FALSE,D19,"")+IF(ISBLANK(E19)=FALSE,E19,"")+IF(ISBLANK(F19)=FALSE,F19,"")+IF(ISBLANK(G19)=FALSE,G19,"")+IF(ISBLANK(H19)=FALSE,H19,""),"") -> 147317.57 | J19: =IFERROR(IF(ISBLANK(I19)=FALSE,I19-I20,""),"") -> 1844.18
A20: 45992 | B20: 2473.39 | C20: 0 | D20: =IFERROR(IF(ISBLANK(B20)=FALSE,B20,"")+IF(ISBLANK(C20)=FALSE,C20,""),"") -> 2473.39 | E20: 0 | F20: 0 | G20: 0 | H20: 143000 | I20: =IFERROR(IF(ISBLANK(D20)=FALSE,D20,"")+IF(ISBLANK(E20)=FALSE,E20,"")+IF(ISBLANK(F20)=FALSE,F20,"")+IF(ISBLANK(G20)=FALSE,G20,"")+IF(ISBLANK(H20)=FALSE,H20,""),"") -> 145473.39 | J20: =IFERROR(IF(ISBLANK(I20)=FALSE,I20-I21,""),"") -> 2070.13
A21: 45962 | B21: 2403.26 | C21: 0 | D21: =IFERROR(IF(ISBLANK(B21)=FALSE,B21,"")+IF(ISBLANK(C21)=FALSE,C21,""),"") -> 2403.26 | E21: 0 | F21: 0 | G21: 0 | H21: 141000 | I21: =IFERROR(IF(ISBLANK(D21)=FALSE,D21,"")+IF(ISBLANK(E21)=FALSE,E21,"")+IF(ISBLANK(F21)=FALSE,F21,"")+IF(ISBLANK(G21)=FALSE,G21,"")+IF(ISBLANK(H21)=FALSE,H21,""),"") -> 143403.26 | J21: =IFERROR(IF(ISBLANK(I21)=FALSE,I21-I22,""),"") -> 1846.43
A22: 45931 | B22: 2556.83 | C22: 0 | D22: =IFERROR(IF(ISBLANK(B22)=FALSE,B22,"")+IF(ISBLANK(C22)=FALSE,C22,""),"") -> 2556.83 | E22: 0 | F22: 0 | G22: 0 | H22: 139000 | I22: =IFERROR(IF(ISBLANK(D22)=FALSE,D22,"")+IF(ISBLANK(E22)=FALSE,E22,"")+IF(ISBLANK(F22)=FALSE,F22,"")+IF(ISBLANK(G22)=FALSE,G22,"")+IF(ISBLANK(H22)=FALSE,H22,""),"") -> 141556.83 | J22: =IFERROR(IF(ISBLANK(I22)=FALSE,I22-I23,""),"") -> 1696.41
A23: 45901 | B23: 1860.42 | C23: 0 | D23: =IFERROR(IF(ISBLANK(B23)=FALSE,B23,"")+IF(ISBLANK(C23)=FALSE,C23,""),"") -> 1860.42 | E23: 0 | F23: 0 | G23: 0 | H23: 138000 | I23: =IFERROR(IF(ISBLANK(D23)=FALSE,D23,"")+IF(ISBLANK(E23)=FALSE,E23,"")+IF(ISBLANK(F23)=FALSE,F23,"")+IF(ISBLANK(G23)=FALSE,G23,"")+IF(ISBLANK(H23)=FALSE,H23,""),"") -> 139860.42 | J23: =IFERROR(IF(ISBLANK(I23)=FALSE,I23-I24,""),"") -> 1645.17
A24: 45870 | B24: 1215.25 | C24: 0 | D24: =IFERROR(IF(ISBLANK(B24)=FALSE,B24,"")+IF(ISBLANK(C24)=FALSE,C24,""),"") -> 1215.25 | E24: 0 | F24: 0 | G24: 0 | H24: 137000 | I24: =IFERROR(IF(ISBLANK(D24)=FALSE,D24,"")+IF(ISBLANK(E24)=FALSE,E24,"")+IF(ISBLANK(F24)=FALSE,F24,"")+IF(ISBLANK(G24)=FALSE,G24,"")+IF(ISBLANK(H24)=FALSE,H24,""),"") -> 138215.25 | J24: =IFERROR(IF(ISBLANK(I24)=FALSE,I24-I25,""),"") -> -4.6
A25: 45839 | B25: 1219.85 | C25: 0 | D25: =IFERROR(IF(ISBLANK(B25)=FALSE,B25,"")+IF(ISBLANK(C25)=FALSE,C25,""),"") -> 1219.85 | E25: 0 | F25: 0 | G25: 0 | H25: 137000 | I25: =IFERROR(IF(ISBLANK(D25)=FALSE,D25,"")+IF(ISBLANK(E25)=FALSE,E25,"")+IF(ISBLANK(F25)=FALSE,F25,"")+IF(ISBLANK(G25)=FALSE,G25,"")+IF(ISBLANK(H25)=FALSE,H25,""),"") -> 138219.85 | J25: =IFERROR(IF(ISBLANK(I25)=FALSE,I25-I26,""),"") -> -121.89
A26: 45809 | B26: 1341.74 | C26: 0 | D26: =IFERROR(IF(ISBLANK(B26)=FALSE,B26,"")+IF(ISBLANK(C26)=FALSE,C26,""),"") -> 1341.74 | E26: 0 | F26: 0 | G26: 0 | H26: 137000 | I26: =IFERROR(IF(ISBLANK(D26)=FALSE,D26,"")+IF(ISBLANK(E26)=FALSE,E26,"")+IF(ISBLANK(F26)=FALSE,F26,"")+IF(ISBLANK(G26)=FALSE,G26,"")+IF(ISBLANK(H26)=FALSE,H26,""),"") -> 138341.74 | J26: =IFERROR(IF(ISBLANK(I26)=FALSE,I26-I27,""),"") -> 2203.75
A27: 45778 | B27: 637.99 | C27: 0 | D27: =IFERROR(IF(ISBLANK(B27)=FALSE,B27,"")+IF(ISBLANK(C27)=FALSE,C27,""),"") -> 637.99 | E27: 0 | F27: 0 | G27: 0 | H27: 135500 | I27: =IFERROR(IF(ISBLANK(D27)=FALSE,D27,"")+IF(ISBLANK(E27)=FALSE,E27,"")+IF(ISBLANK(F27)=FALSE,F27,"")+IF(ISBLANK(G27)=FALSE,G27,"")+IF(ISBLANK(H27)=FALSE,H27,""),"") -> 136137.99 | J27: =IFERROR(IF(ISBLANK(I27)=FALSE,I27-I28,""),"") -> 1953.17
A28: 45748 | B28: 684.82 | C28: 0 | D28: =IFERROR(IF(ISBLANK(B28)=FALSE,B28,"")+IF(ISBLANK(C28)=FALSE,C28,""),"") -> 684.82 | E28: 0 | F28: 0 | G28: 0 | H28: 133500 | I28: =IFERROR(IF(ISBLANK(D28)=FALSE,D28,"")+IF(ISBLANK(E28)=FALSE,E28,"")+IF(ISBLANK(F28)=FALSE,F28,"")+IF(ISBLANK(G28)=FALSE,G28,"")+IF(ISBLANK(H28)=FALSE,H28,""),"") -> 134184.82 | J28: =IFERROR(IF(ISBLANK(I28)=FALSE,I28-I29,""),"") -> 1834.54
... A101: 43525 | B101: 1493.8 | C101: 39000 | D101: =IFERROR(IF(ISBLANK(B101)=FALSE,B101,"")+IF(ISBLANK(C101)=FALSE,C101,""),"") -> 40493.8 | E101: 0 | F101: 0 | G101: 0 | H101: 0 | I101: =IFERROR(IF(ISBLANK(D101)=FALSE,D101,"")+IF(ISBLANK(E101)=FALSE,E101,"")+IF(ISBLANK(F101)=FALSE,F101,"")+IF(ISBLANK(G101)=FALSE,G101,"")+IF(ISBLANK(H101)=FALSE,H101,""),"") -> 40493.8 | J101: =IFERROR(IF(ISBLANK(I101)=FALSE,I101-I102,""),"") -> 726.64
A102: 43497 | B102: 1767.16 | C102: 38000 | D102: =IFERROR(IF(ISBLANK(B102)=FALSE,B102,"")+IF(ISBLANK(C102)=FALSE,C102,""),"") -> 39767.16 | E102: 0 | F102: 0 | G102: 0 | H102: 0 | I102: =IFERROR(IF(ISBLANK(D102)=FALSE,D102,"")+IF(ISBLANK(E102)=FALSE,E102,"")+IF(ISBLANK(F102)=FALSE,F102,"")+IF(ISBLANK(G102)=FALSE,G102,"")+IF(ISBLANK(H102)=FALSE,H102,""),"") -> 39767.16 | J102: =IFERROR(IF(ISBLANK(I102)=FALSE,I102-I103,""),"") -> 1177.73 | K102: =SUM(J90:J102) -> 12290.77
A103: 43466 | B103: 1589.43 | C103: 37000 | D103: =IFERROR(IF(ISBLANK(B103)=FALSE,B103,"")+IF(ISBLANK(C103)=FALSE,C103,""),"") -> 38589.43 | E103: 0 | F103: 0 | G103: 0 | H103: 0 | I103: =IFERROR(IF(ISBLANK(D103)=FALSE,D103,"")+IF(ISBLANK(E103)=FALSE,E103,"")+IF(ISBLANK(F103)=FALSE,F103,"")+IF(ISBLANK(G103)=FALSE,G103,"")+IF(ISBLANK(H103)=FALSE,H103,""),"") -> 38589.43 | J103: =IFERROR(IF(ISBLANK(I103)=FALSE,I103-I104,""),"") -> 797.01
A104: 43435 | B104: 1792.42 | C104: 36000 | D104: =IFERROR(IF(ISBLANK(B104)=FALSE,B104,"")+IF(ISBLANK(C104)=FALSE,C104,""),"") -> 37792.42 | E104: 0 | F104: 0 | G104: 0 | H104: 0 | I104: =IFERROR(IF(ISBLANK(D104)=FALSE,D104,"")+IF(ISBLANK(E104)=FALSE,E104,"")+IF(ISBLANK(F104)=FALSE,F104,"")+IF(ISBLANK(G104)=FALSE,G104,"")+IF(ISBLANK(H104)=FALSE,H104,""),"") -> 37792.42 | J104: =IFERROR(IF(ISBLANK(I104)=FALSE,I104-I105,""),"") -> 1017.59
A105: 43405 | B105: 1774.83 | C105: 35000 | D105: =IFERROR(IF(ISBLANK(B105)=FALSE,B105,"")+IF(ISBLANK(C105)=FALSE,C105,""),"") -> 36774.83 | E105: 0 | F105: 0 | G105: 0 | H105: 0 | I105: =IFERROR(IF(ISBLANK(D105)=FALSE,D105,"")+IF(ISBLANK(E105)=FALSE,E105,"")+IF(ISBLANK(F105)=FALSE,F105,"")+IF(ISBLANK(G105)=FALSE,G105,"")+IF(ISBLANK(H105)=FALSE,H105,""),"") -> 36774.83 | J105: =IFERROR(IF(ISBLANK(I105)=FALSE,I105-I106,""),"") -> 930.31
A106: 43374 | B106: 1844.52 | C106: 34000 | D106: =IFERROR(IF(ISBLANK(B106)=FALSE,B106,"")+IF(ISBLANK(C106)=FALSE,C106,""),"") -> 35844.52 | E106: 0 | F106: 0 | G106: 0 | H106: 0 | I106: =IFERROR(IF(ISBLANK(D106)=FALSE,D106,"")+IF(ISBLANK(E106)=FALSE,E106,"")+IF(ISBLANK(F106)=FALSE,F106,"")+IF(ISBLANK(G106)=FALSE,G106,"")+IF(ISBLANK(H106)=FALSE,H106,""),"") -> 35844.52 | J106: =IFERROR(IF(ISBLANK(I106)=FALSE,I106-I107,""),"") -> 1360.79
A107: 43344 | B107: 2483.73 | C107: 32000 | D107: =IFERROR(IF(ISBLANK(B107)=FALSE,B107,"")+IF(ISBLANK(C107)=FALSE,C107,""),"") -> 34483.73 | E107: 0 | F107: 0 | G107: 0 | H107: 0 | I107: =IFERROR(IF(ISBLANK(D107)=FALSE,D107,"")+IF(ISBLANK(E107)=FALSE,E107,"")+IF(ISBLANK(F107)=FALSE,F107,"")+IF(ISBLANK(G107)=FALSE,G107,"")+IF(ISBLANK(H107)=FALSE,H107,""),"") -> 34483.73 | J107: =IFERROR(IF(ISBLANK(I107)=FALSE,I107-I108,""),"") -> 705.07
A108: 43313 | B108: 1778.66 | C108: 32000 | D108: =IFERROR(IF(ISBLANK(B108)=FALSE,B108,"")+IF(ISBLANK(C108)=FALSE,C108,""),"") -> 33778.66 | E108: 0 | F108: 0 | G108: 0 | H108: 0 | I108: =IFERROR(IF(ISBLANK(D108)=FALSE,D108,"")+IF(ISBLANK(E108)=FALSE,E108,"")+IF(ISBLANK(F108)=FALSE,F108,"")+IF(ISBLANK(G108)=FALSE,G108,"")+IF(ISBLANK(H108)=FALSE,H108,""),"") -> 33778.66 | J108: =IFERROR(IF(ISBLANK(I108)=FALSE,I108-I109,""),"") -> 966.65
A109: 43282 | B109: 1812.01 | C109: 31000 | D109: =IFERROR(IF(ISBLANK(B109)=FALSE,B109,"")+IF(ISBLANK(C109)=FALSE,C109,""),"") -> 32812.01 | E109: 0 | F109: 0 | G109: 0 | H109: 0 | I109: =IFERROR(IF(ISBLANK(D109)=FALSE,D109,"")+IF(ISBLANK(E109)=FALSE,E109,"")+IF(ISBLANK(F109)=FALSE,F109,"")+IF(ISBLANK(G109)=FALSE,G109,"")+IF(ISBLANK(H109)=FALSE,H109,""),"") -> 32812.01 | J109: =IFERROR(IF(ISBLANK(I109)=FALSE,I109-I110,""),"") -> 541.72
A110: 43252 | B110: 1270.29 | C110: 31000 | D110: =IFERROR(IF(ISBLANK(B110)=FALSE,B110,"")+IF(ISBLANK(C110)=FALSE,C110,""),"") -> 32270.29 | E110: 0 | F110: 0 | G110: 0 | H110: 0 | I110: =IFERROR(IF(ISBLANK(D110)=FALSE,D110,"")+IF(ISBLANK(E110)=FALSE,E110,"")+IF(ISBLANK(F110)=FALSE,F110,"")+IF(ISBLANK(G110)=FALSE,G110,"")+IF(ISBLANK(H110)=FALSE,H110,""),"") -> 32270.29 | J110: =IFERROR(IF(ISBLANK(I110)=FALSE,I110-I111,""),"") -> 2.46
A111: 43221 | B111: 1267.83 | C111: 31000 | D111: =IFERROR(IF(ISBLANK(B111)=FALSE,B111,"")+IF(ISBLANK(C111)=FALSE,C111,""),"") -> 32267.83 | E111: 0 | F111: 0 | G111: 0 | H111: 0 | I111: =IFERROR(IF(ISBLANK(D111)=FALSE,D111,"")+IF(ISBLANK(E111)=FALSE,E111,"")+IF(ISBLANK(F111)=FALSE,F111,"")+IF(ISBLANK(G111)=FALSE,G111,"")+IF(ISBLANK(H111)=FALSE,H111,""),"") -> 32267.83 | J111: =IFERROR(IF(ISBLANK(I111)=FALSE,I111-I112,""),"") -> -268.61
A112: 43191 | B112: 1536.44 | C112: 31000 | D112: =IFERROR(IF(ISBLANK(B112)=FALSE,B112,"")+IF(ISBLANK(C112)=FALSE,C112,""),"") -> 32536.44 | E112: 0 | F112: 0 | G112: 0 | H112: 0 | I112: =IFERROR(IF(ISBLANK(D112)=FALSE,D112,"")+IF(ISBLANK(E112)=FALSE,E112,"")+IF(ISBLANK(F112)=FALSE,F112,"")+IF(ISBLANK(G112)=FALSE,G112,"")+IF(ISBLANK(H112)=FALSE,H112,""),"") -> 32536.44 | J112: =IFERROR(IF(ISBLANK(I112)=FALSE,I112-I113,""),"") -> 144.23
A113: 43160 | B113: 1392.21 | C113: 31000 | D113: =IFERROR(IF(ISBLANK(B113)=FALSE,B113,"")+IF(ISBLANK(C113)=FALSE,C113,""),"") -> 32392.21 | E113: 0 | F113: 0 | G113: 0 | H113: 0 | I113: =IFERROR(IF(ISBLANK(D113)=FALSE,D113,"")+IF(ISBLANK(E113)=FALSE,E113,"")+IF(ISBLANK(F113)=FALSE,F113,"")+IF(ISBLANK(G113)=FALSE,G113,"")+IF(ISBLANK(H113)=FALSE,H113,""),"") -> 32392.21 | J113: =IFERROR(IF(ISBLANK(I113)=FALSE,I113-I114,""),"") -> 24.63
A114: 43132 | B114: 1367.58 | C114: 31000 | D114: =IFERROR(IF(ISBLANK(B114)=FALSE,B114,"")+IF(ISBLANK(C114)=FALSE,C114,""),"") -> 32367.58 | E114: 0 | F114: 0 | G114: 0 | H114: 0 | I114: =IFERROR(IF(ISBLANK(D114)=FALSE,D114,"")+IF(ISBLANK(E114)=FALSE,E114,"")+IF(ISBLANK(F114)=FALSE,F114,"")+IF(ISBLANK(G114)=FALSE,G114,"")+IF(ISBLANK(H114)=FALSE,H114,""),"") -> 32367.58 | J114: =IFERROR(IF(ISBLANK(I114)=FALSE,I114-I115,""),"") -> 6.34 | K114: =SUM(J103:J114) -> 6228.19
A115: 43101 | B115: 1361.24 | C115: 31000 | D115: =IFERROR(IF(ISBLANK(B115)=FALSE,B115,"")+IF(ISBLANK(C115)=FALSE,C115,""),"") -> 32361.24 | E115: 0 | F115: 0 | G115: 0 | H115: 0 | I115: =IFERROR(IF(ISBLANK(D115)=FALSE,D115,"")+IF(ISBLANK(E115)=FALSE,E115,"")+IF(ISBLANK(F115)=FALSE,F115,"")+IF(ISBLANK(G115)=FALSE,G115,"")+IF(ISBLANK(H115)=FALSE,H115,""),"") -> 32361.24 | J115: =IFERROR(IF(ISBLANK(I115)=FALSE,I115-I116,""),"") -> 709.29
A116: 43070 | B116: 1651.95 | C116: 30000 | D116: =IFERROR(IF(ISBLANK(B116)=FALSE,B116,"")+IF(ISBLANK(C116)=FALSE,C116,""),"") -> 31651.95 | E116: 0 | F116: 0 | G116: 0 | H116: 0 | I116: =IFERROR(IF(ISBLANK(D116)=FALSE,D116,"")+IF(ISBLANK(E116)=FALSE,E116,"")+IF(ISBLANK(F116)=FALSE,F116,"")+IF(ISBLANK(G116)=FALSE,G116,"")+IF(ISBLANK(H116)=FALSE,H116,""),"") -> 31651.95 | J116: =IFERROR(IF(ISBLANK(I116)=FALSE,I116-I117,""),"") -> 999.72
A117: 43040 | B117: 1652.23 | C117: 29000 | D117: =IFERROR(IF(ISBLANK(B117)=FALSE,B117,"")+IF(ISBLANK(C117)=FALSE,C117,""),"") -> 30652.23 | E117: 0 | F117: 0 | G117: 0 | H117: 0 | I117: =IFERROR(IF(ISBLANK(D117)=FALSE,D117,"")+IF(ISBLANK(E117)=FALSE,E117,"")+IF(ISBLANK(F117)=FALSE,F117,"")+IF(ISBLANK(G117)=FALSE,G117,"")+IF(ISBLANK(H117)=FALSE,H117,""),"") -> 30652.23 | J117: =IFERROR(IF(ISBLANK(I117)=FALSE,I117-I118,""),"") -> 108.41
A118: 43009 | B118: 1543.82 | C118: 29000 | D118: =IFERROR(IF(ISBLANK(B118)=FALSE,B118,"")+IF(ISBLANK(C118)=FALSE,C118,""),"") -> 30543.82 | E118: 0 | F118: 0 | G118: 0 | H118: 0 | I118: =IFERROR(IF(ISBLANK(D118)=FALSE,D118,"")+IF(ISBLANK(E118)=FALSE,E118,"")+IF(ISBLANK(F118)=FALSE,F118,"")+IF(ISBLANK(G118)=FALSE,G118,"")+IF(ISBLANK(H118)=FALSE,H118,""),"") -> 30543.82 | J118: =IFERROR(IF(ISBLANK(I118)=FALSE,I118-I119,""),"") -> 683.65
A119: 42979 | B119: 1860.17 | C119: 28000 | D119: =IFERROR(IF(ISBLANK(B119)=FALSE,B119,"")+IF(ISBLANK(C119)=FALSE,C119,""),"") -> 29860.17 | E119: 0 | F119: 0 | G119: 0 | H119: 0 | I119: =IFERROR(IF(ISBLANK(D119)=FALSE,D119,"")+IF(ISBLANK(E119)=FALSE,E119,"")+IF(ISBLANK(F119)=FALSE,F119,"")+IF(ISBLANK(G119)=FALSE,G119,"")+IF(ISBLANK(H119)=FALSE,H119,""),"") -> 29860.17 | J119: =IFERROR(IF(ISBLANK(I119)=FALSE,I119-I120,""),"") -> 530.7
A120: 42948 | B120: 1329.47 | C120: 28000 | D120: =IFERROR(IF(ISBLANK(B120)=FALSE,B120,"")+IF(ISBLANK(C120)=FALSE,C120,""),"") -> 29329.47 | E120: 0 | F120: 0 | G120: 0 | H120: 0 | I120: =IFERROR(IF(ISBLANK(D120)=FALSE,D120,"")+IF(ISBLANK(E120)=FALSE,E120,"")+IF(ISBLANK(F120)=FALSE,F120,"")+IF(ISBLANK(G120)=FALSE,G120,"")+IF(ISBLANK(H120)=FALSE,H120,""),"") -> 29329.47 | J120: =IFERROR(IF(ISBLANK(I120)=FALSE,I120-I121,""),"") -> 447.21
A121: 42917 | B121: 1882.26 | C121: 27000 | D121: =IFERROR(IF(ISBLANK(B121)=FALSE,B121,"")+IF(ISBLANK(C121)=FALSE,C121,""),"") -> 28882.26 | E121: 0 | F121: 0 | G121: 0 | H121: 0 | I121: =IFERROR(IF(ISBLANK(D121)=FALSE,D121,"")+IF(ISBLANK(E121)=FALSE,E121,"")+IF(ISBLANK(F121)=FALSE,F121,"")+IF(ISBLANK(G121)=FALSE,G121,"")+IF(ISBLANK(H121)=FALSE,H121,""),"") -> 28882.26 | J121: =IFERROR(IF(ISBLANK(I121)=FALSE,I121-I122,""),"") -> 289.28
A122: 42887 | B122: 1592.98 | C122: 27000 | D122: =IFERROR(IF(ISBLANK(B122)=FALSE,B122,"")+IF(ISBLANK(C122)=FALSE,C122,""),"") -> 28592.98 | E122: 0 | F122: 0 | G122: 0 | H122: 0 | I122: =IFERROR(IF(ISBLANK(D122)=FALSE,D122,"")+IF(ISBLANK(E122)=FALSE,E122,"")+IF(ISBLANK(F122)=FALSE,F122,"")+IF(ISBLANK(G122)=FALSE,G122,"")+IF(ISBLANK(H122)=FALSE,H122,""),"") -> 28592.98 | J122: =IFERROR(IF(ISBLANK(I122)=FALSE,I122-I123,""),"") -> 619.04
A123: 42856 | B123: 973.94 | C123: 27000 | D123: =IFERROR(IF(ISBLANK(B123)=FALSE,B123,"")+IF(ISBLANK(C123)=FALSE,C123,""),"") -> 27973.94 | E123: 0 | F123: 0 | G123: 0 | H123: 0 | I123: =IFERROR(IF(ISBLANK(D123)=FALSE,D123,"")+IF(ISBLANK(E123)=FALSE,E123,"")+IF(ISBLANK(F123)=FALSE,F123,"")+IF(ISBLANK(G123)=FALSE,G123,"")+IF(ISBLANK(H123)=FALSE,H123,""),"") -> 27973.94 | J123: =IFERROR(IF(ISBLANK(I123)=FALSE,I123-I124,""),"") -> 55.59
A124: 42826 | B124: 918.35 | C124: 27000 | D124: =IFERROR(IF(ISBLANK(B124)=FALSE,B124,"")+IF(ISBLANK(C124)=FALSE,C124,""),"") -> 27918.35 | E124: 0 | F124: 0 | G124: 0 | H124: 0 | I124: =IFERROR(IF(ISBLANK(D124)=FALSE,D124,"")+IF(ISBLANK(E124)=FALSE,E124,"")+IF(ISBLANK(F124)=FALSE,F124,"")+IF(ISBLANK(G124)=FALSE,G124,"")+IF(ISBLANK(H124)=FALSE,H124,""),"") -> 27918.35 | J124: =IFERROR(IF(ISBLANK(I124)=FALSE,I124-I125,""),"") -> 41.44
A125: 42795 | B125: 876.91 | C125: 27000 | D125: =IFERROR(IF(ISBLANK(B125)=FALSE,B125,"")+IF(ISBLANK(C125)=FALSE,C125,""),"") -> 27876.91 | E125: 0 | F125: 0 | G125: 0 | H125: 0 | I125: =IFERROR(IF(ISBLANK(D125)=FALSE,D125,"")+IF(ISBLANK(E125)=FALSE,E125,"")+IF(ISBLANK(F125)=FALSE,F125,"")+IF(ISBLANK(G125)=FALSE,G125,"")+IF(ISBLANK(H125)=FALSE,H125,""),"") -> 27876.91 | J125: =IFERROR(IF(ISBLANK(I125)=FALSE,I125-I126,""),"") -> 26.34
A126: 42767 | B126: 850.57 | C126: 27000 | D126: =IFERROR(IF(ISBLANK(B126)=FALSE,B126,"")+IF(ISBLANK(C126)=FALSE,C126,""),"") -> 27850.57 | E126: 0 | F126: 0 | G126: 0 | H126: 0 | I126: =IFERROR(IF(ISBLANK(D126)=FALSE,D126,"")+IF(ISBLANK(E126)=FALSE,E126,"")+IF(ISBLANK(F126)=FALSE,F126,"")+IF(ISBLANK(G126)=FALSE,G126,"")+IF(ISBLANK(H126)=FALSE,H126,""),"") -> 27850.57 | J126: =IFERROR(IF(ISBLANK(I126)=FALSE,I126-I127,""),"") -> -8.5 | K126: =SUM(J115:J126) -> 4502.17
A127: 42736 | B127: 859.07 | C127: 27000 | D127: =IFERROR(IF(ISBLANK(B127)=FALSE,B127,"")+IF(ISBLANK(C127)=FALSE,C127,""),"") -> 27859.07 | E127: 0 | F127: 0 | G127: 0 | H127: 0 | I127: =IFERROR(IF(ISBLANK(D127)=FALSE,D127,"")+IF(ISBLANK(E127)=FALSE,E127,"")+IF(ISBLANK(F127)=FALSE,F127,"")+IF(ISBLANK(G127)=FALSE,G127,"")+IF(ISBLANK(H127)=FALSE,H127,""),"") -> 27859.07 | J127: =IFERROR(IF(ISBLANK(I127)=FALSE,I127-I128,""),"") -> 876.94
A128: 42705 | B128: 982.13 | C128: 26000 | D128: =IFERROR(IF(ISBLANK(B128)=FALSE,B128,"")+IF(ISBLANK(C128)=FALSE,C128,""),"") -> 26982.13 | E128: 0 | F128: 0 | G128: 0 | H128: 0 | I128: =IFERROR(IF(ISBLANK(D128)=FALSE,D128,"")+IF(ISBLANK(E128)=FALSE,E128,"")+IF(ISBLANK(F128)=FALSE,F128,"")+IF(ISBLANK(G128)=FALSE,G128,"")+IF(ISBLANK(H128)=FALSE,H128,""),"") -> 26982.13 | J128: =IFERROR(IF(ISBLANK(I128)=FALSE,I128-I129,""),"") -> 1171.31
A129: 42675 | B129: 810.82 | C129: 25000 | D129: =IFERROR(IF(ISBLANK(B129)=FALSE,B129,"")+IF(ISBLANK(C129)=FALSE,C129,""),"") -> 25810.82 | E129: 0 | F129: 0 | G129: 0 | H129: 0 | I129: =IFERROR(IF(ISBLANK(D129)=FALSE,D129,"")+IF(ISBLANK(E129)=FALSE,E129,"")+IF(ISBLANK(F129)=FALSE,F129,"")+IF(ISBLANK(G129)=FALSE,G129,"")+IF(ISBLANK(H129)=FALSE,H129,""),"") -> 25810.82 | J129: =IFERROR(IF(ISBLANK(I129)=FALSE,I129-I130,""),"") -> 770.46
A130: 42644 | B130: 1540.36 | C130: 23500 | D130: =IFERROR(IF(ISBLANK(B130)=FALSE,B130,"")+IF(ISBLANK(C130)=FALSE,C130,""),"") -> 25040.36 | E130: 0 | F130: 0 | G130: 0 | H130: 0 | I130: =IFERROR(IF(ISBLANK(D130)=FALSE,D130,"")+IF(ISBLANK(E130)=FALSE,E130,"")+IF(ISBLANK(F130)=FALSE,F130,"")+IF(ISBLANK(G130)=FALSE,G130,"")+IF(ISBLANK(H130)=FALSE,H130,""),"") -> 25040.36 | J130: =IFERROR(IF(ISBLANK(I130)=FALSE,I130-I131,""),"") -> 1089.61
A131: 42614 | B131: 950.75 | C131: 23000 | D131: =IFERROR(IF(ISBLANK(B131)=FALSE,B131,"")+IF(ISBLANK(C131)=FALSE,C131,""),"") -> 23950.75 | E131: 0 | F131: 0 | G131: 0 | H131: 0 | I131: =IFERROR(IF(ISBLANK(D131)=FALSE,D131,"")+IF(ISBLANK(E131)=FALSE,E131,"")+IF(ISBLANK(F131)=FALSE,F131,"")+IF(ISBLANK(G131)=FALSE,G131,"")+IF(ISBLANK(H131)=FALSE,H131,""),"") -> 23950.75 | J131: =IFERROR(IF(ISBLANK(I131)=FALSE,I131-I132,""),"") -> 704.88
A132: 42583 | B132: 1245.87 | C132: 22000 | D132: =IFERROR(IF(ISBLANK(B132)=FALSE,B132,"")+IF(ISBLANK(C132)=FALSE,C132,""),"") -> 23245.87 | E132: 0 | F132: 0 | G132: 0 | H132: 0 | I132: =IFERROR(IF(ISBLANK(D132)=FALSE,D132,"")+IF(ISBLANK(E132)=FALSE,E132,"")+IF(ISBLANK(F132)=FALSE,F132,"")+IF(ISBLANK(G132)=FALSE,G132,"")+IF(ISBLANK(H132)=FALSE,H132,""),"") -> 23245.87 | J132: =IFERROR(IF(ISBLANK(I132)=FALSE,I132-I133,""),"") -> 596.14
A133: 42552 | B133: 1649.73 | C133: 21000 | D133: =IFERROR(IF(ISBLANK(B133)=FALSE,B133,"")+IF(ISBLANK(C133)=FALSE,C133,""),"") -> 22649.73 | E133: 0 | F133: 0 | G133: 0 | H133: 0 | I133: =IFERROR(IF(ISBLANK(D133)=FALSE,D133,"")+IF(ISBLANK(E133)=FALSE,E133,"")+IF(ISBLANK(F133)=FALSE,F133,"")+IF(ISBLANK(G133)=FALSE,G133,"")+IF(ISBLANK(H133)=FALSE,H133,""),"") -> 22649.73 | J133: =IFERROR(IF(ISBLANK(I133)=FALSE,I133-I134,""),"") -> 393.05
A134: 42522 | B134: 1256.68 | C134: 21000 | D134: =IFERROR(IF(ISBLANK(B134)=FALSE,B134,"")+IF(ISBLANK(C134)=FALSE,C134,""),"") -> 22256.68 | E134: 0 | F134: 0 | G134: 0 | H134: 0 | I134: =IFERROR(IF(ISBLANK(D134)=FALSE,D134,"")+IF(ISBLANK(E134)=FALSE,E134,"")+IF(ISBLANK(F134)=FALSE,F134,"")+IF(ISBLANK(G134)=FALSE,G134,"")+IF(ISBLANK(H134)=FALSE,H134,""),"") -> 22256.68 | J134: =IFERROR(IF(ISBLANK(I134)=FALSE,I134-I135,""),"") -> -181.37
A135: 42491 | B135: 2438.05 | C135: 20000 | D135: =IFERROR(IF(ISBLANK(B135)=FALSE,B135,"")+IF(ISBLANK(C135)=FALSE,C135,""),"") -> 22438.05 | E135: 0 | F135: 0 | G135: 0 | H135: 0 | I135: =IFERROR(IF(ISBLANK(D135)=FALSE,D135,"")+IF(ISBLANK(E135)=FALSE,E135,"")+IF(ISBLANK(F135)=FALSE,F135,"")+IF(ISBLANK(G135)=FALSE,G135,"")+IF(ISBLANK(H135)=FALSE,H135,""),"") -> 22438.05 | J135: =IFERROR(IF(ISBLANK(I135)=FALSE,I135-I136,""),"") -> 1610.82
A136: 42461 | B136: 2327.23 | C136: 18500 | D136: =IFERROR(IF(ISBLANK(B136)=FALSE,B136,"")+IF(ISBLANK(C136)=FALSE,C136,""),"") -> 20827.23 | E136: 0 | F136: 0 | G136: 0 | H136: 0 | I136: =IFERROR(IF(ISBLANK(D136)=FALSE,D136,"")+IF(ISBLANK(E136)=FALSE,E136,"")+IF(ISBLANK(F136)=FALSE,F136,"")+IF(ISBLANK(G136)=FALSE,G136,"")+IF(ISBLANK(H136)=FALSE,H136,""),"") -> 20827.23 | J136: =IFERROR(IF(ISBLANK(I136)=FALSE,I136-I137,""),"") -> 940.59
A137: 42430 | B137: 1386.64 | C137: 18500 | D137: =IFERROR(IF(ISBLANK(B137)=FALSE,B137,"")+IF(ISBLANK(C137)=FALSE,C137,""),"") -> 19886.64 | E137: 0 | F137: 0 | G137: 0 | H137: 0 | I137: =IFERROR(IF(ISBLANK(D137)=FALSE,D137,"")+IF(ISBLANK(E137)=FALSE,E137,"")+IF(ISBLANK(F137)=FALSE,F137,"")+IF(ISBLANK(G137)=FALSE,G137,"")+IF(ISBLANK(H137)=FALSE,H137,""),"") -> 19886.64 | J137: =IFERROR(IF(ISBLANK(I137)=FALSE,I137-I138,""),"") -> 923.1
A138: 42401 | B138: 963.54 | C138: 18000 | D138: =IFERROR(IF(ISBLANK(B138)=FALSE,B138,"")+IF(ISBLANK(C138)=FALSE,C138,""),"") -> 18963.54 | E138: 0 | F138: 0 | G138: 0 | H138: 0 | I138: =IFERROR(IF(ISBLANK(D138)=FALSE,D138,"")+IF(ISBLANK(E138)=FALSE,E138,"")+IF(ISBLANK(F138)=FALSE,F138,"")+IF(ISBLANK(G138)=FALSE,G138,"")+IF(ISBLANK(H138)=FALSE,H138,""),"") -> 18963.54 | J138: =IFERROR(IF(ISBLANK(I138)=FALSE,I138-I139,""),"") -> 529.67 | K138: =SUM(J127:J138) -> 9425.2
A139: 42370 | B139: 933.87 | C139: 17500 | D139: =IFERROR(IF(ISBLANK(B139)=FALSE,B139,"")+IF(ISBLANK(C139)=FALSE,C139,""),"") -> 18433.87 | E139: 0 | F139: 0 | G139: 0 | H139: 0 | I139: =IFERROR(IF(ISBLANK(D139)=FALSE,D139,"")+IF(ISBLANK(E139)=FALSE,E139,"")+IF(ISBLANK(F139)=FALSE,F139,"")+IF(ISBLANK(G139)=FALSE,G139,"")+IF(ISBLANK(H139)=FALSE,H139,""),"") -> 18433.87 | J139: =IFERROR(IF(ISBLANK(I139)=FALSE,I139-I140,""),"") -> 468.5
A140: 42339 | B140: 965.37 | C140: 17000 | D140: =IFERROR(IF(ISBLANK(B140)=FALSE,B140,"")+IF(ISBLANK(C140)=FALSE,C140,""),"") -> 17965.37 | E140: 0 | F140: 0 | G140: 0 | H140: 0 | I140: =IFERROR(IF(ISBLANK(D140)=FALSE,D140,"")+IF(ISBLANK(E140)=FALSE,E140,"")+IF(ISBLANK(F140)=FALSE,F140,"")+IF(ISBLANK(G140)=FALSE,G140,"")+IF(ISBLANK(H140)=FALSE,H140,""),"") -> 17965.37 | J140: =IFERROR(IF(ISBLANK(I140)=FALSE,I140-I141,""),"") -> 618.6
A141: 42309 | B141: 846.77 | C141: 16500 | D141: =IFERROR(IF(ISBLANK(B141)=FALSE,B141,"")+IF(ISBLANK(C141)=FALSE,C141,""),"") -> 17346.77 | E141: 0 | F141: 0 | G141: 0 | H141: 0 | I141: =IFERROR(IF(ISBLANK(D141)=FALSE,D141,"")+IF(ISBLANK(E141)=FALSE,E141,"")+IF(ISBLANK(F141)=FALSE,F141,"")+IF(ISBLANK(G141)=FALSE,G141,"")+IF(ISBLANK(H141)=FALSE,H141,""),"") -> 17346.77 | J141: =IFERROR(IF(ISBLANK(I141)=FALSE,I141-I142,""),"") -> 475.5
A142: 42278 | B142: 871.27 | C142: 16000 | D142: =IFERROR(IF(ISBLANK(B142)=FALSE,B142,"")+IF(ISBLANK(C142)=FALSE,C142,""),"") -> 16871.27 | E142: 0 | F142: 0 | G142: 0 | H142: 0 | I142: =IFERROR(IF(ISBLANK(D142)=FALSE,D142,"")+IF(ISBLANK(E142)=FALSE,E142,"")+IF(ISBLANK(F142)=FALSE,F142,"")+IF(ISBLANK(G142)=FALSE,G142,"")+IF(ISBLANK(H142)=FALSE,H142,""),"") -> 16871.27 | J142: =IFERROR(IF(ISBLANK(I142)=FALSE,I142-I143,""),"") -> 494.76
A143: 42248 | B143: 1376.51 | C143: 15000 | D143: =IFERROR(IF(ISBLANK(B143)=FALSE,B143,"")+IF(ISBLANK(C143)=FALSE,C143,""),"") -> 16376.51 | E143: 0 | F143: 0 | G143: 0 | H143: 0 | I143: =IFERROR(IF(ISBLANK(D143)=FALSE,D143,"")+IF(ISBLANK(E143)=FALSE,E143,"")+IF(ISBLANK(F143)=FALSE,F143,"")+IF(ISBLANK(G143)=FALSE,G143,"")+IF(ISBLANK(H143)=FALSE,H143,""),"") -> 16376.51 | J143: =IFERROR(IF(ISBLANK(I143)=FALSE,I143-I144,""),"") -> 7.97
A144: 42217 | B144: 1368.54 | C144: 15000 | D144: =IFERROR(IF(ISBLANK(B144)=FALSE,B144,"")+IF(ISBLANK(C144)=FALSE,C144,""),"") -> 16368.54 | E144: 0 | F144: 0 | G144: 0 | H144: 0 | I144: =IFERROR(IF(ISBLANK(D144)=FALSE,D144,"")+IF(ISBLANK(E144)=FALSE,E144,"")+IF(ISBLANK(F144)=FALSE,F144,"")+IF(ISBLANK(G144)=FALSE,G144,"")+IF(ISBLANK(H144)=FALSE,H144,""),"") -> 16368.54 | J144: =IFERROR(IF(ISBLANK(I144)=FALSE,I144-I145,""),"") -> -99.68
A145: 42186 | B145: 2468.22 | C145: 14000 | D145: =IFERROR(IF(ISBLANK(B145)=FALSE,B145,"")+IF(ISBLANK(C145)=FALSE,C145,""),"") -> 16468.22 | E145: 0 | F145: 0 | G145: 0 | H145: 0 | I145: =IFERROR(IF(ISBLANK(D145)=FALSE,D145,"")+IF(ISBLANK(E145)=FALSE,E145,"")+IF(ISBLANK(F145)=FALSE,F145,"")+IF(ISBLANK(G145)=FALSE,G145,"")+IF(ISBLANK(H145)=FALSE,H145,""),"") -> 16468.22 | J145: =IFERROR(IF(ISBLANK(I145)=FALSE,I145-I146,""),"") -> 966.87
A146: 42156 | B146: 5261.35 | C146: 10240 | D146: =IFERROR(IF(ISBLANK(B146)=FALSE,B146,"")+IF(ISBLANK(C146)=FALSE,C146,""),"") -> 15501.35 | E146: 0 | F146: 0 | G146: 0 | H146: 0 | I146: =IFERROR(IF(ISBLANK(D146)=FALSE,D146,"")+IF(ISBLANK(E146)=FALSE,E146,"")+IF(ISBLANK(F146)=FALSE,F146,"")+IF(ISBLANK(G146)=FALSE,G146,"")+IF(ISBLANK(H146)=FALSE,H146,""),"") -> 15501.35 | J146: =IFERROR(IF(ISBLANK(I146)=FALSE,I146-I147,""),"") -> 500.98
A147: 42125 | B147: 4710.37 | C147: 10290 | D147: =IFERROR(IF(ISBLANK(B147)=FALSE,B147,"")+IF(ISBLANK(C147)=FALSE,C147,""),"") -> 15000.37 | E147: 0 | F147: 0 | G147: 0 | H147: 0 | I147: =IFERROR(IF(ISBLANK(D147)=FALSE,D147,"")+IF(ISBLANK(E147)=FALSE,E147,"")+IF(ISBLANK(F147)=FALSE,F147,"")+IF(ISBLANK(G147)=FALSE,G147,"")+IF(ISBLANK(H147)=FALSE,H147,""),"") -> 15000.37 | J147: =IFERROR(IF(ISBLANK(I147)=FALSE,I147-I148,""),"") -> 522.48
A148: 42095 | B148: 4227.89 | C148: 10250 | D148: =IFERROR(IF(ISBLANK(B148)=FALSE,B148,"")+IF(ISBLANK(C148)=FALSE,C148,""),"") -> 14477.89 | E148: 0 | F148: 0 | G148: 0 | H148: 0 | I148: =IFERROR(IF(ISBLANK(D148)=FALSE,D148,"")+IF(ISBLANK(E148)=FALSE,E148,"")+IF(ISBLANK(F148)=FALSE,F148,"")+IF(ISBLANK(G148)=FALSE,G148,"")+IF(ISBLANK(H148)=FALSE,H148,""),"") -> 14477.89 | J148: =IFERROR(IF(ISBLANK(I148)=FALSE,I148-I149,""),"") -> 435.35
A149: 42064 | B149: 3832.54 | C149: 10210 | D149: =IFERROR(IF(ISBLANK(B149)=FALSE,B149,"")+IF(ISBLANK(C149)=FALSE,C149,""),"") -> 14042.54 | E149: 0 | F149: 0 | G149: 0 | H149: 0 | I149: =IFERROR(IF(ISBLANK(D149)=FALSE,D149,"")+IF(ISBLANK(E149)=FALSE,E149,"")+IF(ISBLANK(F149)=FALSE,F149,"")+IF(ISBLANK(G149)=FALSE,G149,"")+IF(ISBLANK(H149)=FALSE,H149,""),"") -> 14042.54 | J149: =IFERROR(IF(ISBLANK(I149)=FALSE,I149-I150,""),"") -> 533.15
A150: 42036 | B150: 3339.39 | C150: 10170 | D150: =IFERROR(IF(ISBLANK(B150)=FALSE,B150,"")+IF(ISBLANK(C150)=FALSE,C150,""),"") -> 13509.39 | E150: 0 | F150: 0 | G150: 0 | H150: 0 | I150: =IFERROR(IF(ISBLANK(D150)=FALSE,D150,"")+IF(ISBLANK(E150)=FALSE,E150,"")+IF(ISBLANK(F150)=FALSE,F150,"")+IF(ISBLANK(G150)=FALSE,G150,"")+IF(ISBLANK(H150)=FALSE,H150,""),"") -> 13509.39 | J150: =IFERROR(IF(ISBLANK(I150)=FALSE,I150-I151,""),"") -> 442.93 | K150: =SUM(J139:J150) -> 5367.41
A151: 42005 | B151: 2936.46 | C151: 10130 | D151: =IFERROR(IF(ISBLANK(B151)=FALSE,B151,"")+IF(ISBLANK(C151)=FALSE,C151,""),"") -> 13066.46 | E151: 0 | F151: 0 | G151: 0 | H151: 0 | I151: =IFERROR(IF(ISBLANK(D151)=FALSE,D151,"")+IF(ISBLANK(E151)=FALSE,E151,"")+IF(ISBLANK(F151)=FALSE,F151,"")+IF(ISBLANK(G151)=FALSE,G151,"")+IF(ISBLANK(H151)=FALSE,H151,""),"") -> 13066.46 | J151: =IFERROR(IF(ISBLANK(I151)=FALSE,I151-I152,""),"") -> 224.57
A152: 41974 | B152: 2801.89 | C152: 10040 | D152: =IFERROR(IF(ISBLANK(B152)=FALSE,B152,"")+IF(ISBLANK(C152)=FALSE,C152,""),"") -> 12841.89 | E152: 0 | F152: 0 | G152: 0 | H152: 0 | I152: =IFERROR(IF(ISBLANK(D152)=FALSE,D152,"")+IF(ISBLANK(E152)=FALSE,E152,"")+IF(ISBLANK(F152)=FALSE,F152,"")+IF(ISBLANK(G152)=FALSE,G152,"")+IF(ISBLANK(H152)=FALSE,H152,""),"") -> 12841.89 | J152: =IFERROR(IF(ISBLANK(I152)=FALSE,I152-I153,""),"") -> 164.14
A153: 41944 | B153: 2677.75 | C153: 10000 | D153: =IFERROR(IF(ISBLANK(B153)=FALSE,B153,"")+IF(ISBLANK(C153)=FALSE,C153,""),"") -> 12677.75 | E153: 0 | F153: 0 | G153: 0 | H153: 0 | I153: =IFERROR(IF(ISBLANK(D153)=FALSE,D153,"")+IF(ISBLANK(E153)=FALSE,E153,"")+IF(ISBLANK(F153)=FALSE,F153,"")+IF(ISBLANK(G153)=FALSE,G153,"")+IF(ISBLANK(H153)=FALSE,H153,""),"") -> 12677.75 | J153: =IFERROR(IF(ISBLANK(I153)=FALSE,I153-I154,""),"") -> 159.41
A154: 41913 | B154: 2518.34 | C154: 10000 | D154: =IFERROR(IF(ISBLANK(B154)=FALSE,B154,"")+IF(ISBLANK(C154)=FALSE,C154,""),"") -> 12518.34 | E154: 0 | F154: 0 | G154: 0 | H154: 0 | I154: =IFERROR(IF(ISBLANK(D154)=FALSE,D154,"")+IF(ISBLANK(E154)=FALSE,E154,"")+IF(ISBLANK(F154)=FALSE,F154,"")+IF(ISBLANK(G154)=FALSE,G154,"")+IF(ISBLANK(H154)=FALSE,H154,""),"") -> 12518.34 | J154: =IFERROR(IF(ISBLANK(I154)=FALSE,I154-I155,""),"") -> 154.9
A155: 41883 | B155: 2363.44 | C155: 10000 | D155: =IFERROR(IF(ISBLANK(B155)=FALSE,B155,"")+IF(ISBLANK(C155)=FALSE,C155,""),"") -> 12363.44 | E155: 0 | F155: 0 | G155: 0 | H155: 0 | I155: =IFERROR(IF(ISBLANK(D155)=FALSE,D155,"")+IF(ISBLANK(E155)=FALSE,E155,"")+IF(ISBLANK(F155)=FALSE,F155,"")+IF(ISBLANK(G155)=FALSE,G155,"")+IF(ISBLANK(H155)=FALSE,H155,""),"") -> 12363.44 | J155: =IFERROR(IF(ISBLANK(I155)=FALSE,I155-I156,""),"") -> 201.13
A156: 41852 | B156: 9025.96 | C156: 3136.35 | D156: =IFERROR(IF(ISBLANK(B156)=FALSE,B156,"")+IF(ISBLANK(C156)=FALSE,C156,""),"") -> 12162.31 | E156: 0 | F156: 0 | G156: 0 | H156: 0 | I156: =IFERROR(IF(ISBLANK(D156)=FALSE,D156,"")+IF(ISBLANK(E156)=FALSE,E156,"")+IF(ISBLANK(F156)=FALSE,F156,"")+IF(ISBLANK(G156)=FALSE,G156,"")+IF(ISBLANK(H156)=FALSE,H156,""),"") -> 12162.31 | J156: =IFERROR(IF(ISBLANK(I156)=FALSE,I156-I157,""),"") -> 208.32
A157: 41821 | B157: 9022.94 | C157: 2931.05 | D157: =IFERROR(IF(ISBLANK(B157)=FALSE,B157,"")+IF(ISBLANK(C157)=FALSE,C157,""),"") -> 11953.99 | E157: 0 | F157: 0 | G157: 0 | H157: 0 | I157: =IFERROR(IF(ISBLANK(D157)=FALSE,D157,"")+IF(ISBLANK(E157)=FALSE,E157,"")+IF(ISBLANK(F157)=FALSE,F157,"")+IF(ISBLANK(G157)=FALSE,G157,"")+IF(ISBLANK(H157)=FALSE,H157,""),"") -> 11953.99 | J157: =IFERROR(IF(ISBLANK(I157)=FALSE,I157-I158,""),"") -> 694.52
A158: 41791 | B158: 9018.42 | C158: 2241.05 | D158: =IFERROR(IF(ISBLANK(B158)=FALSE,B158,"")+IF(ISBLANK(C158)=FALSE,C158,""),"") -> 11259.47 | E158: 0 | F158: 0 | G158: 0 | H158: 0 | I158: =IFERROR(IF(ISBLANK(D158)=FALSE,D158,"")+IF(ISBLANK(E158)=FALSE,E158,"")+IF(ISBLANK(F158)=FALSE,F158,"")+IF(ISBLANK(G158)=FALSE,G158,"")+IF(ISBLANK(H158)=FALSE,H158,""),"") -> 11259.47 | J158: =IFERROR(IF(ISBLANK(I158)=FALSE,I158-I159,""),"") -> 669.07
A159: 41760 | B159: 9014.05 | C159: 1576.35 | D159: =IFERROR(IF(ISBLANK(B159)=FALSE,B159,"")+IF(ISBLANK(C159)=FALSE,C159,""),"") -> 10590.4 | E159: 0 | F159: 0 | G159: 0 | H159: 0 | I159: =IFERROR(IF(ISBLANK(D159)=FALSE,D159,"")+IF(ISBLANK(E159)=FALSE,E159,"")+IF(ISBLANK(F159)=FALSE,F159,"")+IF(ISBLANK(G159)=FALSE,G159,"")+IF(ISBLANK(H159)=FALSE,H159,""),"") -> 10590.4 | J159: =IFERROR(IF(ISBLANK(I159)=FALSE,I159-I160,""),"") -> 628.61
A160: 41730 | B160: 9009.53 | C160: 952.26 | D160: =IFERROR(IF(ISBLANK(B160)=FALSE,B160,"")+IF(ISBLANK(C160)=FALSE,C160,""),"") -> 9961.79 | E160: 0 | F160: 0 | G160: 0 | H160: 0 | I160: =IFERROR(IF(ISBLANK(D160)=FALSE,D160,"")+IF(ISBLANK(E160)=FALSE,E160,"")+IF(ISBLANK(F160)=FALSE,F160,"")+IF(ISBLANK(G160)=FALSE,G160,"")+IF(ISBLANK(H160)=FALSE,H160,""),"") -> 9961.79 | J160: =IFERROR(IF(ISBLANK(I160)=FALSE,I160-I161,""),"") -> 209.86
A161: 41699 | B161: 9003.72 | C161: 748.21 | D161: =IFERROR(IF(ISBLANK(B161)=FALSE,B161,"")+IF(ISBLANK(C161)=FALSE,C161,""),"") -> 9751.93 | E161: 0 | F161: 0 | G161: 0 | H161: 0 | I161: =IFERROR(IF(ISBLANK(D161)=FALSE,D161,"")+IF(ISBLANK(E161)=FALSE,E161,"")+IF(ISBLANK(F161)=FALSE,F161,"")+IF(ISBLANK(G161)=FALSE,G161,"")+IF(ISBLANK(H161)=FALSE,H161,""),"") -> 9751.93 | J161: =IFERROR(IF(ISBLANK(I161)=FALSE,I161-I162,""),"") -> 598.33
A162: 41671 | B162: 5059.21 | C162: 4094.39 | D162: =IFERROR(IF(ISBLANK(B162)=FALSE,B162,"")+IF(ISBLANK(C162)=FALSE,C162,""),"") -> 9153.6 | E162: 0 | F162: 0 | G162: 0 | H162: 0 | I162: =IFERROR(IF(ISBLANK(D162)=FALSE,D162,"")+IF(ISBLANK(E162)=FALSE,E162,"")+IF(ISBLANK(F162)=FALSE,F162,"")+IF(ISBLANK(G162)=FALSE,G162,"")+IF(ISBLANK(H162)=FALSE,H162,""),"") -> 9153.6 | J162: =IFERROR(IF(ISBLANK(I162)=FALSE,I162-I163,""),"") -> 584.42 | K162: =SUM(J151:J162) -> 4497.28
A163: 41640 | B163: 5056.16 | C163: 3513.02 | D163: =IFERROR(IF(ISBLANK(B163)=FALSE,B163,"")+IF(ISBLANK(C163)=FALSE,C163,""),"") -> 8569.18 | E163: 0 | F163: 0 | G163: 0 | H163: 0 | I163: =IFERROR(IF(ISBLANK(D163)=FALSE,D163,"")+IF(ISBLANK(E163)=FALSE,E163,"")+IF(ISBLANK(F163)=FALSE,F163,"")+IF(ISBLANK(G163)=FALSE,G163,"")+IF(ISBLANK(H163)=FALSE,H163,""),"") -> 8569.18 | J163: =IFERROR(IF(ISBLANK(I163)=FALSE,I163-I164,""),"") -> 546.37
A164: 41609 | B164: 5052.79 | C164: 2970.02 | D164: =IFERROR(IF(ISBLANK(B164)=FALSE,B164,"")+IF(ISBLANK(C164)=FALSE,C164,""),"") -> 8022.81 | E164: 0 | F164: 0 | G164: 0 | H164: 0 | I164: =IFERROR(IF(ISBLANK(D164)=FALSE,D164,"")+IF(ISBLANK(E164)=FALSE,E164,"")+IF(ISBLANK(F164)=FALSE,F164,"")+IF(ISBLANK(G164)=FALSE,G164,"")+IF(ISBLANK(H164)=FALSE,H164,""),"") -> 8022.81 | J164: =IFERROR(IF(ISBLANK(I164)=FALSE,I164-I165,""),"") -> 663.96
A165: 41579 | B165: 5049.42 | C165: 2309.43 | D165: =IFERROR(IF(ISBLANK(B165)=FALSE,B165,"")+IF(ISBLANK(C165)=FALSE,C165,""),"") -> 7358.85 | E165: 0 | F165: 0 | G165: 0 | H165: 0 | I165: =IFERROR(IF(ISBLANK(D165)=FALSE,D165,"")+IF(ISBLANK(E165)=FALSE,E165,"")+IF(ISBLANK(F165)=FALSE,F165,"")+IF(ISBLANK(G165)=FALSE,G165,"")+IF(ISBLANK(H165)=FALSE,H165,""),"") -> 7358.85 | J165: =IFERROR(IF(ISBLANK(I165)=FALSE,I165-I166,""),"") -> 353.16
A166: 41548 | B166: 5046.16 | C166: 1959.53 | D166: =IFERROR(IF(ISBLANK(B166)=FALSE,B166,"")+IF(ISBLANK(C166)=FALSE,C166,""),"") -> 7005.69 | E166: 0 | F166: 0 | G166: 0 | H166: 0 | I166: =IFERROR(IF(ISBLANK(D166)=FALSE,D166,"")+IF(ISBLANK(E166)=FALSE,E166,"")+IF(ISBLANK(F166)=FALSE,F166,"")+IF(ISBLANK(G166)=FALSE,G166,"")+IF(ISBLANK(H166)=FALSE,H166,""),"") -> 7005.69 | J166: =IFERROR(IF(ISBLANK(I166)=FALSE,I166-I167,""),"") -> 192.16
A167: 41518 | B167: 5025 | C167: 1788.53 | D167: =IFERROR(IF(ISBLANK(B167)=FALSE,B167,"")+IF(ISBLANK(C167)=FALSE,C167,""),"") -> 6813.53 | E167: 0 | F167: 0 | G167: 0 | H167: 0 | I167: =IFERROR(IF(ISBLANK(D167)=FALSE,D167,"")+IF(ISBLANK(E167)=FALSE,E167,"")+IF(ISBLANK(F167)=FALSE,F167,"")+IF(ISBLANK(G167)=FALSE,G167,"")+IF(ISBLANK(H167)=FALSE,H167,""),"") -> 6813.53 | J167: =IFERROR(IF(ISBLANK(I167)=FALSE,I167-I168,""),"") -> 198.02
A168: 41487 | B168: 5025 | C168: 1590.51 | D168: =IFERROR(IF(ISBLANK(B168)=FALSE,B168,"")+IF(ISBLANK(C168)=FALSE,C168,""),"") -> 6615.51 | E168: 0 | F168: 0 | G168: 0 | H168: 0 | I168: =IFERROR(IF(ISBLANK(D168)=FALSE,D168,"")+IF(ISBLANK(E168)=FALSE,E168,"")+IF(ISBLANK(F168)=FALSE,F168,"")+IF(ISBLANK(G168)=FALSE,G168,"")+IF(ISBLANK(H168)=FALSE,H168,""),"") -> 6615.51 | J168: =IFERROR(IF(ISBLANK(I168)=FALSE,I168-I169,""),"") -> 225.6
A169: 41456 | B169: 5025 | C169: 1364.91 | D169: =IFERROR(IF(ISBLANK(B169)=FALSE,B169,"")+IF(ISBLANK(C169)=FALSE,C169,""),"") -> 6389.91 | E169: 0 | F169: 0 | G169: 0 | H169: 0 | I169: =IFERROR(IF(ISBLANK(D169)=FALSE,D169,"")+IF(ISBLANK(E169)=FALSE,E169,"")+IF(ISBLANK(F169)=FALSE,F169,"")+IF(ISBLANK(G169)=FALSE,G169,"")+IF(ISBLANK(H169)=FALSE,H169,""),"") -> 6389.91 | J169: =IFERROR(IF(ISBLANK(I169)=FALSE,I169-I170,""),"") -> 165
A170: 41426 | B170: 5025 | C170: 1199.91 | D170: =IFERROR(IF(ISBLANK(B170)=FALSE,B170,"")+IF(ISBLANK(C170)=FALSE,C170,""),"") -> 6224.91 | E170: 0 | F170: 0 | G170: 0 | H170: 0 | I170: =IFERROR(IF(ISBLANK(D170)=FALSE,D170,"")+IF(ISBLANK(E170)=FALSE,E170,"")+IF(ISBLANK(F170)=FALSE,F170,"")+IF(ISBLANK(G170)=FALSE,G170,"")+IF(ISBLANK(H170)=FALSE,H170,""),"") -> 6224.91 | J170: =IFERROR(IF(ISBLANK(I170)=FALSE,I170-I171,""),"") -> -13.48
A171: 41395 | B171: 5025 | C171: 1213.39 | D171: =IFERROR(IF(ISBLANK(B171)=FALSE,B171,"")+IF(ISBLANK(C171)=FALSE,C171,""),"") -> 6238.39 | E171: 0 | F171: 0 | G171: 0 | H171: 0 | I171: =IFERROR(IF(ISBLANK(D171)=FALSE,D171,"")+IF(ISBLANK(E171)=FALSE,E171,"")+IF(ISBLANK(F171)=FALSE,F171,"")+IF(ISBLANK(G171)=FALSE,G171,"")+IF(ISBLANK(H171)=FALSE,H171,""),"") -> 6238.39 | J171: =IFERROR(IF(ISBLANK(I171)=FALSE,I171-I172,""),"") -> 244
A172: 41365 | B172: 5025 | C172: 969.39 | D172: =IFERROR(IF(ISBLANK(B172)=FALSE,B172,"")+IF(ISBLANK(C172)=FALSE,C172,""),"") -> 5994.39 | E172: 0 | F172: 0 | G172: 0 | H172: 0 | I172: =IFERROR(IF(ISBLANK(D172)=FALSE,D172,"")+IF(ISBLANK(E172)=FALSE,E172,"")+IF(ISBLANK(F172)=FALSE,F172,"")+IF(ISBLANK(G172)=FALSE,G172,"")+IF(ISBLANK(H172)=FALSE,H172,""),"") -> 5994.39 | J172: =IFERROR(IF(ISBLANK(I172)=FALSE,I172-I173,""),"") -> 65
A173: 41334 | B173: 5025 | C173: 904.39 | D173: =IFERROR(IF(ISBLANK(B173)=FALSE,B173,"")+IF(ISBLANK(C173)=FALSE,C173,""),"") -> 5929.39 | E173: 0 | F173: 0 | G173: 0 | H173: 0 | I173: =IFERROR(IF(ISBLANK(D173)=FALSE,D173,"")+IF(ISBLANK(E173)=FALSE,E173,"")+IF(ISBLANK(F173)=FALSE,F173,"")+IF(ISBLANK(G173)=FALSE,G173,"")+IF(ISBLANK(H173)=FALSE,H173,""),"") -> 5929.39 | J173: =IFERROR(IF(ISBLANK(I173)=FALSE,I173-I174,""),"") -> 205.01
A174: 41306 | B174: 5025 | C174: 699.38 | D174: =IFERROR(IF(ISBLANK(B174)=FALSE,B174,"")+IF(ISBLANK(C174)=FALSE,C174,""),"") -> 5724.38 | E174: 0 | F174: 0 | G174: 0 | H174: 0 | I174: =IFERROR(IF(ISBLANK(D174)=FALSE,D174,"")+IF(ISBLANK(E174)=FALSE,E174,"")+IF(ISBLANK(F174)=FALSE,F174,"")+IF(ISBLANK(G174)=FALSE,G174,"")+IF(ISBLANK(H174)=FALSE,H174,""),"") -> 5724.38 | J174: =IFERROR(IF(ISBLANK(I174)=FALSE,I174-I175,""),"") -> 192.16
... A177: 41214 | B177: 5025 | C177: 683.02 | D177: =IFERROR(IF(ISBLANK(B177)=FALSE,B177,"")+IF(ISBLANK(C177)=FALSE,C177,""),"") -> 5708.02 | E177: 0 | F177: 0 | G177: 0 | H177: 0 | I177: =IFERROR(IF(ISBLANK(D177)=FALSE,D177,"")+IF(ISBLANK(E177)=FALSE,E177,"")+IF(ISBLANK(F177)=FALSE,F177,"")+IF(ISBLANK(G177)=FALSE,G177,"")+IF(ISBLANK(H177)=FALSE,H177,""),"") -> 5708.02 | J177: =IFERROR(IF(ISBLANK(I177)=FALSE,I177-I178,""),"") -> -38.51
...

Sheet 25 26 Vadillo
C2: Vadillo Asesores
C5: TOTAL | D5: =+J45+J20 -> 13955.07
D7: Bruto | E7: SS | F7: Desemp | H7: IRPF | I7: Sueldo | J7: Ingresado | K7: Diferencia | Q7: 2026
B8: 2026 | C8: 45658 | D8: 2166.6667 | E8: =(D8+G8)*4.85/100 -> 105.08333 | F8: =(D8+G8)*0.0165 -> 35.75 | H8: =D8*$N$14 -> 281.66667 | I8: =D8-E8-H8-F8 -> 1744.1667 | J8: 1744.17 | K8: =IF(ISBLANK(J8)," ",IF(ABS(J8-I8)<0.01,"Correcto ",IF(J8-I8<0,"Faltan","Sobran"))) -> Correcto | L8: =IF(ISBLANK(J8)," ",IF(ABS(J8-I8)<0.01," ",J8-I8)) | R8: L | S8: M | T8: X | U8: J | V8: V | W8: S | X8: D | Y8: L | Z8: M | AA8: X | AB8: J | AC8: V | AD8: S | AE8: D | AF8: L | AG8: M | AH8: X | AI8: J | AJ8: V | AK8: S | AL8: D | AM8: L | AN8: M | AO8: X | AP8: J | AQ8: V | AR8: S | AS8: D | AT8: L | AU8: M | AV8: X | AW8: J | AX8: V | AY8: S | AZ8: D | BA8: L | BB8: M
C9: 45689 | D9: 2166.6667 | E9: =(D9+G9)*4.85/100 -> 105.08333 | F9: =(D9+G9)*0.0165 -> 35.75 | H9: =D9*$N$14 -> 281.66667 | I9: =D9-E9-H9-F9 -> 1744.1667 | J9: 1744.17 | K9: =IF(ISBLANK(J9)," ",IF(ABS(J9-I9)<0.01,"Correcto ",IF(J9-I9<0,"Faltan","Sobran"))) -> Correcto | L9: =IF(ISBLANK(J9)," ",IF(ABS(J9-I9)<0.01," ",J9-I9)) | Q9: ENE | U9: 1 | V9: 2 | W9: 3 | X9: 4 | Y9: 5 | Z9: 6 | AA9: 7 | AB9: 8 | AC9: 9 | AD9: 10 | AE9: 11 | AF9: 12 | AG9: 13 | AH9: 14 | AI9: 15 | AJ9: 16 | AK9: 17 | AL9: 18 | AM9: 19 | AN9: 20 | AO9: 21 | AP9: 22 | AQ9: 23 | AR9: 24 | AS9: 25 | AT9: 26 | AU9: 27 | AV9: 28 | AW9: 29 | AX9: 30 | AY9: 31
C10: 45717 | D10: 2166.6667 | E10: =(D10+G10)*4.85/100 -> 105.08333 | F10: =(D10+G10)*0.0165 -> 35.75 | H10: =D10*$N$14 -> 281.66667 | I10: =D10-E10-H10-F10 -> 1744.1667 | J10: 1744.17 | K10: =IF(ISBLANK(J10)," ",IF(ABS(J10-I10)<0.01,"Correcto ",IF(J10-I10<0,"Faltan","Sobran"))) -> Correcto | L10: =IF(ISBLANK(J10)," ",IF(ABS(J10-I10)<0.01," ",J10-I10)) | Q10: FEB | X10: 1 | Y10: 2 | Z10: 3 | AA10: 4 | AB10: 5 | AC10: 6 | AD10: 7 | AE10: 8 | AF10: 9 | AG10: 10 | AH10: 11 | AI10: 12 | AJ10: 13 | AK10: 14 | AL10: 15 | AM10: 16 | AN10: 17 | AO10: 18 | AP10: 19 | AQ10: 20 | AR10: 21 | AS10: 22 | AT10: 23 | AU10: 24 | AV10: 25 | AW10: 26 | AX10: 27 | AY10: 28
C11: 45748 | D11: 2166.6667 | E11: =(D11+G11)*4.85/100 -> 105.08333 | F11: =(D11+G11)*0.0165 -> 35.75 | H11: =D11*$N$14 -> 281.66667 | I11: =D11-E11-H11-F11 -> 1744.1667 | J11: 1744.17 | K11: =IF(ISBLANK(J11)," ",IF(ABS(J11-I11)<0.01,"Correcto ",IF(J11-I11<0,"Faltan","Sobran"))) -> Correcto | L11: =IF(ISBLANK(J11)," ",IF(ABS(J11-I11)<0.01," ",J11-I11)) | N11: Rend trabajo 2025 | O11: =SUM(D8:D19) -> 25999.996 | Q11: MAR | X11: 1 | Y11: 2 | Z11: 3 | AA11: 4 | AB11: 5 | AC11: 6 | AD11: 7 | AE11: 8 | AF11: 9 | AG11: 10 | AH11: 11 | AI11: 12 | AJ11: 13 | AK11: 14 | AL11: 15 | AM11: 16 | AN11: 17 | AO11: 18 | AP11: 19 | AQ11: 20 | AR11: 21 | AS11: 22 | AT11: 23 | AU11: 24 | AV11: 25 | AW11: 26 | AX11: 27 | AY11: 28 | AZ11: 29 | BA11: 30 | BB11: 31
C12: 45778 | D12: 2166.6667 | E12: =(D12+G12)*4.85/100 -> 105.08333 | F12: =(D12+G12)*0.0165 -> 35.75 | H12: =D12*$N$14 -> 281.66667 | I12: =D12-E12-H12-F12-G12 -> 1744.1667 | K12: =IF(ISBLANK(J12)," ",IF(ABS(J12-I12)<0.01,"Correcto ",IF(J12-I12<0,"Faltan","Sobran"))) | L12: =IF(ISBLANK(J12)," ",IF(ABS(J12-I12)<0.01," ",J12-I12)) | N12: Gastos Deducibles SS | O12: =SUM(E8:F19) -> 1689.9998 | Q12: ABR | T12: 1 | U12: 2 | V12: 3 | W12: 4 | X12: 5 | Y12: 6 | Z12: 7 | AA12: 8 | AB12: 9 | AC12: 10 | AD12: 11 | AE12: 12 | AF12: 13 | AG12: 14 | AH12: 15 | AI12: 16 | AJ12: 17 | AK12: 18 | AL12: 19 | AM12: 20 | AN12: 21 | AO12: 22 | AP12: 23 | AQ12: 24 | AR12: 25 | AS12: 26 | AT12: 27 | AU12: 28 | AV12: 29 | AW12: 30
C13: 45809 | D13: 2166.6667 | E13: =(D13+G13)*4.85/100 -> 105.08333 | F13: =(D13+G13)*0.0165 -> 35.75 | H13: =D13*$N$14 -> 281.66667 | I13: =D13-E13-H13-F13-G13 -> 1744.1667 | K13: =IF(ISBLANK(J13)," ",IF(ABS(J13-I13)<0.01,"Correcto ",IF(J13-I13<0,"Faltan","Sobran"))) | L13: =IF(ISBLANK(J13)," ",IF(ABS(J13-I13)<0.01," ",J13-I13)) | N13: IRPF | O13: =SUM(H8:H19) -> 3379.9995 | Q13: MAY | V13: 1 | W13: 2 | X13: 3 | Y13: 4 | Z13: 5 | AA13: 6 | AB13: 7 | AC13: 8 | AD13: 9 | AE13: 10 | AF13: 11 | AG13: 12 | AH13: 13 | AI13: 14 | AJ13: 15 | AK13: 16 | AL13: 17 | AM13: 18 | AN13: 19 | AO13: 20 | AP13: 21 | AQ13: 22 | AR13: 23 | AS13: 24 | AT13: 25 | AU13: 26 | AV13: 27 | AW13: 28 | AX13: 29 | AY13: 30 | AZ13: 31
C14: 45839 | D14: 2166.6667 | E14: =(D14+G14)*4.85/100 -> 105.08333 | F14: =(D14+G14)*0.0165 -> 35.75 | H14: =D14*$N$14 -> 281.66667 | I14: =D14-E14-H14-F14-G14 -> 1744.1667 | K14: =IF(ISBLANK(J14)," ",IF(ABS(J14-I14)<0.01,"Correcto ",IF(J14-I14<0,"Faltan","Sobran"))) | L14: =IF(ISBLANK(J14)," ",IF(ABS(J14-I14)<0.01," ",J14-I14)) | N14: 0.13 | Q14: JUN | R14: 1 | S14: 2 | T14: 3 | U14: 4 | V14: 5 | W14: 6 | X14: 7 | Y14: 8 | Z14: 9 | AA14: 10 | AB14: 11 | AC14: 12 | AD14: 13 | AE14: 14 | AF14: 15 | AG14: 16 | AH14: 17 | AI14: 18 | AJ14: 19 | AK14: 20 | AL14: 21 | AM14: 22 | AN14: 23 | AO14: 24 | AP14: 25 | AQ14: 26 | AR14: 27 | AS14: 28 | AT14: 29 | AU14: 30
C15: 45870 | D15: 2166.6667 | E15: =(D15+G15)*4.85/100 -> 105.08333 | F15: =(D15+G15)*0.0165 -> 35.75 | H15: =D15*$N$14 -> 281.66667 | I15: =D15-E15-H15-F15-G15 -> 1744.1667 | K15: =IF(ISBLANK(J15)," ",IF(ABS(J15-I15)<0.01,"Correcto ",IF(J15-I15<0,"Faltan","Sobran"))) | L15: =IF(ISBLANK(J15)," ",IF(ABS(J15-I15)<0.01," ",J15-I15)) | Q15: JUL | T15: 1 | U15: 2 | V15: 3 | W15: 4 | X15: 5 | Y15: 6 | Z15: 7 | AA15: 8 | AB15: 9 | AC15: 10 | AD15: 11 | AE15: 12 | AF15: 13 | AG15: 14 | AH15: 15 | AI15: 16 | AJ15: 17 | AK15: 18 | AL15: 19 | AM15: 20 | AN15: 21 | AO15: 22 | AP15: 23 | AQ15: 24 | AR15: 25 | AS15: 26 | AT15: 27 | AU15: 28 | AV15: 29 | AW15: 30 | AX15: 31
C16: 45901 | D16: =1857.14285714286+309.52 -> 2166.6629 | E16: =(D16+G16)*4.85/100 -> 105.08315 | F16: =(D16+G16)*0.0165 -> 35.749937 | H16: =D16*$N$14 -> 281.66617 | I16: =D16-E16-H16-F16-G16 -> 1744.1636 | K16: =IF(ISBLANK(J16)," ",IF(ABS(J16-I16)<0.01,"Correcto ",IF(J16-I16<0,"Faltan","Sobran"))) | L16: =IF(ISBLANK(J16)," ",IF(ABS(J16-I16)<0.01," ",J16-I16)) | N16: VACACIONES | O16: 22+1 | Q16: AGO | W16: 1 | X16: 2 | Y16: 3 | Z16: 4 | AA16: 5 | AB16: 6 | AC16: 7 | AD16: 8 | AE16: 9 | AF16: 10 | AG16: 11 | AH16: 12 | AI16: 13 | AJ16: 14 | AK16: 15 | AL16: 16 | AM16: 17 | AN16: 18 | AO16: 19 | AP16: 20 | AQ16: 21 | AR16: 22 | AS16: 23 | AT16: 24 | AU16: 25 | AV16: 26 | AW16: 27 | AX16: 28 | AY16: 29 | AZ16: 30 | BA16: 31
C17: 45931 | D17: 2166.6667 | E17: =(D17+G17)*4.85/100 -> 105.08333 | F17: =(D17+G17)*0.0165 -> 35.75 | H17: =D17*$N$14 -> 281.66667 | I17: =D17-E17-H17-F17-G17 -> 1744.1667 | K17: =IF(ISBLANK(J17)," ",IF(ABS(J17-I17)<0.01,"Correcto ",IF(J17-I17<0,"Faltan","Sobran"))) | L17: =IF(ISBLANK(J17)," ",IF(ABS(J17-I17)<0.01," ",J17-I17)) | N17: 29jun-2jul | O17: 4 | Q17: SEP | S17: 1 | T17: 2 | U17: 3 | V17: 4 | W17: 5 | X17: 6 | Y17: 7 | Z17: 8 | AA17: 9 | AB17: 10 | AC17: 11 | AD17: 12 | AE17: 13 | AF17: 14 | AG17: 15 | AH17: 16 | AI17: 17 | AJ17: 18 | AK17: 19 | AL17: 20 | AM17: 21 | AN17: 22 | AO17: 23 | AP17: 24 | AQ17: 25 | AR17: 26 | AS17: 27 | AT17: 28 | AU17: 29 | AV17: 30
C18: 45962 | D18: 2166.6667 | E18: =(D18+G18)*4.85/100 -> 105.08333 | F18: =(D18+G18)*0.0165 -> 35.75 | H18: =D18*$N$14 -> 281.66667 | I18: =D18-E18-H18-F18-G18 -> 1744.1667 | K18: =IF(ISBLANK(J18)," ",IF(ABS(J18-I18)<0.01,"Correcto ",IF(J18-I18<0,"Faltan","Sobran"))) | L18: =IF(ISBLANK(J18)," ",IF(ABS(J18-I18)<0.01," ",J18-I18)) | N18: 6-21 ago | O18: 12 | Q18: OCT | U18: 1 | V18: 2 | W18: 3 | X18: 4 | Y18: 5 | Z18: 6 | AA18: 7 | AB18: 8 | AC18: 9 | AD18: 10 | AE18: 11 | AF18: 12 | AG18: 13 | AH18: 14 | AI18: 15 | AJ18: 16 | AK18: 17 | AL18: 18 | AM18: 19 | AN18: 20 | AO18: 21 | AP18: 22 | AQ18: 23 | AR18: 24 | AS18: 25 | AT18: 26 | AU18: 27 | AV18: 28 | AW18: 29 | AX18: 30 | AY18: 31
C19: 45992 | D19: 2166.6667 | E19: =(D19+G19)*4.85/100 -> 105.08333 | F19: =(D19+G19)*0.0165 -> 35.75 | H19: =D19*$N$14 -> 281.66667 | I19: =D19-E19-H19-F19-G19 -> 1744.1667 | K19: =IF(ISBLANK(J19)," ",IF(ABS(J19-I19)<0.01,"Correcto ",IF(J19-I19<0,"Faltan","Sobran"))) | L19: =IF(ISBLANK(J19)," ",IF(ABS(J19-I19)<0.01," ",J19-I19)) | N19: 14 21 septiembre | O19: 6 | Q19: NOV | X19: 1 | Y19: 2 | Z19: 3 | AA19: 4 | AB19: 5 | AC19: 6 | AD19: 7 | AE19: 8 | AF19: 9 | AG19: 10 | AH19: 11 | AI19: 12 | AJ19: 13 | AK19: 14 | AL19: 15 | AM19: 16 | AN19: 17 | AO19: 18 | AP19: 19 | AQ19: 20 | AR19: 21 | AS19: 22 | AT19: 23 | AU19: 24 | AV19: 25 | AW19: 26 | AX19: 27 | AY19: 28 | AZ19: 29 | BA19: 30
D20: =SUM(D8:D19) -> 25999.996 | E20: =SUM(E8:E19) -> 1260.9998 | F20: =SUM(F8:F19) -> 428.99994 | G20: =SUM(G8:G19) -> 0 | H20: =SUM(H8:H19) -> 3379.9995 | I20: =SUM(I8:I19) -> 20929.997 | J20: =SUM(J8:J19) -> 6976.68 | N20: Disfrutadas | O20: =SUM(O17:O19) -> 22 | Q20: DIC | S20: 1 | T20: 2 | U20: 3 | V20: 4 | W20: 5 | X20: 6 | Y20: 7 | Z20: 8 | AA20: 9 | AB20: 10 | AC20: 11 | AD20: 12 | AE20: 13 | AF20: 14 | AG20: 15 | AH20: 16 | AI20: 17 | AJ20: 18 | AK20: 19 | AL20: 20 | AM20: 21 | AN20: 22 | AO20: 23 | AP20: 24 | AQ20: 25 | AR20: 26 | AS20: 27 | AT20: 28 | AU20: 29 | AV20: 30 | AW20: 31
D21: =D20-E20-H20-F20-G20 -> 20929.997 | N21: =+IF(O20<O15,"Por coger",IF(O20>O15,"Del año que viene"," ")) -> Del año que viene
D29: Bruto | E29: SS | F29: Desemp | H29: IRPF | I29: Sueldo | J29: Ingresado | K29: Diferencia | Q29: 2025
B30: 2025 | C30: 45658 | I30: =D30-E30-H30-F30 -> 0 | K30: =IF(ISBLANK(J30)," ",IF(ABS(J30-I30)<0.01,"Correcto ",IF(J30-I30<0,"Faltan","Sobran"))) | L30: =IF(ISBLANK(J30)," ",IF(ABS(J30-I30)<0.01," ",J30-I30)) | R30: L | S30: M | T30: X | U30: J | V30: V | W30: S | X30: D | Y30: L | Z30: M | AA30: X | AB30: J | AC30: V | AD30: S | AE30: D | AF30: L | AG30: M | AH30: X | AI30: J | AJ30: V | AK30: S | AL30: D | AM30: L | AN30: M | AO30: X | AP30: J | AQ30: V | AR30: S | AS30: D | AT30: L | AU30: M | AV30: X | AW30: J | AX30: V | AY30: S | AZ30: D | BA30: L | BB30: M
C31: 45689 | I31: =D31-E31-H31-F31 -> 0 | K31: =IF(ISBLANK(J31)," ",IF(ABS(J31-I31)<0.01,"Correcto ",IF(J31-I31<0,"Faltan","Sobran"))) | L31: =IF(ISBLANK(J31)," ",IF(ABS(J31-I31)<0.01," ",J31-I31)) | Q31: SEP | R31: 1 | S31: 2 | T31: 3 | U31: 4 | V31: 5 | W31: 6 | X31: 7 | Y31: 8 | Z31: 9 | AA31: 10 | AB31: 11 | AC31: 12 | AD31: 13 | AE31: 14 | AF31: 15 | AG31: 16 | AH31: 17 | AI31: 18 | AJ31: 19 | AK31: 20 | AL31: 21 | AM31: 22 | AN31: 23 | AO31: 24 | AP31: 25 | AQ31: 26 | AR31: 27 | AS31: 28 | AT31: 29 | AU31: 30
C32: 45717 | I32: =D32-E32-H32-F32 -> 0 | K32: =IF(ISBLANK(J32)," ",IF(ABS(J32-I32)<0.01,"Correcto ",IF(J32-I32<0,"Faltan","Sobran"))) | L32: =IF(ISBLANK(J32)," ",IF(ABS(J32-I32)<0.01," ",J32-I32)) | Q32: OCT | T32: 1 | U32: 2 | V32: 3 | W32: 4 | X32: 5 | Y32: 6 | Z32: 7 | AA32: 8 | AB32: 9 | AC32: 10 | AD32: 11 | AE32: 12 | AF32: 13 | AG32: 14 | AH32: 15 | AI32: 16 | AJ32: 17 | AK32: 18 | AL32: 19 | AM32: 20 | AN32: 21 | AO32: 22 | AP32: 23 | AQ32: 24 | AR32: 25 | AS32: 26 | AT32: 27 | AU32: 28 | AV32: 29 | AW32: 30 | AX32: 31
C33: 45748 | I33: =D33-E33-H33-F33 -> 0 | K33: =IF(ISBLANK(J33)," ",IF(ABS(J33-I33)<0.01,"Correcto ",IF(J33-I33<0,"Faltan","Sobran"))) | L33: =IF(ISBLANK(J33)," ",IF(ABS(J33-I33)<0.01," ",J33-I33)) | N33: Rend trabajo 2025 | O33: =SUM(D30:D43) -> 8666.6629 | Q33: NOV | W33: 1 | X33: 2 | Y33: 3 | Z33: 4 | AA33: 5 | AB33: 6 | AC33: 7 | AD33: 8 | AE33: 9 | AF33: 10 | AG33: 11 | AH33: 12 | AI33: 13 | AJ33: 14 | AK33: 15 | AL33: 16 | AM33: 17 | AN33: 18 | AO33: 19 | AP33: 20 | AQ33: 21 | AR33: 22 | AS33: 23 | AT33: 24 | AU33: 25 | AV33: 26 | AW33: 27 | AX33: 28 | AY33: 29 | AZ33: 30
C34: 45778 | I34: =D34-E34-H34-F34-G34 -> 0 | K34: =IF(ISBLANK(J34)," ",IF(ABS(J34-I34)<0.01,"Correcto ",IF(J34-I34<0,"Faltan","Sobran"))) | L34: =IF(ISBLANK(J34)," ",IF(ABS(J34-I34)<0.01," ",J34-I34)) | N34: Gastos Deducibles SS | O34: =SUM(E30:F43) -> 561.59975 | Q34: DIC | R34: 1 | S34: 2 | T34: 3 | U34: 4 | V34: 5 | W34: 6 | X34: 7 | Y34: 8 | Z34: 9 | AA34: 10 | AB34: 11 | AC34: 12 | AD34: 13 | AE34: 14 | AF34: 15 | AG34: 16 | AH34: 17 | AI34: 18 | AJ34: 19 | AK34: 20 | AL34: 21 | AM34: 22 | AN34: 23 | AO34: 24 | AP34: 25 | AQ34: 26 | AR34: 27 | AS34: 28 | AT34: 29 | AU34: 30 | AV34: 31
C35: 45809 | I35: =D35-E35-H35-F35-G35 -> 0 | K35: =IF(ISBLANK(J35)," ",IF(ABS(J35-I35)<0.01,"Correcto ",IF(J35-I35<0,"Faltan","Sobran"))) | L35: =IF(ISBLANK(J35)," ",IF(ABS(J35-I35)<0.01," ",J35-I35)) | N35: IRPF | O35: =SUM(H30:H43) -> 1126.6662
I36: =D36-E36-H36-F36-G36 -> 0 | K36: =IF(ISBLANK(J36)," ",IF(ABS(J36-I36)<0.01,"Correcto ",IF(J36-I36<0,"Faltan","Sobran"))) | L36: =IF(ISBLANK(J36)," ",IF(ABS(J36-I36)<0.01," ",J36-I36)) | N36: 0.13 | R36: Del Octubre a Mayo de 8:30-14:30 - 15:00-17:30
C37: 45839 | I37: =D37-E37-H37-F37-G37 -> 0 | K37: =IF(ISBLANK(J37)," ",IF(ABS(J37-I37)<0.01,"Correcto ",IF(J37-I37<0,"Faltan","Sobran"))) | L37: =IF(ISBLANK(J37)," ",IF(ABS(J37-I37)<0.01," ",J37-I37)) | R37: De Junio a Septiembre de 8 a 15
C38: 45870 | I38: =D38-E38-H38-F38-G38 -> 0 | K38: =IF(ISBLANK(J38)," ",IF(ABS(J38-I38)<0.01,"Correcto ",IF(J38-I38<0,"Faltan","Sobran"))) | L38: =IF(ISBLANK(J38)," ",IF(ABS(J38-I38)<0.01," ",J38-I38))
C39: 45901 | D39: =1857.14285714286+309.52 -> 2166.6629 | E39: =(D39+G39)*0.0483 -> 104.64982 | F39: =(D39+G39)*0.0165 -> 35.749937 | H39: =D39*$N$36 -> 281.66617 | I39: =D39-E39-H39-F39-G39 -> 1744.5969 | J39: 1744.59 | K39: =IF(ISBLANK(J39)," ",IF(ABS(J39-I39)<0.01,"Correcto ",IF(J39-I39<0,"Faltan","Sobran"))) -> Correcto | L39: =IF(ISBLANK(J39)," ",IF(ABS(J39-I39)<0.01," ",J39-I39)) | N39: VACACIONES | O39: =22/12*4 -> 7.3333333
C40: 45931 | D40: 2166.6667 | E40: =(D40+G40)*0.0483 -> 104.65 | F40: =(D40+G40)*0.0165 -> 35.75 | H40: =D40*$N$36 -> 281.66667 | I40: =D40-E40-H40-F40-G40 -> 1744.6 | J40: 1744.6 | K40: =IF(ISBLANK(J40)," ",IF(ABS(J40-I40)<0.01,"Correcto ",IF(J40-I40<0,"Faltan","Sobran"))) -> Correcto | L40: =IF(ISBLANK(J40)," ",IF(ABS(J40-I40)<0.01," ",J40-I40)) | N40: 9 12 diciembre | O40: 4
C41: 45962 | D41: 2166.6667 | E41: =(D41+G41)*0.0483 -> 104.65 | F41: =(D41+G41)*0.0165 -> 35.75 | H41: =D41*$N$36 -> 281.66667 | I41: =D41-E41-H41-F41-G41 -> 1744.6 | J41: 1744.6 | K41: =IF(ISBLANK(J41)," ",IF(ABS(J41-I41)<0.01,"Correcto ",IF(J41-I41<0,"Faltan","Sobran"))) -> Correcto | L41: =IF(ISBLANK(J41)," ",IF(ABS(J41-I41)<0.01," ",J41-I41)) | N41: 26 de diciembre | O41: 1
C42: 45992 | D42: 2166.6667 | E42: =(D42+G42)*0.0483 -> 104.65 | F42: =(D42+G42)*0.0165 -> 35.75 | H42: =D42*$N$36 -> 281.66667 | I42: =D42-E42-H42-F42-G42 -> 1744.6 | J42: 1744.6 | K42: =IF(ISBLANK(J42)," ",IF(ABS(J42-I42)<0.01,"Correcto ",IF(J42-I42<0,"Faltan","Sobran"))) -> Correcto | L42: =IF(ISBLANK(J42)," ",IF(ABS(J42-I42)<0.01," ",J42-I42)) | N42: 29 30 diciembre | O42: 2
K43: =IF(ISBLANK(J43)," ",IF(ABS(J43-I43)<0.01,"Correcto ",IF(J43-I43<0,"Faltan","Sobran"))) | L43: =IF(ISBLANK(J43)," ",IF(J43-I43<0.01," ",J43-I43))
K44: =IF(ISBLANK(J44)," ",IF(ABS(J44-I44)<0.01,"Correcto ",IF(J44-I44<0,"Faltan","Sobran"))) | L44: =IF(ISBLANK(J44)," ",IF(J44-I44<0.01," ",J44-I44)) | N44: Disfrutadas | O44: =SUM(O40:O43) -> 7
D45: =SUM(D30:D44) -> 8666.6629 | E45: =SUM(E30:E44) -> 418.59982 | F45: =SUM(F30:F44) -> 142.99994 | G45: =SUM(G30:G44) -> 0 | H45: =SUM(H30:H44) -> 1126.6662 | I45: =SUM(I30:I44) -> 6978.3969 | J45: =SUM(J30:J44) -> 6978.39 | N45: =+IF(O44<O39,"Por coger",IF(O44>O39,"Del año que viene"," ")) -> Por coger
D46: =D45-E45-H45-F45-G45 -> 6978.3969

Sheet Intereses cuentas
C2: EVO | H2: Banc Sabadell | M2: N26 | R2: Bruto | S2: TOTAL
C3: Intereses | D3: Retención | E3: Neto | F3: Ingresado | H3: Intereses | I3: Retención | J3: Neto | K3: Ingresado | M3: Intereses | N3: Retención | O3: Neto | P3: Ingresado
A4: 2023 | B4: 45139 | C4: 21.3 | D4: =C4*0.19 -> 4.047 | E4: =C4-D4 -> 17.253 | F4: 17.25 | R4: =+C4+H4+M4 -> 21.3 | S4: =SUM(E4,J4,O4) -> 17.253 | U4: =F4+K4+P4 -> 17.25 | Y4: 2023 | Z4: Intereses | AA4: =SUM(C4:C8,H4:H8,M4:M8) -> 566.45481
B5: 45170 | C5: 63.703704 | D5: =C5*0.19 -> 12.103704 | E5: =C5-D5 -> 51.6 | F5: 51.6 | R5: =+C5+H5+M5 -> 63.703704 | S5: =SUM(E5,J5,O5) -> 51.6 | U5: =F5+K5+P5 -> 51.6 | Z5: Retención | AA5: =SUM(D4:D8,I4:I8,N4:N8) -> 107.62641 | AB5: =+AA4-AA5 -> 458.8284
B6: 45200 | C6: 61.641975 | D6: =C6*0.19 -> 11.711975 | E6: =C6-D6 -> 49.93 | F6: 49.93 | H6: 26.71 | I6: =H6*0.19 -> 5.0749 | J6: =H6-I6 -> 21.6351 | K6: 21.64 | M6: 26.01 | N6: =M6*0.19 -> 4.9419 | O6: =M6-N6 -> 21.0681 | P6: 21.07 | R6: =+C6+H6+M6 -> 114.36198 | S6: =SUM(E6,J6,O6) -> 92.6332 | U6: =F6+K6+P6 -> 92.64
B7: 45231 | C7: 61.643836 | D7: =C7*0.19 -> 11.712329 | E7: =C7-D7 -> 49.931507 | F7: 49.93 | H7: 63.7 | I7: =H7*0.19 -> 12.103 | J7: =H7-I7 -> 51.597 | K7: 51.6 | M7: =29000*0.0226/12 -> 54.616667 | N7: =M7*0.19 -> 10.377167 | O7: =M7-N7 -> 44.2395 | P7: 45.08 | R7: =+C7+H7+M7 -> 179.9605 | S7: =SUM(E7,J7,O7) -> 145.76801 | U7: =F7+K7+P7 -> 146.61
B8: 45261 | C8: 63.69863 | D8: =C8*0.19 -> 12.10274 | E8: =C8-D8 -> 51.59589 | F8: 51.6 | H8: 61.64 | I8: =H8*0.19 -> 11.7116 | J8: =H8-I8 -> 49.9284 | K8: 49.93 | M8: 61.79 | N8: =M8*0.19 -> 11.7401 | O8: =M8-N8 -> 50.0499 | P8: 50.05 | R8: =+C8+H8+M8 -> 187.12863 | S8: =SUM(E8,J8,O8) -> 151.57419 | T8: =SUM(S4:S8) -> 458.8284 | U8: =F8+K8+P8 -> 151.58 | V8: =SUM(U4:U8) -> 459.68
C10: EVO | H10: Banc Sabadell | M10: N26 | Y10: 2024 | Z10: Intereses | AA10: =SUM(C12:C19,H12:H19,M12:M23) -> 3132.2744
C11: Intereses | D11: Retención | E11: Neto | F11: Ingresado | H11: Intereses | I11: Retención | J11: Neto | K11: Ingresado | M11: Intereses | N11: Retención | O11: Neto | P11: Ingresado | Z11: Retención | AA11: =SUM(D12:D19,I12:I19,N12:N23) -> 595.13214 | AB11: =+AA10-AA11 -> 2537.1423
A12: 2024 | B12: 45292 | C12: 63.63 | D12: =C12*0.19 -> 12.0897 | E12: =C12-D12 -> 51.5403 | F12: 51.54 | H12: 63.7 | I12: =H12*0.19 -> 12.103 | J12: =H12-I12 -> 51.597 | K12: 51.6 | M12: 67.06 | N12: =M12*0.19 -> 12.7414 | O12: =M12-N12 -> 54.3186 | P12: 54.32 | R12: =+C12+H12+M12 -> 194.39 | S12: =SUM(E12,J12,O12) -> 157.4559 | U12: =F12+K12+P12 -> 157.46
B13: 45323 | C13: 59.432099 | D13: =C13*0.19 -> 11.292099 | E13: =C13-D13 -> 48.14 | F13: 48.14 | H13: 63.7 | I13: =H13*0.19 -> 12.103 | J13: =H13-I13 -> 51.597 | K13: 51.6 | M13: 66.14 | N13: =M13*0.19 -> 12.5666 | O13: =M13-N13 -> 53.5734 | P13: 53.57 | R13: =+C13+H13+M13 -> 189.2721 | S13: =SUM(E13,J13,O13) -> 153.3104 | U13: =F13+K13+P13 -> 153.31
B14: 45352 | C14: 63.518519 | D14: =C14*0.19 -> 12.068519 | E14: =C14-D14 -> 51.45 | F14: 51.45 | H14: 59.59 | I14: =H14*0.19 -> 11.3221 | J14: =H14-I14 -> 48.2679 | K14: 48.27 | M14: 50.567901 | N14: =M14*0.19 -> 9.6079012 | O14: =M14-N14 -> 40.96 | P14: =20.96+20 -> 40.96 | R14: =+C14+H14+M14 -> 173.67642 | S14: =SUM(E14,J14,O14) -> 140.6779 | U14: =F14+K14+P14 -> 140.68
B15: 45383 | C15: 61.481481 | D15: =C15*0.19 -> 11.681481 | E15: =C15-D15 -> 49.8 | F15: 49.8 | H15: 63.7 | I15: =H15*0.19 -> 12.103 | J15: =H15-I15 -> 51.597 | K15: 51.6 | M15: 78.36 | N15: =M15*0.19 -> 14.8884 | O15: =M15-N15 -> 63.4716 | P15: 63.47 | R15: =+C15+H15+M15 -> 203.54148 | S15: =SUM(E15,J15,O15) -> 164.8686 | U15: =F15+K15+P15 -> 164.87 | Y15: 2025 | Z15: Intereses | AA15: =SUM(M27:M29,H27:H30,C27:C38)+C42+40 -> 3348.6303
B16: 45413 | C16: 63.518519 | D16: =C16*0.19 -> 12.068519 | E16: =C16-D16 -> 51.45 | F16: 51.45 | H16: 61.64 | I16: =H16*0.19 -> 11.7116 | J16: =H16-I16 -> 49.9284 | K16: 49.93 | M16: 82.91358 | N16: =M16*0.19 -> 15.75358 | O16: =M16-N16 -> 67.16 | P16: 67.16 | R16: =+C16+H16+M16 -> 208.0721 | S16: =SUM(E16,J16,O16) -> 168.5384 | U16: =F16+K16+P16 -> 168.54 | Z16: Retención | AA16: =SUM(N27:N29,I27:I30,D27:D38)+D42+40*19% -> 636.23426 | AB16: =+AA15-AA16 -> 2712.396
B17: 45444 | C17: 10.654321 | D17: =C17*0.19 -> 2.024321 | E17: =C17-D17 -> 8.63 | F17: 8.63 | H17: 63.7 | I17: =H17*0.19 -> 12.103 | J17: =H17-I17 -> 51.597 | K17: 51.6 | M17: 72.925926 | N17: =M17*0.19 -> 13.855926 | O17: =M17-N17 -> 59.07 | P17: 59.07 | R17: =+C17+H17+M17 -> 147.28025 | S17: =SUM(E17,J17,O17) -> 119.297 | U17: =F17+K17+P17 -> 119.3
B18: 45474 | H18: 10.27 | I18: =H18*0.19 -> 1.9513 | J18: =H18-I18 -> 8.3187 | K18: 8.32 | M18: 284.92593 | N18: =M18*0.19 -> 54.135926 | O18: =M18-N18 -> 230.79 | P18: 230.79 | R18: =+C18+H18+M18 -> 295.19593 | S18: =SUM(E18,J18,O18) -> 239.1087 | U18: =K18+P18 -> 239.11
B19: 45505 | M19: 369.50617 | N19: =M19*0.19 -> 70.206173 | O19: =M19-N19 -> 299.3 | P19: 299.3 | R19: =+C19+H19+M19 -> 369.50617 | S19: =SUM(E19,J19,O19) -> 299.3 | U19: =P19 -> 299.3
B20: 45536 | M20: 381.18 | N20: =M20*0.19 -> 72.4242 | O20: =M20-N20 -> 308.7558 | P20: 308.76 | R20: =+C20+H20+M20 -> 381.18 | S20: =SUM(E20,J20,O20) -> 308.7558 | U20: =+P20 -> 308.76 | Y20: 2026 | Z20: Intereses | AA20: =SUM(C43:C54)+20 -> 3560.1437
B21: 45566 | M21: 373.57 | N21: =M21*0.19 -> 70.9783 | O21: =M21-N21 -> 302.5917 | P21: 302.59 | R21: =+C21+H21+M21 -> 373.57 | S21: =SUM(E21,J21,O21) -> 302.5917 | U21: =P21 -> 302.59 | Z21: Retención | AA21: =SUM(D43:D54)+20*0.19 -> 676.4273 | AB21: =+AA20-AA21 -> 2883.7164
B22: 45597 | H22: =SUM(H4:H21) -> 538.35 | I22: =SUM(I5:I21) -> 102.2865 | J22: =SUM(J5:J21) -> 436.0635 | K22: =SUM(K6:K21) -> 436.09 | M22: =294.37 -> 294.37 | N22: =M22*0.19 -> 55.9303 | O22: =M22-N22 -> 238.4397 | P22: 238.44 | R22: =+M22 -> 294.37 | S22: =SUM(,O22) -> 238.4397 | U22: =P22 -> 238.44
B23: 45627 | M23: 302.22 | N23: =M23*0.19 -> 57.4218 | O23: =M23-N23 -> 244.7982 | P23: 244.8 | R23: =+C23+H23+M23 -> 302.22 | S23: =SUM(E23,J23,O23) -> 244.7982 | T23: =SUM(S12:S23) -> 2537.1423 | U23: =+P23 -> 244.8 | V23: =SUM(U12:U23) -> 2537.16
C25: Bankinter | H25: B100 | M25: N26
C26: Intereses | D26: Retención | E26: Neto | F26: Ingresado | H26: Intereses | I26: Retención | J26: Neto | K26: Ingresado | M26: Intereses | N26: Retención | O26: Neto | P26: Ingresado
A27: 2025 | B27: 45658 | H27: 36.58 | I27: =+H27*0.19 -> 6.9502 | J27: =H27-I27 -> 29.6298 | K27: 29.63 | M27: 319.85 | N27: =M27*0.19 -> 60.7715 | O27: =+M27-N27 -> 259.0785 | P27: 259.08 | R27: =+C27+H27+M27 -> 356.43 | S27: =SUM(E27,J27,O27) -> 288.7083 | U27: =P27+K27 -> 288.71 | AB27: bruto | AC27: retencion
B28: 45689 | H28: 102.41 | I28: =+H28*0.19 -> 19.4579 | J28: =H28-I28 -> 82.9521 | K28: 82.95 | M28: =((128000-50000)*0.025/12/30*23)+(128000*0.028/12/30*7) -> 194.27222 | N28: =M28*0.19 -> 36.911722 | O28: =+M28-N28 -> 157.3605 | P28: 160.19 | R28: =+C28+H28+M28 -> 296.68222 | S28: =SUM(E28,J28,O28) -> 240.3126 | U28: =P28+K28 -> 243.14 | AA28: n26 | AB28: 541.57 | AC28: 102.89
B29: 45717 | C29: 161.65432 | D29: =+C29*0.19 -> 30.714321 | E29: =+C29-D29 -> 130.94 | F29: =119.29+11.65 -> 130.94 | H29: 102.41 | I29: =+H29*0.19 -> 19.4579 | J29: =H29-I29 -> 82.9521 | K29: 82.95 | M29: 27.45 | N29: 5.21 | O29: =+M29-N29 -> 22.24 | P29: 19.41 | R29: =+C29+H29+M29 -> 291.51432 | S29: =SUM(E29,J29,O29) -> 236.1321 | U29: =P29+K29+F29 -> 233.3 | AA29: bankinter | AB29: 2164.51 | AC29: 411.19
B30: 45748 | C30: =118840*0.0247/12 -> 244.61233 | D30: =+C30*0.19 -> 46.476343 | E30: =+C30-D30 -> 198.13599 | F30: 198.14 | H30: 14.28 | I30: =+H30*0.19 -> 2.7132 | J30: =H30-I30 -> 11.5668 | K30: 11.57 | R30: =+C30+H30 -> 258.89233 | S30: =SUM(E30,J30) -> 209.70279 | U30: =K30+F30 -> 209.71 | AA30: openbank | AB30: =+C42 -> 338.13 | AC30: =+D42 -> 64.2447
B31: 45778 | C31: 272.49 | D31: =+C31*0.19 -> 51.7731 | E31: =+C31-D31 -> 220.7169 | F31: 220.72 | R31: =+C31+H31 -> 272.49 | S31: =SUM(E31,J31) -> 220.7169 | U31: =F31 -> 220.72 | AA31: b100 | AB31: =+H33 -> 255.68 | AC31: =+I33 -> 48.5792
B32: 45809 | C32: 285.82 | D32: =+C32*0.19 -> 54.3058 | E32: =+C32-D32 -> 231.5142 | F32: 231.51 | R32: =+C32 -> 285.82 | S32: =SUM(E32,J32) -> 231.5142 | U32: =F32 -> 231.51 | AB32: =SUM(AB28:AB31) -> 3299.89 | AC32: =SUM(AC28:AC31) -> 626.9039
B33: 45839 | C33: 251.64198 | D33: =+C33*0.19 -> 47.811975 | E33: =+C33-D33 -> 203.83 | F33: 203.83 | H33: =SUM(H27:H31) -> 255.68 | I33: =SUM(I27:I31) -> 48.5792 | J33: =SUM(J27:J31) -> 207.1008 | K33: =SUM(K27:K31) -> 207.1 | M33: =+SUM(M4:M8,M12:M23,M27:M30) -> 3107.7284 | N33: =+SUM(N4:N8,N12:N23,N27:N30) -> 590.4629 | O33: =+SUM(O4:O8,O12:O23,O27:O30) -> 2517.2655 | P33: =+SUM(P4:P8,P12:P23,P27:P30) -> 2518.11 | R33: =+C33 -> 251.64198 | S33: =SUM(E33) -> 203.83 | U33: =F33 -> 203.83
B34: 45870 | C34: 231.55556 | D34: =+C34*0.19 -> 43.995556 | E34: =+C34-D34 -> 187.56 | F34: 187.56 | R34: =+C34 -> 231.55556 | S34: =SUM(E34) -> 187.56 | U34: =P34+K34+F34 -> 187.56
B35: 45901 | C35: 231.55556 | D35: =+C35*0.19 -> 43.995556 | E35: =+C35-D35 -> 187.56 | F35: 187.58 | R35: =+C35 -> 231.55556 | S35: =SUM(E35) -> 187.56 | U35: =P35+K35+F35 -> 187.58
B36: 45931 | C36: =(137000/30*23+138000/31*8)*0.0199/12 -> 233.23834 | D36: =+C36*0.19 -> 44.315285 | E36: =+C36-D36 -> 188.92306 | F36: 181.88 | R36: =+C36 -> 233.23834 | S36: =SUM(E36) -> 188.92306 | U36: =P36+K36+F36 -> 181.88
B37: 45962 | C37: 233.73 | D37: =+C37*0.19 -> 44.4087 | E37: =+C37-D37 -> 189.3213 | F37: 189.33 | R37: =+C37 -> 233.73 | S37: =SUM(E37) -> 189.3213 | U37: =F37 -> 189.33
B38: 45992 | C38: 26.95 | D38: =+C38*0.19 -> 5.1205 | E38: =+C38-D38 -> 21.8295 | F38: 21.83 | R38: =+C42+C38 -> 365.08 | S38: =SUM(E38,E42) -> 295.7148 | T38: =SUM(S27:S38) -> 2679.996 | U38: =F38+F42 -> 295.72 | V38: =SUM(U27:U38) -> 2672.99
C40: Openbank / Trade Republic / Cajamar
C41: Intereses | D41: Retención | E41: Neto | F41: Ingresado
A42: 2026 | B42: 45992 | C42: 338.13 | D42: =+C42*0.19 -> 64.2447 | E42: =+C42-D42 -> 273.8853 | F42: 273.89 | R42: =+C43 -> 362.407 | S42: =SUM(E43) -> 293.54967 | U42: =F42 -> 273.89
B43: 46023 | C43: =362.407 -> 362.407 | D43: =+C43*0.19 -> 68.85733 | E43: =+C43-D43 -> 293.54967 | F43: 293.55 | R43: =+C44 -> 371.6 | S43: =SUM(E44) -> 300.996 | U43: =F43 -> 293.55
B44: 46054 | C44: 371.6 | D44: =+C44*0.19 -> 70.604 | E44: =+C44-D44 -> 300.996 | F44: 301 | R44: =+C45 -> 344.75 | S44: =SUM(E45) -> 279.2475 | U44: =F44 -> 301
B45: 46082 | C45: 344.75 | D45: =+C45*0.19 -> 65.5025 | E45: =+C45-D45 -> 279.2475 | F45: 275.34 | R45: =+C46 -> 161.51 | S45: =SUM(E46) -> 130.8231 | U45: =F45 -> 275.34
B46: 46113 | C46: =49.12+87.73+24.66 -> 161.51 | D46: =+C46*0.19 -> 30.6869 | E46: =+C46-D46 -> 130.8231 | F46: 130.82 | R46: =+C47 -> 308.21 | S46: =SUM(E47) -> 249.6501 | U46: =F46 -> 130.82
B47: 46143 | C47: =184.93+123.28 -> 308.21 | D47: =+C47*0.19 -> 58.5599 | E47: =+C47-D47 -> 249.6501 | F47: =99.86+149.79 -> 249.65 | R47: =+C48 -> 279.16667 | S47: =SUM(E48) -> 226.125 | U47: =F47 -> 249.65
B48: 46174 | C48: =+C63+D63 -> 279.16667 | D48: =+C48*0.19 -> 53.041667 | E48: =+C48-D48 -> 226.125 | F48: 101.1 | R48: =+C49 -> 282.29167 | S48: =SUM(E49) -> 228.65625 | U48: =F48 -> 101.1
B49: 46204 | C49: =+C64+D64 -> 282.29167 | D49: =+C49*0.19 -> 53.635417 | E49: =+C49-D49 -> 228.65625 | R49: =+C50 -> 286.45833 | S49: =SUM(E50) -> 232.03125 | U49: =F49 -> 0
B50: 46235 | C50: =+C65+D65 -> 286.45833 | D50: =+C50*0.19 -> 54.427083 | E50: =+C50-D50 -> 232.03125 | R50: =+C51 -> 290.625 | S50: =SUM(E51) -> 235.40625 | U50: =F50 -> 0
B51: 46266 | C51: =+C66+D66 -> 290.625 | D51: =+C51*0.19 -> 55.21875 | E51: =+C51-D51 -> 235.40625 | R51: =+C52 -> 294.79167 | S51: =SUM(E52) -> 238.78125 | U51: =F51 -> 0
B52: 46296 | C52: =+C67+D67 -> 294.79167 | D52: =+C52*0.19 -> 56.010417 | E52: =+C52-D52 -> 238.78125 | R52: =+C53 -> 277.08333 | S52: =SUM(E53) -> 224.4375 | U52: =F52 -> 0
B53: 46327 | C53: =+C68+D68 -> 277.08333 | D53: =+C53*0.19 -> 52.645833 | E53: =+C53-D53 -> 224.4375 | R53: =+C54 -> 281.25 | S53: =SUM(E54) -> 227.8125 | T53: =SUM(S42:S53) -> 2867.5164 | U53: =F53 -> 0
B54: 46357 | C54: =+C69+D69 -> 281.25 | D54: =+C54*0.19 -> 53.4375 | E54: =+C54-D54 -> 227.8125
A56: TOTAL | C56: =SUM(C4:C53) -> 6364.4948 | D56: =SUM(D4:D53) -> 1209.254 | E56: =SUM(E4:E53) -> 5155.2408 | F56: =SUM(F4:F53) -> 3859.99 | H56: =+H33+H22 -> 794.03 | I56: =+I33+I22 -> 150.8657 | J56: =+J33+J22 -> 643.1643 | K56: =+K33+K22 -> 643.19 | M56: =SUM(M4:M31) -> 3107.7284 | N56: =SUM(N4:N31) -> 590.4629 | O56: =SUM(O4:O31) -> 2517.2655 | P56: =SUM(P4:P31) -> 2518.11 | R56: =SUM(R4:R53) -> 10547.503 | S56: =SUM(S4:S53) -> 8543.4831 | U56: =SUM(U4:U53) -> 7295.18 | V56: =SUM(V4:V53) -> 5669.83
B60: 0.19 | C60: 0.025
B63: 74000 | C63: =+B63*$C$60/12 -> 154.16667 | D63: =50000*0.03/12 -> 125 | E63: =+$C63*$B$60+$D63*$B$60 -> 53.041667 | F63: =+C63+D63-E63 -> 226.125
B64: =+B63+1500 -> 75500 | C64: =+B64*$C$60/12 -> 157.29167 | D64: =50000*0.03/12 -> 125 | E64: =+$C64*$B$60+$D64*$B$60 -> 53.635417 | F64: =+C64+D64-E64 -> 228.65625
B65: =+B64+2000 -> 77500 | C65: =+B65*$C$60/12 -> 161.45833 | D65: =50000*0.03/12 -> 125 | E65: =+$C65*$B$60+$D65*$B$60 -> 54.427083 | F65: =+C65+D65-E65 -> 232.03125
B66: =+B65+2000 -> 79500 | C66: =+B66*$C$60/12 -> 165.625 | D66: =50000*0.03/12 -> 125 | E66: =+$C66*$B$60+$D66*$B$60 -> 55.21875 | F66: =+C66+D66-E66 -> 235.40625
B67: =+B66+2000 -> 81500 | C67: =+B67*$C$60/12 -> 169.79167 | D67: =50000*0.03/12 -> 125 | E67: =+$C67*$B$60+$D67*$B$60 -> 56.010417 | F67: =+C67+D67-E67 -> 238.78125
B68: =+B67+1500+50000 -> 133000 | C68: =+B68*$C$60/12 -> 277.08333 | E68: =+$C68*$B$60+$D68*$B$60 -> 52.645833 | F68: =+C68+D68-E68 -> 224.4375
B69: =+B68+2000 -> 135000 | C69: =+B69*$C$60/12 -> 281.25 | E69: =+$C69*$B$60+$D69*$B$60 -> 53.4375 | F69: =+C69+D69-E69 -> 227.8125

Sheet IRPF
B1: RENTA 202 | F1: CUOTA ÍNTEGRA | M1: RENTA 202 | Q1: CUOTA ÍNTEGRA
F2: Resultado de la escala general | J2: =4158+(E14-18080)*0.28 -> -5671.4112 | Q2: Resultado de la escala general | U2: =4158+(P14-18080)*0.28 -> -5671.4112
F3: Minoración | J3: =1615 -> 1615 | Q3: Minoración | U3: =1615 -> 1615
B4: RENTA GENERAL | F4: Cuota íntegra general | J4: =J2-J3 -> -7286.4112 | M4: RENTA GENERAL | Q4: Cuota íntegra general | U4: =U2-U3 -> -7286.4112
B5: Rendimientos del Trabajo | F5: Cuota íntegra del ahorro | J5: =0.19*E21 -> 0 | M5: Rendimientos del Trabajo | Q5: Cuota íntegra del ahorro | U5: =0.2*P22 -> 0
B6: Rendimientos íntegros | M6: Rendimientos íntegros
B7: Gastos deducibles | F7: Total cuota | J7: =J4+J5 -> -7286.4112 | M7: Gastos deducibles | Q7: Total cuota | U7: =U4 -> -7286.4112
B8: Bonificación | E8: =8000-(E6-E7-14800)*0.6098 -> 17025.04 | F8: DEDUCCIONES | M8: Bonificación | P8: =8000-(P6-P7-14800)*0.6098 -> 17025.04 | Q8: DEDUCCIONES
B9: Rendimiento neto del trabajo | E9: =E6-E7-E8 -> -17025.04 | F9: Edad | M9: Rendimiento neto del trabajo | P9: =P6-P7-P8 -> -17025.04 | Q9: Edad
B10: Ganancia patrimonial | F10: Actividades mecenazgo (donativos) | J10: 0 | M10: Ganancia patrimonial | Q10: Actividades mecenazgo (donativos) | U10: 0
B12: TOTAL RENTAS BASE IMPONIBLE GRAL. | E12: =E9 -> -17025.04 | F12: Total deducciones | J12: =J9+J10 -> 0 | M12: TOTAL RENTAS BASE IMPONIBLE GRAL. | P12: =P9 -> -17025.04 | Q12: Total deducciones | U12: =U9+U10 -> 0
F13: CUOTA LÍQUIDA | J13: =IF(J7>0,J7-J12,0) -> 0 | Q13: CUOTA LÍQUIDA | U13: =IF(U7>0,U7-U12,0) -> 0
B14: BASE IMPONIBLE GENERAL | E14: =E12 -> -17025.04 | F14: Incremento por pérdida beneficios | M14: BASE IMPONIBLE GENERAL | P14: =P12 -> -17025.04 | Q14: Incremento por pérdida beneficios
F15: PAGOS A CUENTA | Q15: PAGOS A CUENTA
B16: Capital Mobiliario | F16: Retenciones trabajo | M16: Capital Mobiliario | Q16: Retenciones trabajo
B17: Rendimiento neto capital mobiliario | F17: Retenciones capital mobiliario | M17: Rendimiento neto capital mobiliario | P17: 0 | Q17: Retenciones capital mobiliario | U17: 0
F19: Total pagos a cuenta | J19: =J16+J17 -> 0 | Q19: Total pagos a cuenta | U19: =U16+U17 -> 0
B20: Ganancia patrimonial | F20: Opción tributaria por retenciones | M20: Ganancia patrimonial | Q20: Opción tributaria por retenciones
B21: TOTAL RENTAS B.I. DEL AHORRO | E21: 0 | F21: CUOTA DIFERENCIAL | J21: =J13-J19 -> 0 | M21: TOTAL RENTAS B.I. DEL AHORRO | P21: 0 | Q21: CUOTA DIFERENCIAL | U21: =U13-U19 -> 0
B22: BASE LIQUIDABLE DEL AHORRO | E22: =E17 -> 0 | F22: =IF(J21<0,"A DEVOLVER","A INGRESAR") -> A INGRESAR | J22: =ABS(J21) -> 0 | M22: BASE LIQUIDABLE DEL AHORRO | P22: 0 | Q22: =IF(U21<0,"A DEVOLVER","A INGRESAR") -> A INGRESAR | U22: =ABS(U21) -> 0
G24: Tipo de interes | R24: Tipo de interes
G25: 17720 | H25: 4075.6 | R25: 17720 | S25: 4075.6
G26: =E14-G25 -> -34745.04 | H26: =0.28*G26 -> -9728.6112 | R26: =P14-R25 -> -34745.04 | S26: =0.28*R26 -> -9728.6112
G27: 2500 | H27: =0.2*G27 -> 500 | R27: 2500 | S27: =0.2*R27 -> 500
G28: =+E22-G27 -> -2500 | H28: =+G28*0.21 -> -525 | R28: =+P22-R27 -> -2500 | S28: =+R28*0.21 -> -525
H29: =SUM(H25:H28) -> -5678.0112 | I29: =H29/(E6+E22) -> #DIV/0! | S29: =SUM(S25:S28) -> -5678.0112 | T29: =S29/(P6+P22) -> #DIV/0!
B31: RENTA 2025 | F31: CUOTA ÍNTEGRA | M31: RENTA 2026 | Q31: CUOTA ÍNTEGRA
F32: Resultado de la escala general | J32: =+E44*0.23 -> 2956.1121 | Q32: Resultado de la escala general | U32: =4158+(P44-18080)*0.28 -> 5062.399
F33: Minoración | J33: 1583 | Q33: Minoración | U33: 1583
B34: RENTA GENERAL | F34: Cuota íntegra general | J34: =J32-J33 -> 1373.1121 | M34: RENTA GENERAL | Q34: Cuota íntegra general | U34: =U32-U33 -> 3479.399
B35: Rendimientos del Trabajo | F35: Cuota íntegra del ahorro | J35: =0.2*2500+0.21*(E47-2500) -> 679.4009 | M35: Rendimientos del Trabajo | Q35: Cuota íntegra del ahorro | U35: =0.19*P52 -> 672.6273
B36: Rendimientos íntegros | E36: 19983.6 | M36: Rendimientos íntegros | P36: =+'25 26 Vadillo'!O11 -> 25999.996
B37: Gastos deducibles | E37: 1416.51 | F37: Total cuota | J37: =J34+J35 -> 2052.513 | M37: Gastos deducibles | P37: =+'25 26 Vadillo'!O12 -> 1689.9998 | Q37: Total cuota | U37: =U34+U35 -> 4152.0263
B38: Bonificación | E38: =8000-(E36-E37-14800)*0.6098 -> 5702.8285 | F38: DEDUCCIONES | M38: Bonificación | P38: 3000 | Q38: DEDUCCIONES
B39: Rendimiento neto del trabajo | E39: =E36-E37-E38 -> 12864.261 | F39: Edad | M39: Rendimiento neto del trabajo | P39: =P36-P37-P38 -> 21309.996 | Q39: Edad
B40: Ganancia patrimonial | F40: Actividades mecenazgo (donativos) | J40: 0 | M40: Ganancia patrimonial | Q40: Actividades mecenazgo (donativos) | U40: 0
B42: TOTAL RENTAS BASE IMPONIBLE GRAL. | E42: =E39-11.6 -> 12852.661 | F42: Total deducciones | J42: 0.58 | M42: TOTAL RENTAS BASE IMPONIBLE GRAL. | P42: =P39 -> 21309.996 | Q42: Total deducciones | U42: =U39+U40 -> 0
F43: CUOTA LÍQUIDA | J43: =IF(J37>0,J37-J42,0) -> 2051.933 | Q43: CUOTA LÍQUIDA | U43: =IF(U37>0,U37-U42,0) -> 4152.0263
B44: BASE IMPONIBLE GENERAL | E44: =E42 -> 12852.661 | F44: Incremento por pérdida beneficios | M44: BASE IMPONIBLE GENERAL | P44: =P42 -> 21309.996 | Q44: Incremento por pérdida beneficios
F45: PAGOS A CUENTA | Q45: PAGOS A CUENTA
B46: Capital Mobiliario | F46: Retenciones trabajo | J46: 2650.39 | K46: 0.13 | M46: Capital Mobiliario | Q46: Retenciones trabajo | U46: =+'25 26 Vadillo'!O13 -> 3379.9995 | V46: 0.13
B47: Rendimiento neto capital mobiliario | E47: 3354.29 | F47: Retenciones capital mobiliario | J47: 637.25 | M47: Rendimiento neto capital mobiliario | P47: =+SUM('Intereses cuentas'!C43:C54) -> 3540.1437 | Q47: Retenciones capital mobiliario | U47: =+SUM('Intereses cuentas'!D43:D54) -> 672.6273
F49: Total pagos a cuenta | J49: =J46+J47 -> 3287.64 | Q49: Total pagos a cuenta | U49: =U46+U47 -> 4052.6268
B50: Ganancia patrimonial | F50: Opción tributaria por retenciones | M50: Ganancia patrimonial | Q50: Opción tributaria por retenciones
B51: TOTAL RENTAS B.I. DEL AHORRO | E51: 0 | F51: CUOTA DIFERENCIAL | J51: =J43-J49 -> -1235.707 | M51: TOTAL RENTAS B.I. DEL AHORRO | P51: 0 | Q51: CUOTA DIFERENCIAL | U51: =U43-U49 -> 99.399498
B52: BASE LIQUIDABLE DEL AHORRO | E52: =E47 -> 3354.29 | F52: =IF(J51<0,"A DEVOLVER","A INGRESAR") -> A DEVOLVER | J52: =ABS(J51) -> 1235.707 | M52: BASE LIQUIDABLE DEL AHORRO | P52: =+P47 -> 3540.1437 | Q52: =IF(U51<0,"A DEVOLVER","A INGRESAR") -> A INGRESAR | U52: =ABS(U51) -> 99.399498
G54: Tipo de interes | R54: Tipo de interes
G55: 17720 | H55: 4075.6 | R55: 17720 | S55: 4075.6
G56: =E44-G55 -> -4867.3385 | H56: =0.28*G56 -> -1362.8548 | R56: =P44-R55 -> 3589.9964 | S56: =0.28*R56 -> 1005.199
G57: 2500 | H57: =0.2*G57 -> 500 | R57: 2500 | S57: =0.2*R57 -> 500
G58: =+E52-G57 -> 854.29 | H58: =+G58*0.21 -> 179.4009 | R58: =+P52-R57 -> 1040.1437 | S58: =+R58*0.21 -> 218.43017
H59: =SUM(H55:H58) -> 3392.1461 | I59: =H59/(E36+E52) -> 0.14534931 | S59: =SUM(S55:S58) -> 5799.2292 | T59: =S59/(P36+P52) -> 0.19631692
B62: RENTA 2024 | F62: CUOTA ÍNTEGRA
F63: Resultado de la escala general | J63: =4075.6+(E75-17720)*0.28 -> 4810.628
F64: Minoración | J64: =1583+200 -> 1783
B65: RENTA GENERAL | F65: Cuota íntegra general | J65: =J63-J64 -> 3027.628
B66: Rendimientos del Trabajo | F66: Cuota íntegra del ahorro | J66: =0.2*2500+0.21*(E78-2500) -> 647.1785
B67: Rendimientos íntegros | E67: 24959.94
B68: Gastos deducibles | E68: 1614.84 | F68: Total cuota | J68: =J65+J66 -> 3674.8065
B69: Bonificación | E69: 3000 | F69: DEDUCCIONES
B70: Rendimiento neto del trabajo | E70: =E67-E68-E69 -> 20345.1 | F70: Edad
B71: Ganancia patrimonial | F71: Actividades mecenazgo (donativos) | J71: 0
B73: TOTAL RENTAS BASE IMPONIBLE GRAL. | E73: =E70 -> 20345.1 | F73: Total deducciones | J73: =J70+J71 -> 0
F74: CUOTA LÍQUIDA | J74: =IF(J68>0,J68-J73,0) -> 3674.8065
B75: BASE IMPONIBLE GENERAL | E75: =E73 -> 20345.1 | F75: Incremento por pérdida beneficios
F76: PAGOS A CUENTA
B77: Capital Mobiliario | F77: Retenciones trabajo | J77: 3427.89 | K77: 0.14
B78: Rendimiento neto capital mobiliario | E78: 3200.85 | F78: Retenciones capital mobiliario | J78: ='Intereses cuentas'!AA11 -> 595.13214
F80: Total pagos a cuenta | J80: 4062.88
B81: Ganancia patrimonial | F81: Opción tributaria por retenciones
B82: TOTAL RENTAS B.I. DEL AHORRO | E82: 0 | F82: CUOTA DIFERENCIAL | J82: =J74-J80 -> -388.0735
B83: BASE LIQUIDABLE DEL AHORRO | E83: =E78 -> 3200.85 | F83: =IF(J82<0,"A DEVOLVER","A INGRESAR") -> A DEVOLVER | J83: =ABS(J82) -> 388.0735
G85: Tipo de interes
G86: 17720 | H86: 4075.6
G87: =E75-G86 -> 2625.1 | H87: =0.28*G87 -> 735.028
H88: =SUM(H86:H87) -> 4810.628 | I88: =H88/E67 -> 0.19273396
B94: RENTA 2023 | F94: CUOTA ÍNTEGRA | M94: RENTA 2022 | Q94: CUOTA ÍNTEGRA
F95: Resultado de la escala general | J95: =3974.4+(E107-17280)*0.28 -> 4670.0096 | Q95: Resultado de la escala general | U95: =P107*0.23 -> 3538.1329
F96: Minoración | J96: =1544+200 -> 1744 | Q96: Minoración | U96: =1513+200 -> 1713
B97: RENTA GENERAL | F97: Cuota íntegra general | J97: =J95-J96 -> 2926.0096 | M97: RENTA GENERAL | Q97: Cuota íntegra general | U97: =U95-U96 -> 1825.1329
B98: Rendimientos del Trabajo | F98: Cuota íntegra del ahorro | J98: =0.2*E115 -> 113.88 | M98: Rendimientos del Trabajo | Q98: Cuota íntegra del ahorro | U98: =0.2*P115 -> 0
B99: Rendimientos íntegros | E99: ='22 25 FarmaConsulting'!D76 -> 24333.52 | M99: Rendimientos íntegros | P99: =1028.35+'22 25 FarmaConsulting'!O90 -> 19628.397
B100: Gastos deducibles | E100: =1569.2 -> 1569.2 | F100: Total cuota | J100: =J97+J98 -> 3039.8896 | M100: Gastos deducibles | P100: 1245.21 | Q100: Total cuota | U100: =U97 -> 1825.1329
B101: Bonificación | E101: 3000 | F101: DEDUCCIONES | M101: Bonificación | P101: 3000 | Q101: DEDUCCIONES
B102: Rendimiento neto del trabajo | E102: =E99-E100-E101 -> 19764.32 | F102: Edad | M102: Rendimiento neto del trabajo | P102: =P99-P100-P101 -> 15383.187 | Q102: Edad
B103: Ganancia patrimonial | F103: Actividades mecenazgo (donativos) | J103: 0 | M103: Ganancia patrimonial | Q103: Actividades mecenazgo (donativos) | U103: 0
B105: TOTAL RENTAS BASE IMPONIBLE GRAL. | E105: =E102 -> 19764.32 | F105: Total deducciones | J105: =J102+J103 -> 0 | M105: TOTAL RENTAS BASE IMPONIBLE GRAL. | P105: =P102 -> 15383.187 | Q105: Total deducciones | U105: =U102+U103 -> 0
F106: CUOTA LÍQUIDA | J106: =IF(J100>0,J100-J105,0) -> 3039.8896 | Q106: CUOTA LÍQUIDA | U106: =IF(U100>0,U100-U105,0) -> 1825.1329
B107: BASE IMPONIBLE GENERAL | E107: =E105 -> 19764.32 | F107: Incremento por pérdida beneficios | M107: BASE IMPONIBLE GENERAL | P107: =P105 -> 15383.187 | Q107: Incremento por pérdida beneficios
F108: PAGOS A CUENTA | Q108: PAGOS A CUENTA
B109: Capital Mobiliario | F109: Retenciones trabajo | J109: ='22 25 FarmaConsulting'!O66 -> 3365.7378 | K109: 0.14 | M109: Capital Mobiliario | Q109: Retenciones trabajo | U109: =51.42+'22 25 FarmaConsulting'!O92 -> 2469.446 | V109: 0.13
B110: Rendimiento neto capital mobiliario | E110: 569.4 | F110: Retenciones capital mobiliario | J110: ='Intereses cuentas'!AA5 -> 107.62641 | M110: Rendimiento neto capital mobiliario | P110: 0 | Q110: Retenciones capital mobiliario | U110: 0
F112: Total pagos a cuenta | J112: =J109+J110 -> 3473.3642 | Q112: Total pagos a cuenta | U112: =U109+U110 -> 2469.446
B113: Ganancia patrimonial | F113: Opción tributaria por retenciones | M113: Ganancia patrimonial | Q113: Opción tributaria por retenciones
B114: TOTAL RENTAS B.I. DEL AHORRO | E114: 0 | F114: CUOTA DIFERENCIAL | J114: =J106-J112 -> -433.47461 | M114: TOTAL RENTAS B.I. DEL AHORRO | P114: 0 | Q114: CUOTA DIFERENCIAL | U114: =U106-U112 -> -644.31315
B115: BASE LIQUIDABLE DEL AHORRO | E115: =E110 -> 569.4 | F115: =IF(J114<0,"A DEVOLVER","A INGRESAR") -> A DEVOLVER | J115: =ABS(J114) -> 433.47461 | M115: BASE LIQUIDABLE DEL AHORRO | P115: 0 | Q115: =IF(U114<0,"A DEVOLVER","A INGRESAR") -> A DEVOLVER | U115: =ABS(U114) -> 644.31315
G117: Tipo de interes | R117: Tipo de interes
G118: 17280 | H118: 3974.4 | R118: 16940 | S118: 3686.9
G119: =E107-G118 -> 2484.32 | H119: =0.28*G119 -> 695.6096 | R119: =IF(P107-R118>0,P107-R118,0) -> 0 | S119: =0.28*R119 -> 0
H120: =SUM(H118:H119) -> 4670.0096 | I120: =H120/E99 -> 0.19191673 | S120: =SUM(S118:S119) -> 3686.9 | T120: =S120/P99 -> 0.18783501

Sheet 25 Eurocybcar
C2: Eurocybcar
C5: TOTAL | D5: =+J25 -> 2327.33
D9: Bruto | E9: SS | F9: Desemp | G9: EPSV | H9: IRPF | I9: Sueldo | J9: Ingresado | K9: Diferencia | M9: Paga Extra | R9: 2025
B10: 2025 | C10: 45658 | I10: =D10-E10-H10-F10 -> 0 | K10: =IF(ISBLANK(J10)," ",IF(J10-I10<0.01,"Correcto ",IF(J10-I10<0.01,"Faltan","Sobran"))) | L10: =IF(ISBLANK(J10)," ",IF(ABS(J10-I10)<0.01," ",J10-I10)) | R10: 44562 | S10: L | T10: M | U10: X | V10: J | W10: V | X10: S | Y10: D | Z10: L | AA10: M | AB10: X | AC10: J | AD10: V | AE10: S | AF10: D | AG10: L | AH10: M | AI10: X | AJ10: J | AK10: V | AL10: S | AM10: D | AN10: L | AO10: M | AP10: X | AQ10: J | AR10: V | AS10: S | AT10: D | AU10: L | AV10: M | AW10: X | AX10: J | AY10: V | AZ10: S | BA10: D | BB10: L | BC10: M
C11: 45689 | I11: =D11-E11-H11-F11 -> 0 | K11: =IF(ISBLANK(J11)," ",IF(J11-I11<0.01,"Correcto ",IF(J11-I11<0.01,"Faltan","Sobran"))) | L11: =IF(ISBLANK(J11)," ",IF(ABS(J11-I11)<0.01," ",J11-I11)) | R11: MAY | Z11: 5 | AA11: 6 | AB11: 7 | AC11: 8 | AD11: 9 | AE11: 10 | AF11: 11 | AG11: 12 | AH11: 13 | AI11: 14 | AJ11: 15 | AK11: 16 | AL11: 17 | AM11: 18 | AN11: 19 | AO11: 20 | AP11: 21 | AQ11: 22 | AR11: 23 | AS11: 24 | AT11: 25 | AU11: 26 | AV11: 27 | AW11: 28 | AX11: 29 | AY11: 30 | AZ11: 31
C12: 45717 | I12: =D12-E12-H12-F12 -> 0 | K12: =IF(ISBLANK(J12)," ",IF(J12-I12<0.01,"Correcto ",IF(J12-I12<0.01,"Faltan","Sobran"))) | L12: =IF(ISBLANK(J12)," ",IF(ABS(J12-I12)<0.01," ",J12-I12)) | R12: JUN | Y12: 1 | Z12: 2 | AA12: 3 | AB12: 4 | AC12: 5 | AD12: 6 | AE12: 7 | AF12: 8 | AG12: 9 | AH12: 10 | AI12: 11 | AJ12: 12 | AK12: 13
C13: 45748 | I13: =D13-E13-H13-F13 -> 0 | K13: =IF(ISBLANK(J13)," ",IF(J13-I13<0.01,"Correcto ",IF(J13-I13<0.01,"Faltan","Sobran"))) | L13: =IF(ISBLANK(J13)," ",IF(ABS(J13-I13)<0.01," ",J13-I13)) | O13: Rend trabajo 2025 | P13: =SUM(D10:D23) -> 2898.1892
C14: 45778 | D14: =27*(49.95+1.18+4.1623+5.8273) -> 1650.2292 | E14: =(D14+M14+G14)*0.0483 -> 90.74407 | F14: =(D14+M14+G14)*0.0165 -> 30.999527 | G14: =(D14+M14)*0.2/100 -> 3.7500184 | H14: =D14*$O$16 -> 214.5298 | I14: =D14-E14-H14-F14-G14 -> 1310.2058 | J14: 1310.21 | K14: =IF(ISBLANK(J14)," ",IF(J14-I14<0.01,"Correcto ",IF(J14-I14<0.01,"Faltan","Sobran"))) -> Correcto | L14: =IF(ISBLANK(J14)," ",IF(ABS(J14-I14)<0.01," ",J14-I14)) | M14: 224.78 | O14: Gastos Deducibles SS | P14: =SUM(E10:F23) -> 188.3036
C15: 45821 | D15: =794.56+331.16+122.24 -> 1247.96 | E15: =49.61+16.95 -> 66.56 | G15: 2.05 | H15: =1247.96*0.13 -> 162.2348 | I15: =D15-E15-H15-F15-G15 -> 1017.1152 | J15: 1017.12 | K15: =IF(ISBLANK(J15)," ",IF(ABS(J15-I15)<0.01,"Correcto ",IF(J15-I15<0,"Faltan","Sobran"))) -> Correcto | L15: =IF(ISBLANK(J15)," ",IF(ABS(J15-I15)<0.01," ",J15-I15)) | O15: IRPF | P15: =SUM(H10:H23) -> 376.7646
C16: Extra JUL25 | H16: =D16*$O$16 -> 0 | I16: =D16-E16-H16-F16-G16 -> 0 | K16: =IF(ISBLANK(J16)," ",IF(ABS(J16-I16)<0.01,"Correcto ",IF(J16-I16<0,"Faltan","Sobran"))) | L16: =IF(ISBLANK(J16)," ",IF(ABS(J16-I16)<0.01," ",J16-I16)) | O16: 0.13
C17: 45839 | E17: =(D17+M17+G17)*0.0483 -> 0 | F17: =(D17+M17+G17)*0.0165 -> 0 | G17: =(D17+M17)*0.2/100 -> 0 | H17: =D17*$O$16 -> 0 | I17: =D17-E17-H17-F17-G17 -> 0 | K17: =IF(ISBLANK(J17)," ",IF(ABS(J17-I17)<0.01,"Correcto ",IF(J17-I17<0,"Faltan","Sobran"))) | L17: =IF(ISBLANK(J17)," ",IF(ABS(J17-I17)<0.01," ",J17-I17))
C18: 45870 | E18: =(D18+M18+G18)*0.0483 -> 0 | F18: =(D18+M18+G18)*0.0165 -> 0 | G18: =(D18+M18)*0.2/100 -> 0 | H18: =D18*$O$16 -> 0 | I18: =D18-E18-H18-F18-G18 -> 0 | K18: =IF(ISBLANK(J18)," ",IF(ABS(J18-I18)<0.01,"Correcto ",IF(J18-I18<0,"Faltan","Sobran"))) | L18: =IF(ISBLANK(J18)," ",IF(ABS(J18-I18)<0.01," ",J18-I18))
C19: 45901 | E19: =(D19+M19+G19)*0.0483 -> 0 | F19: =(D19+M19+G19)*0.0165 -> 0 | G19: =(D19+M19)*0.2/100 -> 0 | H19: =D19*$O$16 -> 0 | I19: =D19-E19-H19-F19-G19 -> 0 | K19: =IF(ISBLANK(J19)," ",IF(ABS(J19-I19)<0.01,"Correcto ",IF(J19-I19<0,"Faltan","Sobran"))) | L19: =IF(ISBLANK(J19)," ",IF(ABS(J19-I19)<0.01," ",J19-I19)) | O19: VACACIONES | P19: =22/12*1.25 -> 2.2916667
C20: 45931 | E20: =(D20+M20+G20)*0.0483 -> 0 | F20: =(D20+M20+G20)*0.0165 -> 0 | G20: =(D20+M20)*0.2/100 -> 0 | H20: =D20*$O$16 -> 0 | I20: =D20-E20-H20-F20-G20 -> 0 | K20: =IF(ISBLANK(J20)," ",IF(ABS(J20-I20)<0.01,"Correcto ",IF(J20-I20<0,"Faltan","Sobran"))) | L20: =IF(ISBLANK(J20)," ",IF(ABS(J20-I20)<0.01," ",J20-I20)) | R20: Horas 2025
C21: 45962 | E21: =(D21+M21+G21)*0.0483 -> 0 | F21: =(D21+M21+G21)*0.0165 -> 0 | G21: =(D21+M21)*0.2/100 -> 0 | H21: =D21*$O$16 -> 0 | I21: =D21-E21-H21-F21-G21 -> 0 | K21: =IF(ISBLANK(J21)," ",IF(ABS(J21-I21)<0.01,"Correcto ",IF(J21-I21<0,"Faltan","Sobran"))) | L21: =IF(ISBLANK(J21)," ",IF(ABS(J21-I21)<0.01," ",J21-I21)) | R21: 44562 | S21: L | T21: M | U21: X | V21: J | W21: V | X21: S | Y21: D | Z21: L | AA21: M | AB21: X | AC21: J | AD21: V | AE21: S | AF21: D | AG21: L | AH21: M | AI21: X | AJ21: J | AK21: V | AL21: S | AM21: D | AN21: L | AO21: M | AP21: X | AQ21: J | AR21: V | AS21: S | AT21: D | AU21: L | AV21: M | AW21: X | AX21: J | AY21: V | AZ21: S | BA21: D | BB21: L | BC21: M
C22: 45992 | E22: =(D22+M22+G22)*0.0483 -> 0 | F22: =(D22+M22+G22)*0.0165 -> 0 | G22: =(D22+M22)*0.2/100 -> 0 | H22: =D22*$O$16 -> 0 | I22: =D22-E22-H22-F22-G22 -> 0 | K22: =IF(ISBLANK(J22)," ",IF(ABS(J22-I22)<0.01,"Correcto ",IF(J22-I22<0,"Faltan","Sobran"))) | L22: =IF(ISBLANK(J22)," ",IF(ABS(J22-I22)<0.01," ",J22-I22)) | R22: MAY | Z22: 8.5 | AA22: 8.5 | AB22: 8.5 | AC22: 8.5 | AD22: 6 | AG22: 8.5 | AH22: 8.5 | AI22: 8.5 | AJ22: 8.5 | AK22: 6 | AN22: 8.5 | AO22: 8.5 | AP22: 8.5 | AQ22: 8.5 | AR22: 6 | AU22: 8.5 | AV22: 8.5 | AW22: 8.5 | AX22: 8.5 | AY22: 6 | BD22: =SUM(S22:BC22) -> 160
C23: Extra DIC25 | H23: =D23*$O$16 -> 0 | I23: =D23-E23-H23-F23-G23 -> 0 | K23: =IF(ISBLANK(J23)," ",IF(ABS(J23-I23)<0.01,"Correcto ",IF(J23-I23<0,"Faltan","Sobran"))) | L23: =IF(ISBLANK(J23)," ",IF(J23-I23<0.01," ",J23-I23)) | R23: JUN | Z23: 8.5 | AA23: 8.5 | AB23: 8.5 | AC23: 8.5 | AD23: 6 | AG23: 8.5 | AH23: 8.5 | AI23: 8.5 | AJ23: 8.5 | AK23: 6 | BB23: 7 | BD23: =SUM(S23:BC23) -> 87
C24: Bonus | E24: =(D24+M24)*0.0483 -> 0 | F24: =(D24+M24)*0.0165 -> 0 | G24: =(D24+M24)*0.2/100 -> 0 | H24: =D24*$O$16 -> 0 | I24: =D24-E24-H24-F24-G24 -> 0 | K24: =IF(ISBLANK(J24)," ",IF(ABS(J24-I24)<0.01,"Correcto ",IF(J24-I24<0,"Faltan","Sobran"))) | L24: =IF(ISBLANK(J24)," ",IF(J24-I24<0.01," ",J24-I24)) | O24: Disfrutadas | P24: =SUM(P20:P23) -> 0 | BD24: =SUM(BD22:BD23) -> 247
D25: =SUM(D10:D24) -> 2898.1892 | E25: =SUM(E10:E24) -> 157.30407 | F25: =SUM(F10:F24) -> 30.999527 | G25: =SUM(G10:G24) -> 5.8000184 | H25: =SUM(H10:H24) -> 376.7646 | I25: =SUM(I10:I24) -> 2327.321 | J25: =SUM(J10:J24) -> 2327.33 | O25: =+IF(P24<P19,"Por coger",IF(P24>P19,"Del año que viene"," ")) -> Por coger | P25: =ABS(P24-P19) -> 2.2916667
D26: =D25-E25-H25-F25-G25 -> 2327.321

Sheet 22 25 FarmaConsulting
C2: FarmaConsulting
C5: TOTAL | D5: =I100+I76+I50+I25 -> 61006.36
N7: Liquidación
N8: P extra | O8: =+L10+L12 -> 487.35432
D9: Bruto | E9: SS | F9: Desemp | G9: IRPF | H9: Sueldo | I9: Ingresado | J9: Diferencia | L9: Paga Extra | N9: Vacaciones | O9: =9.55*25500/365 -> 667.19178 | Q9: 2025
B10: 2025 | C10: 45658 | D10: 1821.51 | E10: =(D10+L10)*0.0483 -> 102.64185 | F10: =(D10+L10)*0.0165 -> 35.063985 | G10: =D10*0.13 -> 236.7963 | H10: =D10-E10-G10-F10 -> 1447.0079 | I10: 1447.01 | J10: =IF(ISBLANK(I10)," ",IF(I10-H10<0.01,"Correcto ",IF(I10-H10<0.01,"Faltan","Sobran"))) -> Correcto | K10: =IF(ISBLANK(I10)," ",IF(ABS(I10-H10)<0.01," ",I10-H10)) | L10: =303.58 -> 303.58 | O10: =SUM(O8:O9) -> 1154.5461 | Q10: 44562 | R10: L | S10: M | T10: X | U10: J | V10: V | W10: S | X10: D | Y10: L | Z10: M | AA10: X | AB10: J | AC10: V | AD10: S | AE10: D | AF10: L | AG10: M | AH10: X | AI10: J | AJ10: V | AK10: S | AL10: D | AM10: L | AN10: M | AO10: X | AP10: J | AQ10: V | AR10: S | AS10: D | AT10: L | AU10: M | AV10: X | AW10: J | AX10: V | AY10: S | AZ10: D | BA10: L | BB10: M
C11: Bonus | D11: 1160.16 | E11: =(D11+L11)*0.0483 -> 56.035728 | F11: =(D11+L11)*0.0165 -> 19.14264 | G11: =D11*0.13 -> 150.8208 | H11: =D11-E11-G11-F11 -> 934.16083 | I11: 934.2 | J11: =IF(ISBLANK(I11)," ",IF(I11-H11<0.01,"Correcto ",IF(I11-H11<0.01,"Faltan","Sobran"))) -> Sobran | K11: =IF(ISBLANK(I11)," ",IF(ABS(I11-H11)<0.01," ",I11-H11)) -> 0.039168 | Q11: ENE | T11: 1 | U11: 2 | V11: 3 | W11: 4 | X11: 5 | Y11: 6 | Z11: 7 | AA11: 8 | AB11: 9 | AC11: 10 | AD11: 11 | AE11: 12 | AF11: 13 | AG11: 14 | AH11: 15 | AI11: 16 | AJ11: 17 | AK11: 18 | AL11: 19 | AM11: 20 | AN11: 21 | AO11: 22 | AP11: 23 | AQ11: 24 | AR11: 25 | AS11: 26 | AT11: 27 | AU11: 28 | AV11: 29 | AW11: 30 | AX11: 31
C12: 45689 | D12: 1170.3 | E12: =2125.19*0.0483 -> 102.64668 | F12: =2125.19*0.0165 -> 35.065635 | G12: =1170.3*$N$41 -> 163.842 | H12: =D12-E12-G12-F12 -> 868.74569 | I12: 868.74 | J12: =IF(ISBLANK(I12)," ",IF(I12-H12<0.01,"Correcto ",IF(I12-H12<0.01,"Faltan","Sobran"))) -> Correcto | K12: =IF(ISBLANK(I12)," ",IF(ABS(I12-H12)<0.01," ",I12-H12)) | L12: =+'feb mar 25 baja'!F10 -> 183.77432 | Q12: FEB | W12: 1 | X12: 2 | Y12: 3 | Z12: 4 | AA12: 5 | AB12: 6 | AC12: 7 | AD12: 8 | AE12: 9 | AF12: 10 | AG12: 11 | AH12: 12 | AI12: 13 | AJ12: 14 | AK12: 15 | AL12: 16 | AM12: 17 | AN12: 18 | AO12: 19 | AP12: 20 | AQ12: 21 | AR12: 22 | AS12: 23 | AT12: 24 | AU12: 25 | AV12: 26 | AW12: 27 | AX12: 28
C13: 45717 | D13: =1647.03 -> 1647.03 | E13: =2125.19*0.0483 -> 102.64668 | F13: =2125.19*0.0165 -> 35.065635 | G13: =D13*$N$41 -> 230.5842 | H13: =D13-E13-G13-F13 -> 1278.7335 | I13: 1278.73 | J13: =IF(ISBLANK(I13)," ",IF(I13-H13<0.01,"Correcto ",IF(I13-H13<0.01,"Faltan","Sobran"))) -> Correcto | K13: =IF(ISBLANK(I13)," ",IF(ABS(I13-H13)<0.01," ",I13-H13)) | N13: Rend trabajo 2024 | O13: =SUM(D10:D24) -> 8653.7061 | Q13: MAR | W13: 1 | X13: 2 | Y13: 3 | Z13: 4 | AA13: 5 | AB13: 6 | AC13: 7 | AD13: 8 | AE13: 9 | AF13: 10 | AG13: 11 | AH13: 12 | AI13: 13 | AJ13: 14 | AK13: 15 | AL13: 16 | AM13: 17 | AN13: 18 | AO13: 19 | AP13: 20 | AQ13: 21 | AR13: 22 | AS13: 23 | AT13: 24 | AU13: 25 | AV13: 26 | AW13: 27 | AX13: 28 | AY13: 29 | AZ13: 30 | BA13: 31
C14: 45748 | D14: =53.13*30 -> 1593.9 | E14: =2125.19*0.0483 -> 102.64668 | F14: =2125.19*0.0165 -> 35.065635 | G14: =+(D14+L10+L12)*14% -> 291.37561 | H14: =D14-E14-G14-F14 -> 1164.8121 | I14: 1164.81 | J14: =IF(ISBLANK(I14)," ",IF(I14-H14<0.01,"Correcto ",IF(I14-H14<0.01,"Faltan","Sobran"))) -> Correcto | K14: =IF(ISBLANK(I14)," ",IF(ABS(I14-H14)<0.01," ",I14-H14)) | N14: Gastos Deducibles SS | O14: =SUM(E10:F24) -> 706.21597 | Q14: ABR | S14: 1 | T14: 2 | U14: 3 | V14: 4 | W14: 5 | X14: 6 | Y14: 7 | Z14: 8 | AA14: 9 | AB14: 10 | AC14: 11 | AD14: 12 | AE14: 13 | AF14: 14 | AG14: 15 | AH14: 16 | AI14: 17 | AJ14: 18 | AK14: 19 | AL14: 20 | AM14: 21 | AN14: 22 | AO14: 23 | AP14: 24 | AQ14: 25 | AR14: 26 | AS14: 27 | AT14: 28 | AU14: 29 | AV14: 30
C15: FINIQUITO | D15: =+O10 -> 1154.5461 | E15: =(D15+L15)*0.0483 -> 55.764577 | F15: =(D15+L15)*0.0165 -> 19.050011 | G15: =D15*0.13 -> 150.09099 | H15: =D15-E15-G15-F15 -> 929.64052 | I15: 929.64 | J15: =IF(ISBLANK(I15)," ",IF(I15-H15<0.01,"Correcto ",IF(I15-H15<0.01,"Faltan","Sobran"))) -> Correcto | K15: =IF(ISBLANK(I15)," ",IF(ABS(I15-H15)<0.01," ",I15-H15)) | N15: IRPF | O15: =SUM(G10:G24) -> 1237.3199
C16: BAJA MUTUA | D16: 106.26 | E16: =(D16+L16)*0.0483 -> 5.132358 | F16: =(E16+M16)*0.0483 -> 0.24789289 | G16: 13.81 | H16: =D16-E16-G16-F16 -> 87.069749 | I16: 92.45 | J16: =IF(ISBLANK(I16)," ",IF(ABS(I16-H16)<0.01,"Correcto ",IF(ABS(I16-H16)>0.01,"Faltan","Sobran"))) -> Faltan | K16: =IF(ISBLANK(I16)," ",IF(ABS(I16-H16)<0.01," ",I16-H16)) -> 5.3802509 | N16: 0.14
H17: =D17-E17-G17-F17 -> 0 | J17: =IF(ISBLANK(I17)," ",IF(ABS(I17-H17)<0.01,"Correcto ",IF(ABS(I17-H17)>0.01,"Faltan","Sobran"))) | K17: =IF(ISBLANK(I17)," ",IF(ABS(I17-H17)<0.01," ",I17-H17))
H18: =D18-E18-G18-F18 -> 0 | J18: =IF(ISBLANK(I18)," ",IF(ABS(I18-H18)<0.01,"Correcto ",IF(ABS(I18-H18)>0.01,"Faltan","Sobran"))) | K18: =IF(ISBLANK(I18)," ",IF(ABS(I18-H18)<0.01," ",I18-H18))
H19: =D19-E19-G19-F19 -> 0 | J19: =IF(ISBLANK(I19)," ",IF(ABS(I19-H19)<0.01,"Correcto ",IF(ABS(I19-H19)>0.01,"Faltan","Sobran"))) | K19: =IF(ISBLANK(I19)," ",IF(ABS(I19-H19)<0.01," ",I19-H19)) | N19: VACACIONES | O19: 22
H20: =D20-E20-G20-F20 -> 0 | J20: =IF(ISBLANK(I20)," ",IF(ABS(I20-H20)<0.01,"Correcto ",IF(ABS(I20-H20)>0.01,"Faltan","Sobran"))) | K20: =IF(ISBLANK(I20)," ",IF(ABS(I20-H20)<0.01," ",I20-H20))
H21: =D21-E21-G21-F21 -> 0 | J21: =IF(ISBLANK(I21)," ",IF(ABS(I21-H21)<0.01,"Correcto ",IF(ABS(I21-H21)>0.01,"Faltan","Sobran"))) | K21: =IF(ISBLANK(I21)," ",IF(ABS(I21-H21)<0.01," ",I21-H21))
H22: =D22-E22-G22-F22 -> 0 | J22: =IF(ISBLANK(I22)," ",IF(ABS(I22-H22)<0.01,"Correcto ",IF(ABS(I22-H22)>0.01,"Faltan","Sobran"))) | K22: =IF(ISBLANK(I22)," ",IF(ABS(I22-H22)<0.01," ",I22-H22))
H23: =D23-E23-G23-F23 -> 0 | J23: =IF(ISBLANK(I23)," ",IF(ABS(I23-H23)<0.01,"Correcto ",IF(ABS(I23-H23)>0.01,"Faltan","Sobran"))) | K23: =IF(ISBLANK(I23)," ",IF(ABS(I23-H23)<0.01," ",I23-H23))
H24: =D24-E24-G24-F24 -> 0 | J24: =IF(ISBLANK(I24)," ",IF(ABS(I24-H24)<0.01,"Correcto ",IF(ABS(I24-H24)>0.01,"Faltan","Sobran"))) | K24: =IF(ISBLANK(I24)," ",IF(I24-H24<0.01," ",I24-H24))
D25: =SUM(D10:D24) -> 8653.7061 | E25: =SUM(E10:E24) -> 527.51454 | F25: =SUM(F10:F24) -> 178.70143 | G25: =SUM(G10:G24) -> 1237.3199 | H25: =SUM(H10:H24) -> 6710.1702 | I25: =SUM(I10:I24) -> 6715.58
D26: =D25-E25-G25-F25 -> 6710.1702
I27: 2025 | J27: 2550 | K27: Cumplimiento
I28: Cierres | J28: 0.4 | K28: 0 | L28: =J28*K28*$O$52 -> 0
I29: Ventas | J29: 0.4 | K29: 0 | L29: =J29*K29*$O$52 -> 0 | M29: 173
I30: NPS | J30: 0.2 | K30: 0 | L30: =J30*K30*$O$52 -> 0
K31: Extra Beneficios | L31: =SUM(L28:L30) -> 0
D34: Bruto | E34: SS | F34: Desemp | G34: IRPF | H34: Sueldo | I34: Ingresado | J34: Diferencia | L34: Paga Extra | Q34: 2024
B35: 2024 | C35: 45292 | D35: =24000*1.03/14 -> 1765.7143 | E35: =(D35+L35)*0.0482 -> 99.291966 | F35: =(D35+L35)*0.0165 -> 33.989988 | G35: =D35*0.12 -> 211.88571 | H35: =D35-E35-G35-F35 -> 1420.5466 | I35: 1420.54 | J35: =IF(ISBLANK(I35)," ",IF(ABS(I35-H35)<0.01,"Correcto ",IF(ABS(I35-H35)>0.01,"Faltan","Sobran"))) -> Correcto | K35: =IF(ISBLANK(I35)," ",IF(ABS(I35-H35)<0.01," ",I35-H35)) | L35: =1765.71/6 -> 294.285 | Q35: 44562 | R35: L | S35: M | T35: X | U35: J | V35: V | W35: S | X35: D | Y35: L | Z35: M | AA35: X | AB35: J | AC35: V | AD35: S | AE35: D | AF35: L | AG35: M | AH35: X | AI35: J | AJ35: V | AK35: S | AL35: D | AM35: L | AN35: M | AO35: X | AP35: J | AQ35: V | AR35: S | AS35: D | AT35: L | AU35: M | AV35: X | AW35: J | AX35: V | AY35: S | AZ35: D | BA35: L | BB35: M
C36: Bonus | D36: 240.05 | E36: =(D36+L36)*0.0482 -> 11.57041 | F36: =(D36+L36)*0.0165 -> 3.960825 | G36: =D36*0.12 -> 28.806 | H36: =D36-E36-G36-F36 -> 195.71276 | I36: 195.72 | J36: =IF(ISBLANK(I36)," ",IF(ABS(I36-H36)<0.01,"Correcto ",IF(ABS(I36-H36)>0.01,"Faltan","Sobran"))) -> Correcto | K36: =IF(ISBLANK(I36)," ",IF(ABS(I36-H36)<0.01," ",I36-H36)) | Q36: ENE | R36: 45292 | S36: 45293 | T36: 45294 | U36: 45295 | V36: 45296 | W36: 45297 | X36: 45298 | Y36: 45299 | Z36: 45300 | AA36: 45301 | AB36: 45302 | AC36: 45303 | AD36: 45304 | AE36: 45305 | AF36: 45306 | AG36: 45307 | AH36: 45308 | AI36: 45309 | AJ36: 45310 | AK36: 45311 | AL36: 45312 | AM36: 45313 | AN36: 45314 | AO36: 45315 | AP36: 45316 | AQ36: 45317 | AR36: 45318 | AS36: 45319 | AT36: 45320 | AU36: 45321 | AV36: 45322
C37: 45323 | D37: =24000*1.03/14 -> 1765.7143 | E37: =(D37+L37)*0.0482 -> 99.291966 | F37: =(D37+L37)*0.0165 -> 33.989988 | G37: =D37*$N$41 -> 247.2 | H37: =D37-E37-G37-F37 -> 1385.2323 | I37: 1385.23 | J37: =IF(ISBLANK(I37)," ",IF(ABS(I37-H37)<0.01,"Correcto ",IF(ABS(I37-H37)>0.01,"Faltan","Sobran"))) -> Correcto | K37: =IF(ISBLANK(I37)," ",IF(ABS(I37-H37)<0.01," ",I37-H37)) | L37: 294.285 | Q37: FEB | U37: 45323 | V37: 45324 | W37: 45325 | X37: 45326 | Y37: 45327 | Z37: 45328 | AA37: 45329 | AB37: 45330 | AC37: 45331 | AD37: 45332 | AE37: 45333 | AF37: 45334 | AG37: 45335 | AH37: 45336 | AI37: 45337 | AJ37: 45338 | AK37: 45339 | AL37: 45340 | AM37: 45341 | AN37: 45342 | AO37: 45343 | AP37: 45344 | AQ37: 45345 | AR37: 45346 | AS37: 45347 | AT37: 45348 | AU37: 45349 | AV37: 45350 | AW37: 45351
C38: 45352 | D38: =24000*1.03/14 -> 1765.7143 | E38: =(D38+L38)*0.0482 -> 99.291966 | F38: =(D38+L38)*0.0165 -> 33.989988 | G38: =D38*$N$41 -> 247.2 | H38: =D38-E38-G38-F38 -> 1385.2323 | I38: 1385.23 | J38: =IF(ISBLANK(I38)," ",IF(ABS(I38-H38)<0.01,"Correcto ",IF(ABS(I38-H38)>0.01,"Faltan","Sobran"))) -> Correcto | K38: =IF(ISBLANK(I38)," ",IF(ABS(I38-H38)<0.01," ",I38-H38)) | L38: 294.285 | N38: Rend trabajo 2023 | O38: =SUM(D35:D49) -> 24960.05 | Q38: MAR | V38: 45352 | W38: 45353 | X38: 45354 | Y38: 45355 | Z38: 45356 | AA38: 45357 | AB38: 45358 | AC38: 45359 | AD38: 45360 | AE38: 45361 | AF38: 45362 | AG38: 45363 | AH38: 45364 | AI38: 45365 | AJ38: 45366 | AK38: 45367 | AL38: 45368 | AM38: 45369 | AN38: 45370 | AO38: 45371 | AP38: 45372 | AQ38: 45373 | AR38: 45374 | AS38: 45375 | AT38: 45376 | AU38: 45377 | AV38: 45378 | AW38: 45379 | AX38: 45380 | AY38: 45381 | AZ38: 45382
C39: 45383 | D39: =24000*1.03/14 -> 1765.7143 | E39: =(D39+L39)*0.0482 -> 99.291966 | F39: =(D39+L39)*0.0165 -> 33.989988 | G39: =D39*$N$41 -> 247.2 | H39: =D39-E39-G39-F39 -> 1385.2323 | I39: 1385.23 | J39: =IF(ISBLANK(I39)," ",IF(ABS(I39-H39)<0.01,"Correcto ",IF(ABS(I39-H39)>0.01,"Faltan","Sobran"))) -> Correcto | K39: =IF(ISBLANK(I39)," ",IF(ABS(I39-H39)<0.01," ",I39-H39)) | L39: 294.285 | N39: Gastos Deducibles SS | O39: =SUM(E35:F49) -> 1614.9147 | Q39: ABR | R39: 45383 | S39: 45384 | T39: 45385 | U39: 45386 | V39: 45387 | W39: 45388 | X39: 45389 | Y39: 45390 | Z39: 45391 | AA39: 45392 | AB39: 45393 | AC39: 45394 | AD39: 45395 | AE39: 45396 | AF39: 45397 | AG39: 45398 | AH39: 45399 | AI39: 45400 | AJ39: 45401 | AK39: 45402 | AL39: 45403 | AM39: 45404 | AN39: 45405 | AO39: 45406 | AP39: 45407 | AQ39: 45408 | AR39: 45409 | AS39: 45410 | AT39: 45411 | AU39: 45412
C40: 45413 | D40: =24000*1.03/14 -> 1765.7143 | E40: =(D40+L40)*0.0482 -> 99.291966 | F40: =(D40+L40)*0.0165 -> 33.989988 | G40: =D40*$N$41 -> 247.2 | H40: =D40-E40-G40-F40 -> 1385.2323 | I40: 1385.23 | J40: =IF(ISBLANK(I40)," ",IF(ABS(I40-H40)<0.01,"Correcto ",IF(ABS(I40-H40)>0.01,"Faltan","Sobran"))) -> Correcto | K40: =IF(ISBLANK(I40)," ",IF(ABS(I40-H40)<0.01," ",I40-H40)) | L40: 294.285 | N40: IRPF | O40: =SUM(G35:G49) -> 3454.2917 | Q40: MAY | T40: 45413 | U40: 45414 | V40: 45415 | W40: 45416 | X40: 45417 | Y40: 45418 | Z40: 45419 | AA40: 45420 | AB40: 45421 | AC40: 45422 | AD40: 45423 | AE40: 45424 | AF40: 45425 | AG40: 45426 | AH40: 45427 | AI40: 45428 | AJ40: 45429 | AK40: 45430 | AL40: 45431 | AM40: 45432 | AN40: 45433 | AO40: 45434 | AP40: 45435 | AQ40: 45436 | AR40: 45437 | AS40: 45438 | AT40: 45439 | AU40: 45440 | AV40: 45441 | AW40: 45442 | AX40: 45443
C41: 45444 | D41: =24000*1.03/14 -> 1765.7143 | E41: =(D41+L41)*0.0482 -> 99.291966 | F41: =(D41+L41)*0.0165 -> 33.989988 | G41: =D41*$N$41 -> 247.2 | H41: =D41-E41-G41-F41 -> 1385.2323 | I41: 1385.23 | J41: =IF(ISBLANK(I41)," ",IF(ABS(I41-H41)<0.01,"Correcto ",IF(ABS(I41-H41)>0.01,"Faltan","Sobran"))) -> Correcto | K41: =IF(ISBLANK(I41)," ",IF(ABS(I41-H41)<0.01," ",I41-H41)) | L41: 294.285 | N41: 0.14 | Q41: JUN | W41: 45444 | X41: 45445 | Y41: 45446 | Z41: 45447 | AA41: 45448 | AB41: 45449 | AC41: 45450 | AD41: 45451 | AE41: 45452 | AF41: 45453 | AG41: 45454 | AH41: 45455 | AI41: 45456 | AJ41: 45457 | AK41: 45458 | AL41: 45459 | AM41: 45460 | AN41: 45461 | AO41: 45462 | AP41: 45463 | AQ41: 45464 | AR41: 45465 | AS41: 45466 | AT41: 45467 | AU41: 45468 | AV41: 45469 | AW41: 45470 | AX41: 45471 | AY41: 45472 | AZ41: 45473
C42: Extra JUL24 | D42: =24000*1.03/14 -> 1765.7143 | G42: =D42*$N$41 -> 247.2 | H42: =D42-E42-G42-F42 -> 1518.5143 | I42: 1518.51 | J42: =IF(ISBLANK(I42)," ",IF(ABS(I42-H42)<0.01,"Correcto ",IF(ABS(I42-H42)>0.01,"Faltan","Sobran"))) -> Correcto | K42: =IF(ISBLANK(I42)," ",IF(ABS(I42-H42)<0.01," ",I42-H42)) | Q42: JUL | R42: 45474 | S42: 45475 | T42: 45476 | U42: 45477 | V42: 45478 | W42: 45479 | X42: 45480 | Y42: 45481 | Z42: 45482 | AA42: 45483 | AB42: 45484 | AC42: 45485 | AD42: 45486 | AE42: 45487 | AF42: 45488 | AG42: 45489 | AH42: 45490 | AI42: 45491 | AJ42: 45492 | AK42: 45493 | AL42: 45494 | AM42: 45495 | AN42: 45496 | AO42: 45497 | AP42: 45498 | AQ42: 45499 | AR42: 45500 | AS42: 45501 | AT42: 45502 | AU42: 45503 | AV42: 45504
C43: 45474 | D43: =24000*1.03/14 -> 1765.7143 | E43: =(D43+L43)*0.0482 -> 99.291966 | F43: =(D43+L43)*0.0165 -> 33.989988 | G43: =D43*$N$41 -> 247.2 | H43: =D43-E43-G43-F43 -> 1385.2323 | I43: 1385.23 | J43: =IF(ISBLANK(I43)," ",IF(ABS(I43-H43)<0.01,"Correcto ",IF(ABS(I43-H43)>0.01,"Faltan","Sobran"))) -> Correcto | K43: =IF(ISBLANK(I43)," ",IF(ABS(I43-H43)<0.01," ",I43-H43)) | L43: 294.285 | Q43: AGO | U43: 45505 | V43: 45506 | W43: 45507 | X43: 45508 | Y43: 45509 | Z43: 45510 | AA43: 45511 | AB43: 45512 | AC43: 45513 | AD43: 45514 | AE43: 45515 | AF43: 45516 | AG43: 45517 | AH43: 45518 | AI43: 45519 | AJ43: 45520 | AK43: 45521 | AL43: 45522 | AM43: 45523 | AN43: 45524 | AO43: 45525 | AP43: 45526 | AQ43: 45527 | AR43: 45528 | AS43: 45529 | AT43: 45530 | AU43: 45531 | AV43: 45532 | AW43: 45533 | AX43: 45534 | AY43: 45535
C44: 45505 | D44: =24000*1.03/14 -> 1765.7143 | E44: =(D44+L44)*0.0482 -> 99.291966 | F44: =(D44+L44)*0.0165 -> 33.989988 | G44: =D44*$N$41 -> 247.2 | H44: =D44-E44-G44-F44 -> 1385.2323 | I44: 1385.23 | J44: =IF(ISBLANK(I44)," ",IF(ABS(I44-H44)<0.01,"Correcto ",IF(ABS(I44-H44)>0.01,"Faltan","Sobran"))) -> Correcto | K44: =IF(ISBLANK(I44)," ",IF(ABS(I44-H44)<0.01," ",I44-H44)) | L44: 294.285 | N44: VACACIONES | O44: =22+3 -> 25 | Q44: SEP | X44: 45536 | Y44: 45537 | Z44: 45538 | AA44: 45539 | AB44: 45540 | AC44: 45541 | AD44: 45542 | AE44: 45543 | AF44: 45544 | AG44: 45545 | AH44: 45546 | AI44: 45547 | AJ44: 45548 | AK44: 45549 | AL44: 45550 | AM44: 45551 | AN44: 45552 | AO44: 45553 | AP44: 45554 | AQ44: 45555 | AR44: 45556 | AS44: 45557 | AT44: 45558 | AU44: 45559 | AV44: 45560 | AW44: 45561 | AX44: 45562 | AY44: 45563 | AZ44: 45564 | BA44: 45565
C45: 45536 | D45: =24000*1.03/14 -> 1765.7143 | E45: =(D45+L45)*0.0482 -> 99.291966 | F45: =(D45+L45)*0.0165 -> 33.989988 | G45: =D45*$N$41 -> 247.2 | H45: =D45-E45-G45-F45 -> 1385.2323 | I45: 1385.23 | J45: =IF(ISBLANK(I45)," ",IF(ABS(I45-H45)<0.01,"Correcto ",IF(ABS(I45-H45)>0.01,"Faltan","Sobran"))) -> Correcto | K45: =IF(ISBLANK(I45)," ",IF(ABS(I45-H45)<0.01," ",I45-H45)) | L45: 294.285 | N45: Viaje sep | O45: 6 | Q45: OCT | S45: 45566 | T45: 45567 | U45: 45568 | V45: 45569 | W45: 45570 | X45: 45571 | Y45: 45572 | Z45: 45573 | AA45: 45574 | AB45: 45575 | AC45: 45576 | AD45: 45577 | AE45: 45578 | AF45: 45579 | AG45: 45580 | AH45: 45581 | AI45: 45582 | AJ45: 45583 | AK45: 45584 | AL45: 45585 | AM45: 45586 | AN45: 45587 | AO45: 45588 | AP45: 45589 | AQ45: 45590 | AR45: 45591 | AS45: 45592 | AT45: 45593 | AU45: 45594 | AV45: 45595 | AW45: 45596
C46: 45566 | D46: =24000*1.03/14 -> 1765.7143 | E46: =(D46+L46)*0.0482 -> 99.291966 | F46: =(D46+L46)*0.0165 -> 33.989988 | G46: =D46*$N$41 -> 247.2 | H46: =D46-E46-G46-F46 -> 1385.2323 | I46: 1385.23 | J46: =IF(ISBLANK(I46)," ",IF(ABS(I46-H46)<0.01,"Correcto ",IF(ABS(I46-H46)>0.01,"Faltan","Sobran"))) -> Correcto | K46: =IF(ISBLANK(I46)," ",IF(ABS(I46-H46)<0.01," ",I46-H46)) | L46: 294.285 | N46: Agosto | O46: 12 | Q46: NOV | V46: 45597 | W46: 45598 | X46: 45599 | Y46: 45600 | Z46: 45601 | AA46: 45602 | AB46: 45603 | AC46: 45604 | AD46: 45605 | AE46: 45606 | AF46: 45607 | AG46: 45608 | AH46: 45609 | AI46: 45610 | AJ46: 45611 | AK46: 45612 | AL46: 45613 | AM46: 45614 | AN46: 45615 | AO46: 45616 | AP46: 45617 | AQ46: 45618 | AR46: 45619 | AS46: 45620 | AT46: 45621 | AU46: 45622 | AV46: 45623 | AW46: 45624 | AX46: 45625 | AY46: 45626
C47: 45597 | D47: =24000*1.03/14 -> 1765.7143 | E47: =(D47+L47)*0.0482 -> 99.291966 | F47: =(D47+L47)*0.0165 -> 33.989988 | G47: =D47*$N$41 -> 247.2 | H47: =D47-E47-G47-F47 -> 1385.2323 | I47: 1385.23 | J47: =IF(ISBLANK(I47)," ",IF(ABS(I47-H47)<0.01,"Correcto ",IF(ABS(I47-H47)>0.01,"Faltan","Sobran"))) -> Correcto | K47: =IF(ISBLANK(I47)," ",IF(ABS(I47-H47)<0.01," ",I47-H47)) | L47: 294.285 | N47: Crucero jun | O47: 6 | Q47: DIC | X47: 45627 | Y47: 45628 | Z47: 45629 | AA47: 45630 | AB47: 45631 | AC47: 45632 | AD47: 45633 | AE47: 45634 | AF47: 45635 | AG47: 45636 | AH47: 45637 | AI47: 45638 | AJ47: 45639 | AK47: 45640 | AL47: 45641 | AM47: 45642 | AN47: 45643 | AO47: 45644 | AP47: 45645 | AQ47: 45646 | AR47: 45647 | AS47: 45648 | AT47: 45649 | AU47: 45650 | AV47: 45651 | AW47: 45652 | AX47: 45653 | AY47: 45654 | AZ47: 45655 | BA47: 45656 | BB47: 45657
C48: 45627 | D48: =24000*1.03/14 -> 1765.7143 | E48: =(D48+L48)*0.0482 -> 99.291966 | F48: =(D48+L48)*0.0165 -> 33.989988 | G48: =D48*$N$41 -> 247.2 | H48: =D48-E48-G48-F48 -> 1385.2323 | I48: 1385.23 | J48: =IF(ISBLANK(I48)," ",IF(ABS(I48-H48)<0.01,"Correcto ",IF(ABS(I48-H48)>0.01,"Faltan","Sobran"))) -> Correcto | K48: =IF(ISBLANK(I48)," ",IF(ABS(I48-H48)<0.01," ",I48-H48)) | L48: 294.285 | N48: Julio | O48: =O44-O45-O46-O47 -> 1
C49: Extra DIC24 | D49: =24000*1.03/14 -> 1765.7143 | G49: =D49*$N$41 -> 247.2 | H49: =D49-E49-G49-F49 -> 1518.5143 | I49: 1518.51 | J49: =IF(ISBLANK(I49)," ",IF(ABS(I49-H49)<0.01,"Correcto ",IF(ABS(I49-H49)>0.01,"Faltan","Sobran"))) -> Correcto | K49: =IF(ISBLANK(I49)," ",IF(I49-H49<0.01," ",I49-H49))
D50: =SUM(D35:D49) -> 24960.05 | E50: =SUM(E35:E49) -> 1203.074 | F50: =SUM(F35:F49) -> 411.84068 | G50: =SUM(G35:G49) -> 3454.2917 | H50: =SUM(H35:H49) -> 19890.844 | I50: =SUM(I35:I49) -> 19890.81
D51: =D50-E50-G50-F50 -> 19890.844
I52: 2023 | J52: 1714.29 | K52: Cumplimiento | N52: 2024 | O52: 2472 | P52: Cumplimiento
I53: Cierres | J53: 0.25 | K53: 0.3933 | L53: =J53*K53*$J$52 -> 168.55756 | N53: Cierres | O53: 0.4 | P53: 0.6733 | Q53: =O53*P53*$O$52 -> 665.75904
I54: Ventas | J54: 0.25 | K54: 0 | L54: =J54*K54*$J$52 -> 0 | N54: Ventas | O54: 0.4 | P54: 0 | Q54: =O54*P54*$O$52 -> 0
I55: NPS | J55: 0.25 | K55: 0 | L55: =J55*K55*$J$52 -> 0 | N55: NPS | O55: 0.2 | P55: 1 | Q55: =O55*P55*$O$52 -> 494.4
I56: Específico | J56: 0.25 | K56: 0 | L56: =J56*K56*$J$52 -> 0 | P56: Extra Beneficios | Q56: =SUM(Q53:Q55) -> 1160.159
K57: Extra Beneficios | L57: =SUM(L53:L56) -> 168.55756
D60: Bruto | E60: SS | F60: Desemp | G60: IRPF | H60: Sueldo | I60: Ingresado | J60: Diferencia | L60: Paga Extra | Q60: 2023
B61: 2023 | C61: 44927 | D61: 1714.29 | E61: =(D61+L61)*0.048 -> 96.00024 | F61: =(D61+L61)*0.0165 -> 33.000082 | G61: =D61*0.12 -> 205.7148 | H61: =D61-E61-G61-F61 -> 1379.5749 | I61: 1379.58 | J61: =IF(ISBLANK(I61)," ",IF(I61-H61<0.01,"Correcto ",IF(I61-H61<0.01,"Faltan","Sobran"))) -> Correcto | K61: =IF(ISBLANK(I61)," ",IF(I61-H61<0.01," ",I61-H61)) | L61: =1714.29/6 -> 285.715 | Q61: 44562 | R61: L | S61: M | T61: X | U61: J | V61: V | W61: S | X61: D | Y61: L | Z61: M | AA61: X | AB61: J | AC61: V | AD61: S | AE61: D | AF61: L | AG61: M | AH61: X | AI61: J | AJ61: V | AK61: S | AL61: D | AM61: L | AN61: M | AO61: X | AP61: J | AQ61: V | AR61: S | AS61: D | AT61: L | AU61: M | AV61: X | AW61: J | AX61: V | AY61: S | AZ61: D | BA61: L | BB61: M
C62: Bonus | D62: 333.46 | E62: =(D62+L62)*0.048 -> 16.00608 | F62: =(D62+L62)*0.0165 -> 5.50209 | G62: =D62*0.12 -> 40.0152 | H62: =D62-E62-G62-F62 -> 271.93663 | I62: 272.7 | J62: =IF(ISBLANK(I62)," ",IF(I62-H62<0.01,"Correcto ",IF(I62-H62<0.01,"Faltan","Sobran"))) -> Sobran | K62: =IF(ISBLANK(I62)," ",IF(I62-H62<0.01," ",I62-H62)) -> 0.76337
C63: 44958 | D63: 1714.29 | E63: =(D63+L63)*0.048 -> 96.00024 | F63: =(D63+L63)*0.0165 -> 33.000082 | G63: =D63*$N$67 -> 240.0006 | H63: =D63-E63-G63-F63 -> 1345.2891 | I63: 1345.29 | J63: =IF(ISBLANK(I63)," ",IF(I63-H63<0.01,"Correcto ",IF(I63-H63<0.01,"Faltan","Sobran"))) -> Correcto | K63: =IF(ISBLANK(I63)," ",IF(I63-H63<0.01," ",I63-H63)) | L63: =1714.29/6 -> 285.715 | Q63: ENE | Y63: 2 | Z63: 3 | AA63: 4 | AB63: 5 | AF63: 9 | AG63: 10 | AH63: 11 | AI63: 12 | AJ63: 13 | AM63: 16 | AN63: 17 | AO63: 18 | AP63: 19 | AQ63: 20 | AT63: 23 | AU63: 24 | AV63: 25 | AW63: 26 | AX63: 27 | BA63: 30 | BB63: 31
C64: 44986 | D64: =1714.29 -> 1714.29 | E64: =(D64+L64)*0.048 -> 96.00024 | F64: =(D64+L64)*0.0165 -> 33.000082 | G64: =D64*$N$67 -> 240.0006 | H64: =D64-E64-G64-F64 -> 1345.2891 | I64: 1345.29 | J64: =IF(ISBLANK(I64)," ",IF(I64-H64<0.01,"Correcto ",IF(I64-H64<0.01,"Faltan","Sobran"))) -> Correcto | K64: =IF(ISBLANK(I64)," ",IF(I64-H64<0.01," ",I64-H64)) | L64: =1714.29/6 -> 285.715 | N64: Rend trabajo 2023 | O64: =SUM(D61:D75) -> 24333.52 | Q64: FEB | T64: 1 | U64: 2 | V64: 3 | Y64: 6 | Z64: 7 | AA64: 8 | AB64: 9 | AC64: 10 | AF64: 13 | AG64: 14 | AH64: 15 | AI64: 16 | AJ64: 17 | AM64: 20 | AN64: 21 | AO64: 22 | AP64: 23 | AQ64: 24 | AT64: 27 | AU64: 28
C65: 45017 | D65: 1714.29 | E65: =(D65+L65)*0.048 -> 96.00024 | F65: =(D65+L65)*0.0165 -> 33.000082 | G65: =D65*$N$67 -> 240.0006 | H65: =D65-E65-G65-F65 -> 1345.2891 | I65: 1345.29 | J65: =IF(ISBLANK(I65)," ",IF(I65-H65<0.01,"Correcto ",IF(I65-H65<0.01,"Faltan","Sobran"))) -> Correcto | K65: =IF(ISBLANK(I65)," ",IF(I65-H65<0.01," ",I65-H65)) | L65: =1714.29/6 -> 285.715 | N65: Gastos Deducibles SS | O65: =SUM(E61:F75) -> 1565.512 | Q65: MAR | T65: 1 | U65: 2 | V65: 3 | Y65: 6 | Z65: 7 | AA65: 8 | AB65: 9 | AC65: 10 | AF65: 13 | AG65: 14 | AH65: 15 | AI65: 16 | AJ65: 17 | AM65: 20 | AN65: 21 | AO65: 22 | AP65: 23 | AQ65: 24 | AT65: 27 | AU65: 28 | AV65: 29 | AW65: 30 | AX65: 31
C66: 45047 | D66: 1714.29 | E66: =(D66+L66)*0.048 -> 96.00024 | F66: =(D66+L66)*0.0165 -> 33.000082 | G66: =D66*$N$67 -> 240.0006 | H66: =D66-E66-G66-F66 -> 1345.2891 | I66: 1345.29 | J66: =IF(ISBLANK(I66)," ",IF(I66-H66<0.01,"Correcto ",IF(I66-H66<0.01,"Faltan","Sobran"))) -> Correcto | K66: =IF(ISBLANK(I66)," ",IF(I66-H66<0.01," ",I66-H66)) | L66: =1714.29/6 -> 285.715 | N66: IRPF | O66: =SUM(G61:G75) -> 3365.7378 | Q66: ABR | Y66: 3 | Z66: 4 | AA66: 5 | AG66: 11 | AH66: 12 | AI66: 13 | AJ66: 14 | AM66: 17 | AN66: 18 | AO66: 19 | AP66: 20 | AQ66: 21 | AT66: 24 | AU66: 25 | AV66: 26 | AW66: 27
C67: 45078 | D67: 1714.29 | E67: =(D67+L67)*0.046 -> 92.00023 | F67: =(D67+L67)*0.0165 -> 33.000082 | G67: =D67*$N$67 -> 240.0006 | H67: =D67-E67-G67-F67 -> 1349.2891 | I67: 1345.29 | J67: =IF(ISBLANK(I67)," ",IF(I67-H67<0.01,"Correcto ",IF(I67-H67<0.01,"Faltan","Sobran"))) -> Correcto | K67: =IF(ISBLANK(I67)," ",IF(I67-H67<0.01," ",I67-H67)) | L67: =1714.29/6 -> 285.715 | N67: 0.14 | Q67: MAY | S67: 2 | T67: 3 | U67: 4 | V67: 5 | Y67: 8 | Z67: 9 | AA67: 10 | AB67: 11 | AC67: 12 | AF67: 15 | AG67: 16 | AH67: 17 | AI67: 18 | AJ67: 19 | AM67: 22 | AN67: 23 | AO67: 24 | AP67: 25 | AQ67: 26 | AT67: 29 | AU67: 30 | AV67: 31
C68: Extra JUL23 | D68: 1714.29 | G68: =D68*$N$67 -> 240.0006 | H68: =D68-E68-G68-F68 -> 1474.2894 | I68: 1474.29 | J68: =IF(ISBLANK(I68)," ",IF(I68-H68<0.01,"Correcto ",IF(I68-H68<0.01,"Faltan","Sobran"))) -> Correcto | K68: =IF(ISBLANK(I68)," ",IF(I68-H68<0.01," ",I68-H68)) | Q68: JUN | U68: 1 | V68: 2 | Y68: 5 | Z68: 6 | AA68: 7 | AB68: 8 | AC68: 9 | AF68: 12 | AG68: 13 | AH68: 14 | AI68: 15 | AJ68: 16 | AM68: 19 | AN68: 20 | AO68: 21 | AP68: 22 | AQ68: 23 | AT68: 26 | AU68: 27 | AV68: 28 | AW68: 29 | AX68: 30
C69: 45108 | D69: 1714.29 | E69: =(D69+L69)*0.048 -> 96.00024 | F69: =(D69+L69)*0.0165 -> 33.000082 | G69: =D69*$N$67 -> 240.0006 | H69: =D69-E69-G69-F69 -> 1345.2891 | I69: 1345.29 | J69: =IF(ISBLANK(I69)," ",IF(I69-H69<0.01,"Correcto ",IF(I69-H69<0.01,"Faltan","Sobran"))) -> Correcto | K69: =IF(ISBLANK(I69)," ",IF(I69-H69<0.01," ",I69-H69)) | L69: =1714.29/6 -> 285.715 | Q69: JUL | Y69: 3 | Z69: 4 | AA69: 5 | AB69: 6 | AC69: 7 | AF69: 10 | AG69: 11 | AH69: 12 | AI69: 13 | AJ69: 14 | AM69: 17 | AN69: 18 | AO69: 19 | AP69: 20 | AQ69: 21 | AT69: 24 | AV69: 26 | AW69: 27 | AX69: 28 | BA69: 31
C70: 45139 | D70: 1714.29 | E70: =(D70+L70)*0.048 -> 96.00024 | F70: =(D70+L70)*0.0165 -> 33.000082 | G70: =D70*$N$67 -> 240.0006 | H70: =D70-E70-G70-F70 -> 1345.2891 | I70: 1345.29 | J70: =IF(ISBLANK(I70)," ",IF(I70-H70<0.01,"Correcto ",IF(I70-H70<0.01,"Faltan","Sobran"))) -> Correcto | K70: =IF(ISBLANK(I70)," ",IF(I70-H70<0.01," ",I70-H70)) | L70: =1714.29/6 -> 285.715 | N70: VACACIONES | O70: 22 | Q70: AGO | S70: 1 | T70: 2 | U70: 3 | V70: 4 | Y70: 7 | Z70: 8 | AA70: 9 | AB70: 10 | AC70: 11 | AF70: 14 | AH70: 16 | AI70: 17 | AJ70: 18 | AM70: 21 | AN70: 22 | AO70: 23 | AP70: 24 | AQ70: 25 | AT70: 28 | AU70: 29 | AV70: 30 | AW70: 31
C71: 45170 | D71: 1714.29 | E71: =(D71+L71)*0.048 -> 96.00024 | F71: =(D71+L71)*0.0165 -> 33.000082 | G71: =D71*$N$67 -> 240.0006 | H71: =D71-E71-G71-F71 -> 1345.2891 | I71: 1345.29 | J71: =IF(ISBLANK(I71)," ",IF(I71-H71<0.01,"Correcto ",IF(I71-H71<0.01,"Faltan","Sobran"))) -> Correcto | K71: =IF(ISBLANK(I71)," ",IF(I71-H71<0.01," ",I71-H71)) | L71: =1714.29/6 -> 285.715 | N71: Viaje | O71: 10 | Q71: SEP | V71: 1 | Y71: 4 | Z71: 5 | AA71: 6 | AB71: 7 | AC71: 8 | AF71: 11 | AG71: 12 | AH71: 13 | AI71: 14 | AJ71: 15 | AM71: 18 | AN71: 19 | AO71: 20 | AP71: 21 | AQ71: 22 | AT71: 25 | AU71: 26 | AV71: 27 | AW71: 28 | AX71: 29
C72: 45200 | D72: 1714.29 | E72: =(D72+L72)*0.048 -> 96.00024 | F72: =(D72+L72)*0.0165 -> 33.000082 | G72: =D72*$N$67 -> 240.0006 | H72: =D72-E72-G72-F72 -> 1345.2891 | I72: 1345.29 | J72: =IF(ISBLANK(I72)," ",IF(I72-H72<0.01,"Correcto ",IF(I72-H72<0.01,"Faltan","Sobran"))) -> Correcto | K72: =IF(ISBLANK(I72)," ",IF(I72-H72<0.01," ",I72-H72)) | L72: =1714.29/6 -> 285.715 | N72: Agosto | O72: 9 | Q72: OCT | Y72: 2 | Z72: 3 | AA72: 4 | AB72: 5 | AC72: 6 | AF72: 9 | AG72: 10 | AH72: 11 | AJ72: 13 | AM72: 16 | AN72: 17 | AO72: 18 | AP72: 19 | AQ72: 20 | AT72: 23 | AU72: 24 | AV72: 25 | AW72: 26 | AX72: 27 | BA72: 30 | BB72: 31
C73: 45231 | D73: 1714.29 | E73: =(D73+L73)*0.048 -> 96.00024 | F73: =(D73+L73)*0.0165 -> 33.000082 | G73: =D73*$N$67 -> 240.0006 | H73: =D73-E73-G73-F73 -> 1345.2891 | I73: 1345.29 | J73: =IF(ISBLANK(I73)," ",IF(I73-H73<0.01,"Correcto ",IF(I73-H73<0.01,"Faltan","Sobran"))) -> Correcto | K73: =IF(ISBLANK(I73)," ",IF(I73-H73<0.01," ",I73-H73)) | L73: =1714.29/6 -> 285.715 | Q73: NOV | U73: 2 | V73: 3 | Y73: 6 | Z73: 7 | AA73: 8 | AB73: 9 | AC73: 10 | AF73: 13 | AG73: 14 | AH73: 15 | AI73: 16 | AJ73: 17 | AM73: 20 | AN73: 21 | AO73: 22 | AP73: 23 | AQ73: 24 | AT73: 27 | AU73: 28 | AV73: 29 | AW73: 30
C74: 45261 | D74: 1714.29 | E74: =(D74+L74)*0.048 -> 96.00024 | F74: =(D74+L74)*0.0165 -> 33.000082 | G74: =D74*$N$67 -> 240.0006 | H74: =D74-E74-G74-F74 -> 1345.2891 | I74: 1345.29 | J74: =IF(ISBLANK(I74)," ",IF(I74-H74<0.01,"Correcto ",IF(I74-H74<0.01,"Faltan","Sobran"))) -> Correcto | K74: =IF(ISBLANK(I74)," ",IF(I74-H74<0.01," ",I74-H74)) | L74: =1714.29/6 -> 285.715 | N74: Quedan | O74: =O70-O71-O72-O73 -> 3 | Q74: DIC | V74: 1 | Y74: 4 | Z74: 5 | AB74: 7 | AF74: 11 | AG74: 12 | AH74: 13 | AI74: 14 | AJ74: 15 | AM74: 18 | AN74: 19 | AO74: 20 | AP74: 21 | AQ74: 22 | AU74: 26 | AV74: 27 | AW74: 28 | AX74: 29
C75: Extra DIC23 | D75: =SUM(L69:L74) -> 1714.29 | G75: =D75*$N$67 -> 240.0006 | H75: =D75-E75-G75-F75 -> 1474.2894 | I75: 1474.29 | J75: =IF(ISBLANK(I75)," ",IF(I75-H75<0.01,"Correcto ",IF(I75-H75<0.01,"Faltan","Sobran"))) -> Correcto | K75: =IF(ISBLANK(I75)," ",IF(I75-H75<0.01," ",I75-H75))
D76: =SUM(D61:D75) -> 24333.52 | E76: =SUM(E61:E75) -> 1164.0089 | F76: =SUM(F61:F75) -> 401.50308 | G76: =SUM(G61:G75) -> 3365.7378 | H76: =SUM(H61:H75) -> 19402.27 | I76: =SUM(I61:I75) -> 19399.05
D77: =D76-E76-G76-F76 -> 19402.27
I78: 2022 | J78: 1714.29 | K78: Cumplimiento
I79: Cierres | J79: 0.25 | K79: 0 | L79: =J79*$J$79*K79 -> 0
I80: Ventas | J80: 0.25 | K80: 0 | L80: =J80*$J$79*K80 -> 0
I81: NPS | J81: 0.25 | K81: 1 | L81: =J81*$J$79*K81 -> 0.0625
I82: Específico | J82: 0.25 | K82: 0 | L82: =J82*$J$79*K82 -> 0
K83: Extra Beneficios | L83: =SUM(L79:L82) -> 0.0625
D87: Bruto | E87: SS | F87: Desemp | G87: IRPF | H87: Sueldo | I87: Ingresado | J87: Diferencia | L87: Paga Extra | Q87: 2022
B88: 2022 | C88: 44621 | D88: =1714.29/30*9 -> 514.287 | E88: =(D88+L88)*0.047 -> 28.200071 | F88: =(D88+L88)*0.0165 -> 9.9000248 | G88: =D88*$N$93 -> 66.85731 | H88: =D88-E88-G88-F88 -> 409.32959 | I88: 409.33 | J88: =IF(ISBLANK(I88)," ",IF(I88-H88<0.01,"Correcto ",IF(I88-H88<0.01,"Faltan","Sobran"))) -> Correcto | K88: =IF(ISBLANK(I88)," ",IF(I88-H88<0.01," ",I88-H88)) | L88: =1714.29/6/30*9 -> 85.7145 | Q88: 44562 | R88: L | S88: M | T88: X | U88: J | V88: V | W88: S | X88: D | Y88: L | Z88: M | AA88: X | AB88: J | AC88: V | AD88: S | AE88: D | AF88: L | AG88: M | AH88: X | AI88: J | AJ88: V | AK88: S | AL88: D | AM88: L | AN88: M | AO88: X | AP88: J | AQ88: V | AR88: S | AS88: D | AT88: L | AU88: M | AV88: X | AW88: J | AX88: V | AY88: S | AZ88: D | BA88: L | BB88: M
C89: 44652 | D89: 1714.29 | E89: =(D89+L89)*0.047 -> 94.000235 | F89: =(D89+L89)*0.0165 -> 33.000082 | G89: =D89*$N$93 -> 222.8577 | H89: =D89-E89-G89-F89 -> 1364.432 | I89: 1364.43 | J89: =IF(ISBLANK(I89)," ",IF(I89-H89<0.01,"Correcto ",IF(I89-H89<0.01,"Faltan","Sobran"))) -> Correcto | K89: =IF(ISBLANK(I89)," ",IF(I89-H89<0.01," ",I89-H89)) | L89: =1714.29/6 -> 285.715 | Q89: ENE
C90: 44682 | D90: 1714.29 | E90: =(D90+L90)*0.047 -> 94.000235 | F90: =(D90+L90)*0.0165 -> 33.000082 | G90: =D90*$N$93 -> 222.8577 | H90: =D90-E90-G90-F90 -> 1364.432 | I90: 1364.43 | J90: =IF(ISBLANK(I90)," ",IF(I90-H90<0.01,"Correcto ",IF(I90-H90<0.01,"Faltan","Sobran"))) -> Correcto | K90: =IF(ISBLANK(I90)," ",IF(I90-H90<0.01," ",I90-H90)) | L90: =1714.29/6 -> 285.715 | N90: Rend trabajo 2022 | O90: =SUM(D88:D99) -> 18600.047 | Q90: FEB
C91: 44713 | D91: 1714.29 | E91: =(D91+L91)*0.047 -> 94.000235 | F91: =(D91+L91)*0.0165 -> 33.000082 | G91: =D91*$N$93 -> 222.8577 | H91: =D91-E91-G91-F91 -> 1364.432 | I91: 1364.43 | J91: =IF(ISBLANK(I91)," ",IF(I91-H91<0.01,"Correcto ",IF(I91-H91<0.01,"Faltan","Sobran"))) -> Correcto | K91: =IF(ISBLANK(I91)," ",IF(I91-H91<0.01," ",I91-H91)) | L91: =1714.29/6 -> 285.715 | N91: Gastos Deducibles SS | O91: =SUM(E88:F98) -> 1181.103 | Q91: MAR | AO91: 44643 | AP91: 44644 | AQ91: 44645 | AT91: 44648 | AU91: 44649 | AV91: 44650 | AW91: 44651
C92: Extra JUL22 | D92: =SUM(L88:L91) -> 942.8595 | G92: =D92*$N$93 -> 122.57173 | H92: =D92-E92-G92-F92 -> 820.28776 | I92: 820.29 | J92: =IF(ISBLANK(I92)," ",IF(I92-H92<0.01,"Correcto ",IF(I92-H92<0.01,"Faltan","Sobran"))) -> Correcto | K92: =IF(ISBLANK(I92)," ",IF(I92-H92<0.01," ",I92-H92)) | N92: IRPF | O92: =SUM(G88:G99)+0.02 -> 2418.026 | Q92: ABR | Y92: 44655 | Z92: 44656 | AA92: 44657 | AB92: 44658 | AC92: 44659 | AF92: 44662 | AG92: 44663 | AH92: 44664 | AI92: 44665 | AJ92: 44666 | AM92: 44669 | AN92: 44670 | AO92: 44671 | AP92: 44672 | AQ92: 44673 | AT92: 44676 | AU92: 44677 | AV92: 44678 | AX92: 44680
C93: 44743 | D93: 1714.29 | E93: =(D93+L93)*0.047 -> 94.000235 | F93: =(D93+L93)*0.0165 -> 33.000082 | G93: =D93*$N$93 -> 222.8577 | H93: =D93-E93-G93-F93 -> 1364.432 | I93: 1364.43 | J93: =IF(ISBLANK(I93)," ",IF(I93-H93<0.01,"Correcto ",IF(I93-H93<0.01,"Faltan","Sobran"))) -> Correcto | K93: =IF(ISBLANK(I93)," ",IF(I93-H93<0.01," ",I93-H93)) | L93: =1714.29/6 -> 285.715 | N93: 0.13 | Q93: MAY | Y93: 44683 | Z93: 44684 | AA93: 44685 | AB93: 44686 | AC93: 44687 | AF93: 44690 | AG93: 44691 | AH93: 44692 | AI93: 44693 | AJ93: 44694 | AM93: 44697 | AN93: 44698 | AO93: 44699 | AP93: 44700 | AQ93: 44701 | AT93: 44704 | AU93: 44705 | AV93: 44706 | AW93: 44707 | AX93: 44708 | BA93: 44711 | BB93: 44712
C94: 44774 | D94: 1714.29 | E94: =(D94+L94)*0.047 -> 94.000235 | F94: =(D94+L94)*0.0165 -> 33.000082 | G94: =D94*$N$93 -> 222.8577 | H94: =D94-E94-G94-F94 -> 1364.432 | I94: 1364.43 | J94: =IF(ISBLANK(I94)," ",IF(I94-H94<0.01,"Correcto ",IF(I94-H94<0.01,"Faltan","Sobran"))) -> Correcto | K94: =IF(ISBLANK(I94)," ",IF(I94-H94<0.01," ",I94-H94)) | L94: =1714.29/6 -> 285.715 | Q94: JUN | T94: 44713 | U94: 44714 | V94: 44715 | Y94: 44718 | Z94: 44719 | AA94: 44720 | AB94: 44721 | AC94: 44722 | AF94: 44725 | AG94: 44726 | AH94: 44727 | AI94: 44728 | AJ94: 44729 | AM94: 44732 | AN94: 44733 | AO94: 44734 | AP94: 44735 | AQ94: 44736 | AT94: 44739 | AU94: 44740 | AV94: 44741 | AW94: 44742
C95: 44805 | D95: 1714.29 | E95: =(D95+L95)*0.047 -> 94.000235 | F95: =(D95+L95)*0.0165 -> 33.000082 | G95: =D95*$N$93 -> 222.8577 | H95: =D95-E95-G95-F95 -> 1364.432 | I95: 1364.43 | J95: =IF(ISBLANK(I95)," ",IF(I95-H95<0.01,"Correcto ",IF(I95-H95<0.01,"Faltan","Sobran"))) -> Correcto | K95: =IF(ISBLANK(I95)," ",IF(I95-H95<0.01," ",I95-H95)) | L95: =1714.29/6 -> 285.715 | Q95: JUL | V95: 44743 | Y95: 44746 | Z95: 44747 | AA95: 44748 | AB95: 44749 | AC95: 44750 | AF95: 44753 | AG95: 44754 | AH95: 44755 | AI95: 44756 | AJ95: 44757 | AM95: 44760 | AN95: 44761 | AO95: 44762 | AP95: 44763 | AQ95: 44764 | AT95: 44767 | AU95: 44768 | AV95: 44769 | AW95: 44770 | AX95: 44771
C96: 44835 | D96: 1714.29 | E96: =(D96+L96)*0.047 -> 94.000235 | F96: =(D96+L96)*0.0165 -> 33.000082 | G96: =D96*$N$93 -> 222.8577 | H96: =D96-E96-G96-F96 -> 1364.432 | I96: 1364.43 | J96: =IF(ISBLANK(I96)," ",IF(I96-H96<0.01,"Correcto ",IF(I96-H96<0.01,"Faltan","Sobran"))) -> Correcto | K96: =IF(ISBLANK(I96)," ",IF(I96-H96<0.01," ",I96-H96)) | L96: =1714.29/6 -> 285.715 | N96: VACACIONES | O96: 17 | Q96: AGO | R96: 44774 | S96: 44775 | T96: 44776 | U96: 44777 | Y96: 44781 | Z96: 44782 | AA96: 44783 | AB96: 44784 | AC96: 44785 | AG96: 44789 | AH96: 44790 | AI96: 44791 | AJ96: 44792 | AM96: 44795 | AN96: 44796 | AO96: 44797 | AP96: 44798 | AQ96: 44799 | AT96: 44802 | AU96: 44803 | AV96: 44804
C97: 44866 | D97: 1714.29 | E97: =(D97+L97)*0.047 -> 94.000235 | F97: =(D97+L97)*0.0165 -> 33.000082 | G97: =D97*$N$93 -> 222.8577 | H97: =D97-E97-G97-F97 -> 1364.432 | I97: 1364.43 | J97: =IF(ISBLANK(I97)," ",IF(I97-H97<0.01,"Correcto ",IF(I97-H97<0.01,"Faltan","Sobran"))) -> Correcto | K97: =IF(ISBLANK(I97)," ",IF(I97-H97<0.01," ",I97-H97)) | L97: =1714.29/6 -> 285.715 | N97: Viaje | O97: =COUNTA(Y97:AM97) -> 10 | Q97: SEP | U97: 44805 | V97: 44806 | Y97: 44809 | AA97: 44811 | AB97: 44812 | AC97: 44813 | AF97: 44816 | AG97: 44817 | AH97: 44818 | AI97: 44819 | AJ97: 44820 | AM97: 44823 | AN97: 44824 | AO97: 44825 | AP97: 44826 | AQ97: 44827 | AT97: 44830 | AU97: 44831 | AV97: 44832 | AW97: 44833 | AX97: 44834
C98: 44896 | D98: 1714.29 | E98: =(D98+L98)*0.047 -> 94.000235 | F98: =(D98+L98)*0.0165 -> 33.000082 | G98: =D98*$N$93 -> 222.8577 | H98: =D98-E98-G98-F98 -> 1364.432 | I98: 1364.43 | J98: =IF(ISBLANK(I98)," ",IF(I98-H98<0.01,"Correcto ",IF(I98-H98<0.01,"Faltan","Sobran"))) -> Correcto | K98: =IF(ISBLANK(I98)," ",IF(I98-H98<0.01," ",I98-H98)) | L98: =1714.29/6 -> 285.715 | N98: Agosto | O98: =COUNTA(R96:U96) -> 4 | Q98: OCT | Y98: 44837 | Z98: 44838 | AA98: 44839 | AB98: 44840 | AC98: 44841 | AF98: 44844 | AG98: 44845 | AI98: 44847 | AJ98: 44848 | AM98: 44851 | AN98: 44852 | AO98: 44853 | AP98: 44854 | AQ98: 44855 | AT98: 44858 | AU98: 44859 | AV98: 44860 | AW98: 44861 | AX98: 44862 | BA98: 44865
C99: Extra DIC22 | D99: =SUM(L93:L98) -> 1714.29 | G99: =D99*$N$93 -> 222.8577 | H99: =D99-E99-G99-F99 -> 1491.4323 | I99: 1491.43 | J99: =IF(ISBLANK(I99)," ",IF(I99-H99<0.01,"Correcto ",IF(I99-H99<0.01,"Faltan","Sobran"))) -> Correcto | K99: =IF(ISBLANK(I99)," ",IF(I99-H99<0.01," ",I99-H99)) | N99: 44927 | O99: =O96-O97-O98 -> 3 | Q99: NOV | T99: 44867 | U99: 44868 | V99: 44869 | Y99: 44872 | Z99: 44873 | AA99: 44874 | AB99: 44875 | AC99: 44876 | AF99: 44879 | AG99: 44880 | AH99: 44881 | AI99: 44882 | AJ99: 44883 | AM99: 44886 | AN99: 44887 | AO99: 44888 | AP99: 44889 | AQ99: 44890 | AT99: 44893 | AU99: 44894 | AV99: 44895
D100: =SUM(D88:D99) -> 18600.047 | E100: =SUM(E88:E98) -> 874.20219 | F100: =SUM(F88:F98) -> 306.90077 | G100: =SUM(G88:G99) -> 2418.006 | H100: =SUM(H88:H99) -> 15000.938 | I100: =SUM(I88:I99) -> 15000.92 | Q100: DIC | U100: 44896 | V100: 44897 | Y100: 44900 | AA100: 44902 | AC100: 44904 | AF100: 44907 | AG100: 44908 | AH100: 44909 | AI100: 44910 | AJ100: 44911 | AM100: 44914 | AN100: 44915 | AO100: 44916 | AP100: 44917 | AQ100: 44918 | AT100: 44921 | AU100: 44922 | AV100: 44923 | AW100: 44924 | AX100: 44925
D101: =D100-E100-G100-F100 -> 15000.938
N107: 44643
N108: =TODAY()-N107 -> 1537
N109: =(N108/365)*33*(2000/30) -> 9264.1096 | O109: indem desp 33

Sheet feb mar 25 baja
E1: mes | F1: paga
E2: 1821.43 | F2: 303.58
D3: diario | E3: =+E2/28 -> 65.051071 | F3: =+F2/28 -> 10.842143
C4: 30
C5: baja | D5: 45692
C6: 1 | D6: 3 | E6: =+E3*$D$6 -> 195.15321 | F6: =+F3*$D$6 -> 32.526429 | H6: =+D5+D6 -> 45695
C7: 0.6 | D7: 17 | E7: =+E3*$D$7*$C$7 -> 663.52093 | F7: =+F3*$D$7*$C$7 -> 110.58986 | H7: =+H6+D7 -> 45712
C8: 0.75 | D8: 5 | E8: =+$E$3*$D$8*$C$8 -> 243.94152 | F8: =+$F$3*$D$8*$C$8 -> 40.658036 | H8: =+H7+D8 -> 45717
E10: =SUM(E6:E8) -> 1102.6157 | F10: =SUM(F6:F8) -> 183.77432
D12: Marzo
C13: 0.75 | D13: 31 | E13: =+$E$3*$D$13*$C$13 -> 1512.4374 | F13: =+$F$3*$D$13*$C$13 -> 252.07982 | I13: =25500/12 -> 2125
I14: =+I13*0.75 -> 1593.75
D16: Abril
C17: 0.75 | D17: 30 | E17: =+$E$3*$D$17*$C$17 -> 1463.6491 | F17: =+$F$3*$D$17*$C$17 -> 243.94821

Sheet Ahorro BBVA antiguo
C2: AHORRO MIKEL | D2: AHORRO MIKEL
A4: Mes | B4: Cuenta | C4: Ahorro | D4: BBVA | E4: Sant | F4: EVO | G4: B100 | H4: Bankinter | I4: TOTAL | J4: Balance | L4: TOTAL | Q4: TOTAL BBVA | V4: TOTAL BANKINTER | AA4: TOTAL B100
A5: 41183 | B5: 4025 | C5: 1721.53 | D5: =B5+C5 -> 5746.53 | I5: =B5+C5 -> 5746.53
A6: 41214 | B6: 5025 | C6: 683.02 | D6: =B6+C6 -> 5708.02 | I6: =B6+C6 -> 5708.02 | J6: =I6-I5 -> -38.51 | Q6: =OFFSET(D4,COUNT(D:D),0) -> 684.82 | V6: =LOOKUP(MAX(H:H)+1,(H:H)) -> 133500 | AA6: =LOOKUP(MAX(G:G)+1,(G:G)) -> 0
A7: 41244 | B7: 5025 | C7: 432.93 | D7: =B7+C7 -> 5457.93 | I7: =B7+C7 -> 5457.93 | J7: =I7-I6 -> -250.09 | L7: =OFFSET(I4,COUNT(I:I),0) -> 134184.82
A8: 41275 | B8: 5025 | C8: 507.22 | D8: =B8+C8 -> 5532.22 | I8: =B8+C8 -> 5532.22 | J8: =I8-I7 -> 74.29
A9: 41306 | B9: 5025 | C9: 699.38 | D9: =B9+C9 -> 5724.38 | I9: =B9+C9 -> 5724.38 | J9: =I9-I8 -> 192.16
A10: 41334 | B10: 5025 | C10: 904.39 | D10: =B10+C10 -> 5929.39 | I10: =B10+C10 -> 5929.39 | J10: =I10-I9 -> 205.01
A11: 41365 | B11: 5025 | C11: 969.39 | D11: =B11+C11 -> 5994.39 | I11: =B11+C11 -> 5994.39 | J11: =I11-I10 -> 65
A12: 41395 | B12: 5025 | C12: 1213.39 | D12: =B12+C12 -> 6238.39 | I12: =B12+C12 -> 6238.39 | J12: =I12-I11 -> 244
A13: 41426 | B13: 5025 | C13: 1199.91 | D13: =B13+C13 -> 6224.91 | I13: =B13+C13 -> 6224.91 | J13: =I13-I12 -> -13.48
A14: 41456 | B14: 5025 | C14: 1364.91 | D14: =B14+C14 -> 6389.91 | I14: =B14+C14 -> 6389.91 | J14: =I14-I13 -> 165
A15: 41487 | B15: 5025 | C15: 1590.51 | D15: =B15+C15 -> 6615.51 | I15: =B15+C15 -> 6615.51 | J15: =I15-I14 -> 225.6
A16: 41518 | B16: 5025 | C16: 1788.53 | D16: =B16+C16 -> 6813.53 | I16: =B16+C16 -> 6813.53 | J16: =I16-I15 -> 198.02
A17: 41548 | B17: 5046.16 | C17: 1959.53 | D17: =B17+C17 -> 7005.69 | I17: =B17+C17 -> 7005.69 | J17: =I17-I16 -> 192.16
A18: 41579 | B18: 5049.42 | C18: 2309.43 | D18: =B18+C18 -> 7358.85 | I18: =B18+C18 -> 7358.85 | J18: =I18-I17 -> 353.16
A19: 41609 | B19: 5052.79 | C19: 2970.02 | D19: =B19+C19 -> 8022.81 | I19: =B19+C19 -> 8022.81 | J19: =I19-I18 -> 663.96
... A33: 42036 | B33: 3339.39 | C33: 10170 | D33: =B33+C33 -> 13509.39 | I33: =B33+C33 -> 13509.39 | J33: =I33-I32 -> 442.93
A34: 42064 | B34: 3832.54 | C34: 10210 | D34: =B34+C34 -> 14042.54 | I34: =B34+C34 -> 14042.54 | J34: =I34-I33 -> 533.15 | L34: AHORRO ÚLTIMO MES
A35: 42095 | B35: 4227.89 | C35: 10250 | D35: =B35+C35 -> 14477.89 | I35: =B35+C35 -> 14477.89 | J35: =I35-I34 -> 435.35
A36: 42125 | B36: 4710.37 | C36: 10290 | D36: =B36+C36 -> 15000.37 | I36: =B36+C36 -> 15000.37 | J36: =I36-I35 -> 522.48
A37: 42156 | B37: 5261.35 | C37: =10000+240 -> 10240 | D37: =B37+C37 -> 15501.35 | I37: =B37+C37 -> 15501.35 | J37: =I37-I36 -> 500.98
A38: 42186 | B38: 2468.22 | C38: =10000+4000 -> 14000 | D38: =B38+C38 -> 16468.22 | I38: =B38+C38 -> 16468.22 | J38: =I38-I37 -> 966.87
A39: 42217 | B39: 1368.54 | C39: =10000+5000 -> 15000 | D39: =B39+C39 -> 16368.54 | I39: =B39+C39 -> 16368.54 | J39: =I39-I38 -> -99.68
A40: 42248 | B40: 1376.51 | C40: 15000 | D40: =B40+C40 -> 16376.51 | I40: =B40+C40 -> 16376.51 | J40: =I40-I39 -> 7.97
A41: 42278 | B41: 871.27 | C41: 16000 | D41: =B41+C41 -> 16871.27 | I41: =B41+C41 -> 16871.27 | J41: =I41-I40 -> 494.76
A42: 42309 | B42: 846.77 | C42: 16500 | D42: =B42+C42 -> 17346.77 | I42: =B42+C42 -> 17346.77 | J42: =I42-I41 -> 475.5 | L42: =OFFSET(J4,COUNT(J:J)+1,0) -> 1834.54
A43: 42339 | B43: 965.37 | C43: 17000 | D43: =B43+C43 -> 17965.37 | I43: =B43+C43 -> 17965.37 | J43: =I43-I42 -> 618.6
A44: 42370 | B44: 933.87 | C44: 17500 | D44: =B44+C44 -> 18433.87 | I44: =B44+C44 -> 18433.87 | J44: =I44-I43 -> 468.5
A45: 42401 | B45: 963.54 | C45: 18000 | D45: =B45+C45 -> 18963.54 | I45: =B45+C45 -> 18963.54 | J45: =I45-I44 -> 529.67
A46: 42430 | B46: 1386.64 | C46: 18500 | D46: =B46+C46 -> 19886.64 | I46: =B46+C46 -> 19886.64 | J46: =I46-I45 -> 923.1
A47: 42461 | B47: 2327.23 | C47: 18500 | D47: =B47+C47 -> 20827.23 | I47: =B47+C47 -> 20827.23 | J47: =I47-I46 -> 940.59
A48: 42491 | B48: 2438.05 | C48: 20000 | D48: =B48+C48 -> 22438.05 | I48: =B48+C48 -> 22438.05 | J48: =I48-I47 -> 1610.82
A49: 42522 | B49: 1256.68 | C49: 21000 | D49: =B49+C49 -> 22256.68 | I49: =B49+C49 -> 22256.68 | J49: =I49-I48 -> -181.37
A50: 42552 | B50: 1649.73 | C50: 21000 | D50: =B50+C50 -> 22649.73 | I50: =B50+C50 -> 22649.73 | J50: =I50-I49 -> 393.05
A51: 42583 | B51: 1245.87 | C51: 22000 | D51: =B51+C51 -> 23245.87 | I51: =B51+C51 -> 23245.87 | J51: =I51-I50 -> 596.14
A52: 42614 | B52: 950.75 | C52: 23000 | D52: =B52+C52 -> 23950.75 | I52: =B52+C52 -> 23950.75 | J52: =I52-I51 -> 704.88
A53: 42644 | B53: 1540.36 | C53: 23500 | D53: =B53+C53 -> 25040.36 | I53: =B53+C53 -> 25040.36 | J53: =I53-I52 -> 1089.61
A54: 42675 | B54: 810.82 | C54: 25000 | D54: =B54+C54 -> 25810.82 | I54: =B54+C54 -> 25810.82 | J54: =I54-I53 -> 770.46
... A74: 43282 | B74: 1812.01 | C74: 31000 | D74: =B74+C74 -> 32812.01 | I74: =B74+C74 -> 32812.01 | J74: =I74-I73 -> 541.72
A75: 43313 | B75: =1778.66 -> 1778.66 | C75: 32000 | D75: =B75+C75 -> 33778.66 | I75: =B75+C75 -> 33778.66 | J75: =I75-I74 -> 966.65
A76: 43344 | B76: 2483.73 | C76: 32000 | D76: =B76+C76 -> 34483.73 | I76: =B76+C76 -> 34483.73 | J76: =I76-I75 -> 705.07
A77: 43374 | B77: =1844.52 -> 1844.52 | C77: 34000 | D77: =B77+C77 -> 35844.52 | I77: =B77+C77 -> 35844.52 | J77: =I77-I76 -> 1360.79
A78: 43405 | B78: 1774.83 | C78: 35000 | D78: =B78+C78 -> 36774.83 | I78: =B78+C78 -> 36774.83 | J78: =I78-I77 -> 930.31
A79: 43435 | B79: 1792.42 | C79: 36000 | D79: =B79+C79 -> 37792.42 | I79: =B79+C79 -> 37792.42 | J79: =I79-I78 -> 1017.59 | K79: =SUM(J67:J79) -> 7140.19
A80: 43466 | B80: 1589.43 | C80: 37000 | D80: =B80+C80 -> 38589.43 | I80: =B80+C80 -> 38589.43 | J80: =I80-I79 -> 797.01
A81: 43497 | B81: 1767.16 | C81: 38000 | D81: =B81+C81 -> 39767.16 | I81: =B81+C81 -> 39767.16 | J81: =I81-I80 -> 1177.73
A82: 43525 | B82: 1493.8 | C82: 39000 | D82: =B82+C82 -> 40493.8 | I82: =B82+C82 -> 40493.8 | J82: =I82-I81 -> 726.64
A83: 43556 | B83: 1469.22 | C83: 40000 | D83: =B83+C83 -> 41469.22 | I83: =B83+C83 -> 41469.22 | J83: =I83-I82 -> 975.42
A84: 43586 | B84: 1435.48 | C84: 41000 | D84: =B84+C84 -> 42435.48 | I84: =B84+C84 -> 42435.48 | J84: =I84-I83 -> 966.26
A85: 43617 | B85: =1728.02-10+2.76 -> 1720.78 | C85: 41220 | D85: =B85+C85 -> 42940.78 | I85: =B85+C85 -> 42940.78 | J85: =I85-I84 -> 505.3
A86: 43647 | B86: 1572.05 | C86: 43000 | D86: =B86+C86 -> 44572.05 | I86: =B86+C86 -> 44572.05 | J86: =I86-I85 -> 1631.27
A87: 43678 | B87: 2364.05 | C87: 43000 | D87: =B87+C87 -> 45364.05 | I87: =B87+C87 -> 45364.05 | J87: =I87-I86 -> 792
A88: 43709 | B88: =1195.15 -> 1195.15 | C88: 45000 | D88: =B88+C88 -> 46195.15 | I88: =B88+C88 -> 46195.15 | J88: =I88-I87 -> 831.1
A89: 43739 | B89: 1212.24 | C89: 46000 | D89: =B89+C89 -> 47212.24 | I89: =B89+C89 -> 47212.24 | J89: =I89-I88 -> 1017.09
A90: 43770 | B90: 1945.82 | C90: 46000 | D90: =B90+C90 -> 47945.82 | I90: =B90+C90 -> 47945.82 | J90: =I90-I89 -> 733.58
A91: 43800 | B91: 1880.04 | C91: 47000 | D91: =B91+C91 -> 48880.04 | I91: =B91+C91 -> 48880.04 | J91: =I91-I90 -> 934.22 | K91: =SUM(J80:J91) -> 11087.62
A92: 43831 | B92: 1103.36 | C92: 49000 | D92: =B92+C92 -> 50103.36 | I92: =B92+C92 -> 50103.36 | J92: =I92-I91 -> 1223.32
A93: 43862 | B93: 880.2 | C93: 50000 | D93: =B93+C93 -> 50880.2 | I93: =B93+C93 -> 50880.2 | J93: =I93-I92 -> 776.84
A94: 43891 | B94: 1413.36 | C94: 50000 | D94: =B94+C94 -> 51413.36 | I94: =B94+C94 -> 51413.36 | J94: =I94-I93 -> 533.16
A95: 43922 | B95: =1345+630.63 -> 1975.63 | C95: 50000 | D95: =B95+C95 -> 51975.63 | I95: =B95+C95 -> 51975.63 | J95: =I95-I94 -> 562.27
A96: 43952 | B96: 2771.38 | C96: 50000 | D96: =B96+C96 -> 52771.38 | I96: =B96+C96 -> 52771.38 | J96: =I96-I95 -> 795.75
A97: 43983 | B97: 701.64 | C97: 53000 | D97: =B97+C97 -> 53701.64 | I97: =B97+C97 -> 53701.64 | J97: =I97-I96 -> 930.26
A98: 44013 | B98: =1316.71-810.88 -> 505.83 | C98: 54000 | D98: =B98+C98 -> 54505.83 | I98: =B98+C98 -> 54505.83 | J98: =I98-I97 -> 804.19
A99: 44044 | B99: =1359.54 -> 1359.54 | C99: 54000 | D99: =B99+C99 -> 55359.54 | I99: =B99+C99 -> 55359.54 | J99: =I99-I98 -> 853.71
A100: 44075 | B100: 2370.18 | C100: 54000 | D100: =B100+C100 -> 56370.18 | I100: =B100+C100 -> 56370.18 | J100: =I100-I99 -> 1010.64
A101: 44105 | B101: =2180.5-51.18-53.65 -> 2075.67 | C101: 55000 | D101: =B101+C101 -> 57075.67 | I101: =B101+C101 -> 57075.67 | J101: =I101-I100 -> 705.49
A102: 44136 | B102: 2738.63 | C102: 55000 | D102: =B102+C102 -> 57738.63 | I102: =B102+C102 -> 57738.63 | J102: =I102-I101 -> 662.96
A103: 44166 | B103: 2645.21 | C103: 55000 | D103: =B103+C103 -> 57645.21 | I103: =B103+C103 -> 57645.21 | J103: =I103-I102 -> -93.42 | K103: =SUM(J92:J103) -> 8765.17
A104: 44197 | B104: 2574.15 | C104: 55000 | D104: =B104+C104 -> 57574.15 | I104: =B104+C104 -> 57574.15 | J104: =I104-I103 -> -71.06
A105: 44228 | B105: 2505.15 | C105: 55000 | D105: =B105+C105 -> 57505.15 | I105: =B105+C105 -> 57505.15 | J105: =I105-I104 -> -69
A106: 44256 | B106: =2478.94 -> 2478.94 | C106: 55000 | D106: =B106+C106 -> 57478.94 | I106: =B106+C106 -> 57478.94 | J106: =I106-I105 -> -26.21
A107: 44287 | B107: =1413.94-100-10-21.75 -> 1282.19 | C107: 58000 | D107: =B107+C107 -> 59282.19 | I107: =B107+C107 -> 59282.19 | J107: =I107-I106 -> 1803.25
A108: 44317 | B108: =1241.66-50 -> 1191.66 | C108: 59000 | D108: =B108+C108 -> 60191.66 | I108: =B108+C108 -> 60191.66 | J108: =I108-I107 -> 909.47
A109: 44348 | B109: 939.06 | C109: 60000 | D109: =B109+C109 -> 60939.06 | I109: =B109+C109 -> 60939.06 | J109: =I109-I108 -> 747.4
A110: 44378 | B110: =3489.11-50-60 -> 3379.11 | C110: 60000 | D110: =B110+C110 -> 63379.11 | I110: =B110+C110 -> 63379.11 | J110: =I110-I109 -> 2440.05
A111: 44409 | B111: 4550.14 | C111: 60000 | D111: =B111+C111 -> 64550.14 | I111: =B111+C111 -> 64550.14 | J111: =I111-I110 -> 1171.03
A112: 44440 | B112: 1344.79 | C112: 65000 | D112: =B112+C112 -> 66344.79 | I112: =B112+C112 -> 66344.79 | J112: =I112-I111 -> 1794.65
A113: 44470 | B113: 2101.05 | C113: 65000 | D113: =B113+C113 -> 67101.05 | I113: =B113+C113 -> 67101.05 | J113: =I113-I112 -> 756.26
A114: 44501 | B114: 3123.13 | C114: 65000 | D114: =B114+C114 -> 68123.13 | I114: =B114+C114 -> 68123.13 | J114: =I114-I113 -> 1022.08
A115: 44531 | B115: 3061.34 | C115: 65000 | D115: =B115+C115 -> 68061.34 | I115: =B115+C115 -> 68061.34 | J115: =I115-I114 -> -61.79 | K115: =SUM(J104:J115) -> 10416.13
A116: 44562 | B116: 3078.74 | C116: 65000 | D116: =B116+C116 -> 68078.74 | I116: =B116+C116 -> 68078.74 | J116: =I116-I115 -> 17.4
A117: 44593 | B117: 2101.13 | C117: 66000 | D117: =B117+C117 -> 68101.13 | I117: =B117+C117 -> 68101.13 | J117: =I117-I116 -> 22.39
A118: 44621 | B118: 2182.7 | C118: 66000 | D118: =B118+C118 -> 68182.7 | I118: =B118+C118 -> 68182.7 | J118: =I118-I117 -> 81.57
A119: 44652 | B119: 1431.28 | C119: 67000 | D119: =B119+C119 -> 68431.28 | I119: =B119+C119 -> 68431.28 | J119: =I119-I118 -> 248.58
A120: 44682 | B120: 1754.92 | C120: 68000 | D120: =B120+C120 -> 69754.92 | I120: =B120+C120 -> 69754.92 | J120: =I120-I119 -> 1323.64
A121: 44713 | B121: 1874.95 | C121: 69000 | D121: =B121+C121 -> 70874.95 | I121: =B121+C121 -> 70874.95 | J121: =I121-I120 -> 1120.03
A122: 44743 | B122: 1937.76 | C122: 71000 | D122: =B122+C122 -> 72937.76 | E122: 0 | I122: =B122+C122+E122 -> 72937.76 | J122: =I122-I121 -> 2062.81
A123: 44774 | B123: 1287.57 | C123: 73000 | D123: =IFERROR(IF(ISBLANK(B123)=FALSE,B123,"")+IF(ISBLANK(C123)=FALSE,C123,""),"") -> 74287.57 | E123: 0 | I123: =IFERROR(IF(ISBLANK(D123)=FALSE,D123,"")+IF(ISBLANK(E123)=FALSE,E123,""),"") -> 74287.57 | J123: =I123-I122 -> 1349.81
A124: 44805 | B124: 1616.06 | C124: 72000 | D124: =IFERROR(IF(ISBLANK(B124)=FALSE,B124,"")+IF(ISBLANK(C124)=FALSE,C124,""),"") -> 73616.06 | E124: 2000 | I124: =IFERROR(IF(ISBLANK(D124)=FALSE,D124,"")+IF(ISBLANK(E124)=FALSE,E124,""),"") -> 75616.06 | J124: =I124-I123 -> 1328.49
A125: 44835 | B125: 1952.45 | C125: 73000 | D125: =IFERROR(IF(ISBLANK(B125)=FALSE,B125,"")+IF(ISBLANK(C125)=FALSE,C125,""),"") -> 74952.45 | E125: 2000 | I125: =IFERROR(IF(ISBLANK(D125)=FALSE,D125,"")+IF(ISBLANK(E125)=FALSE,E125,""),"") -> 76952.45 | J125: =IF(ISBLANK(I125)=FALSE,I125-I124,"") -> 1336.39
A126: 44866 | B126: 1311.93 | C126: 75000 | D126: =IFERROR(IF(ISBLANK(B126)=FALSE,B126,"")+IF(ISBLANK(C126)=FALSE,C126,""),"") -> 76311.93 | E126: 2000 | I126: =IFERROR(IF(ISBLANK(D126)=FALSE,D126,"")+IF(ISBLANK(E126)=FALSE,E126,""),"") -> 78311.93 | J126: =IFERROR(IF(ISBLANK(E126)=FALSE,E126,"")+IF(ISBLANK(I126)=FALSE,I126-I125-E126,""),"") -> 1359.48
A127: 44896 | B127: =1143.24+10-11.99-1.42 -> 1139.83 | C127: 75000 | D127: =IFERROR(IF(ISBLANK(B127)=FALSE,B127,"")+IF(ISBLANK(C127)=FALSE,C127,""),"") -> 76139.83 | E127: 5000 | I127: =IFERROR(IF(ISBLANK(D127)=FALSE,D127,"")+IF(ISBLANK(E127)=FALSE,E127,""),"") -> 81139.83 | J127: =IFERROR(IF(ISBLANK(E127)=FALSE,E127,"")+IF(ISBLANK(I127)=FALSE,I127-I126-E127,""),"") -> 2827.9 | K127: =SUM(J116:J127) -> 13078.49
A128: 44927 | B128: 1418.23 | C128: 76000 | D128: =IFERROR(IF(ISBLANK(B128)=FALSE,B128,"")+IF(ISBLANK(C128)=FALSE,C128,""),"") -> 77418.23 | E128: 5000 | I128: =IFERROR(IF(ISBLANK(D128)=FALSE,D128,"")+IF(ISBLANK(E128)=FALSE,E128,""),"") -> 82418.23 | J128: =IFERROR(IF(ISBLANK(E128)=FALSE,E128,"")+IF(ISBLANK(I128)=FALSE,I128-I127-E128,""),"") -> 1278.4
A129: 44958 | B129: 1826.87 | C129: 77000 | D129: =IFERROR(IF(ISBLANK(B129)=FALSE,B129,"")+IF(ISBLANK(C129)=FALSE,C129,""),"") -> 78826.87 | E129: 5000 | I129: =IFERROR(IF(ISBLANK(D129)=FALSE,D129,"")+IF(ISBLANK(E129)=FALSE,E129,""),"") -> 83826.87 | J129: =IFERROR(IF(ISBLANK(E129)=FALSE,E129,"")+IF(ISBLANK(I129)=FALSE,I129-I128-E129,""),"") -> 1408.64
A130: 44986 | B130: 1188.76 | C130: 74000 | D130: =IFERROR(IF(ISBLANK(B130)=FALSE,B130,"")+IF(ISBLANK(C130)=FALSE,C130,""),"") -> 75188.76 | E130: 10000 | I130: =IFERROR(IF(ISBLANK(D130)=FALSE,D130,"")+IF(ISBLANK(E130)=FALSE,E130,""),"") -> 85188.76 | J130: =IFERROR(IF(ISBLANK(E130)=FALSE,E130,"")+IF(ISBLANK(I130)=FALSE,I130-I129-E130,""),"") -> 1361.89
A131: 45017 | B131: =1527.24-16.14 -> 1511.1 | C131: 75000 | D131: =IFERROR(IF(ISBLANK(B131)=FALSE,B131,"")+IF(ISBLANK(C131)=FALSE,C131,""),"") -> 76511.1 | E131: 10000 | I131: =IFERROR(IF(ISBLANK(D131)=FALSE,D131,"")+IF(ISBLANK(E131)=FALSE,E131,""),"") -> 86511.1 | J131: =IFERROR(IF(ISBLANK(E131)=FALSE,E131,"")+IF(ISBLANK(I131)=FALSE,I131-I130-E131,""),"") -> 1322.34
A132: 45047 | B132: 1687.39 | C132: 76000 | D132: =IFERROR(IF(ISBLANK(B132)=FALSE,B132,"")+IF(ISBLANK(C132)=FALSE,C132,""),"") -> 77687.39 | E132: 10000 | I132: =IFERROR(IF(ISBLANK(D132)=FALSE,D132,"")+IF(ISBLANK(E132)=FALSE,E132,""),"") -> 87687.39 | J132: =IFERROR(IF(ISBLANK(E132)=FALSE,E132,"")+IF(ISBLANK(I132)=FALSE,I132-I131-E132,""),"") -> 1176.29
A133: 45078 | B133: =1922.84-5-39.5-2.51 -> 1875.83 | C133: 72000 | D133: =IFERROR(IF(ISBLANK(B133)=FALSE,B133,"")+IF(ISBLANK(C133)=FALSE,C133,""),"") -> 73875.83 | E133: 15000 | I133: =IFERROR(IF(ISBLANK(D133)=FALSE,D133,"")+IF(ISBLANK(E133)=FALSE,E133,""),"") -> 88875.83 | J133: =IFERROR(IF(ISBLANK(E133)=FALSE,E133,"")+IF(ISBLANK(I133)=FALSE,I133-I132-E133,""),"") -> 1188.44
A134: 45108 | B134: 1560.58 | C134: 25000 | D134: =IFERROR(IF(ISBLANK(B134)=FALSE,B134,"")+IF(ISBLANK(C134)=FALSE,C134,""),"") -> 26560.58 | E134: 1000 | F134: 34000 | G134: 30000 | I134: =IFERROR(IF(ISBLANK(D134)=FALSE,D134,"")+IF(ISBLANK(E134)=FALSE,E134,"")+IF(ISBLANK(F134)=FALSE,F134,"")+IF(ISBLANK(G134)=FALSE,G134,""),"") -> 91560.58 | J134: =IFERROR(IF(ISBLANK(E134)=FALSE,E134,"")+IF(ISBLANK(I134)=FALSE,I134-I133-E134,""),"") -> 2684.75
...

Sheet Sueldo CRN
B2: Nómina EHU/UPV - Caja Rural de Navarra
D9: De | E9: Hasta | F9: Bruto | G9: SS | H9: IRPF (2%) | I9: Sueldo | J9: Ingresado | K9: Diferencia
C10: Mayo | D10: 41764 | F10: 500 | H10: =0.02*F10 -> 10 | I10: =F10-G10-H10 -> 490 | J10: 490 | K10: =IF(ISBLANK(J10)," ",IF(J10-I10=0,"Correcto ",IF(J10-I10<0,"Faltan","Sobran"))) -> Correcto | L10: =IF(ISBLANK(J10)," ",IF(J10-I10=0," ",J10-I10))
C11: Junio | F11: 500 | H11: =0.02*F11 -> 10 | I11: =F11-G11-H11 -> 490 | J11: 490 | K11: =IF(ISBLANK(J11)," ",IF(J11-I11=0,"Correcto ",IF(J11-I11<0,"Faltan","Sobran"))) -> Correcto | L11: =IF(ISBLANK(J11)," ",IF(J11-I11=0," ",J11-I11))
C12: Julio | E12: 41844 | F12: 500 | H12: =0.02*F12 -> 10 | I12: =F12-G12-H12 -> 490 | J12: 490 | K12: =IF(ISBLANK(J12)," ",IF(J12-I12=0,"Correcto ",IF(J12-I12<0,"Faltan","Sobran"))) -> Correcto | L12: =IF(ISBLANK(J12)," ",IF(J12-I12=0," ",J12-I12))
D13: TOTAL | F13: =SUM(F10:F12) -> 1500 | G13: =SUM(G10:G12) -> 0 | H13: =SUM(H10:H12) -> 30 | I13: =SUM(I10:I12) -> 1470 | J13: =SUM(J10:J12) -> 1470 | K13: =IF(ISBLANK(J13)," ",IF(J13-I13=0,"Correcto ",IF(J13-I13<0,"Faltan","Sobran"))) -> Correcto | L13: =IF(ISBLANK(J13)," ",IF(J13-I13=0," ",J13-I13))
F14: =F13-G13-H13 -> 1470

Sheet Sueldo MB
C2: Nómina SEA - Mercedes-Benz
D9: De | E9: Hasta | F9: Días | G9: Bolsa | H9: SS | I9: IRPF (2%) | J9: Sueldo | K9: Ingresado | L9: A LK | M9: Diferencia | O9: A LK
C10: Octubre | D10: 41565 | E10: 41578 | F10: =E10-D10+1 -> 14 | G10: 149.32 | H10: 6.09 | I10: =0.02*G10 -> 2.9864 | J10: 140.24 | K10: 140.24 | L10: 140.24 | M10: =IF(ISBLANK(K10)," ",IF(K10-J10=0,"Correcto ",IF(K10-J10<0,"Faltan","Sobran"))) -> Correcto | N10: =IF(ISBLANK(K10)," ",IF(K10-J10=0," ",K10-J10)) | O10: =IF(ISBLANK(L10)," ",IF(L10-K10=0,"Correcto ",IF(L10-K10<0,"Faltan por ingresar","Sobran"))) -> Correcto | P10: =IF(ISBLANK(K10)," ",IF(L10-K10=0," ",L10-K10))
C11: Noviembre | G11: 365 | H11: 6.09 | I11: =0.02*G11 -> 7.3 | J11: =365-6.09-0.02*365 -> 351.61 | K11: 351.61 | L11: 351.61 | M11: =IF(ISBLANK(K11)," ",IF(K11-J11=0,"Correcto ",IF(K11-J11<0,"Faltan","Sobran"))) -> Correcto | N11: =IF(ISBLANK(K11)," ",IF(K11-J11=0," ",K11-J11)) | O11: =IF(ISBLANK(L11)," ",IF(L11-K11=0,"Correcto ",IF(L11-K11<0,"Faltan por ingresar","Sobran"))) -> Correcto | P11: =IF(ISBLANK(K11)," ",IF(L11-K11=0," ",L11-K11))
C12: Diciembre | F12: 24 | G12: 282.58 | H12: 6.09 | I12: =0.02*G12 -> 5.6516 | J12: =G12-H12-I12 -> 270.8384 | K12: 270.49 | L12: 270.49 | M12: =IF(ISBLANK(K12)," ",IF(K12-J12=0,"Correcto ",IF(K12-J12<0,"Faltan","Sobran"))) -> Faltan | N12: =IF(ISBLANK(K12)," ",IF(K12-J12=0," ",K12-J12)) -> -0.3484 | O12: =IF(ISBLANK(L12)," ",IF(L12-K12=0,"Correcto ",IF(L12-K12<0,"Faltan por ingresar","Sobran"))) -> Correcto | P12: =IF(ISBLANK(K12)," ",IF(L12-K12=0," ",L12-K12))
C13: Enero | F13: 28 | G13: 329.68 | H13: 6.09 | I13: =0.02*G13 -> 6.5936 | J13: =G13-H13-I13 -> 316.9964 | K13: 316.85 | L13: 316.85 | M13: =IF(ISBLANK(K13)," ",IF(K13-J13=0,"Correcto ",IF(K13-J13<0,"Faltan","Sobran"))) -> Faltan | N13: =IF(ISBLANK(K13)," ",IF(K13-J13=0," ",K13-J13)) -> -0.1464 | O13: =IF(ISBLANK(L13)," ",IF(L13-K13=0,"Correcto ",IF(L13-K13<0,"Faltan por ingresar","Sobran"))) -> Correcto | P13: =IF(ISBLANK(K13)," ",IF(L13-K13=0," ",L13-K13))
C14: Febrero | G14: 365 | H14: 6.09 | I14: =0.02*G14 -> 7.3 | J14: =365-6.09-0.02*365 -> 351.61 | K14: 351.61 | L14: 351.61 | M14: =IF(ISBLANK(K14)," ",IF(K14-J14=0,"Correcto ",IF(K14-J14<0,"Faltan","Sobran"))) -> Correcto | N14: =IF(ISBLANK(K14)," ",IF(K14-J14=0," ",K14-J14)) | O14: =IF(ISBLANK(L14)," ",IF(L14-K14=0,"Correcto ",IF(L14-K14<0,"Faltan por ingresar","Sobran"))) -> Correcto | P14: =IF(ISBLANK(K14)," ",IF(L14-K14=0," ",L14-K14))
C15: Marzo | G15: 365 | H15: 6.09 | I15: =0.02*G15 -> 7.3 | J15: =365-6.09-0.02*365 -> 351.61 | K15: 351.61 | L15: 351.61 | M15: =IF(ISBLANK(K15)," ",IF(K15-J15=0,"Correcto ",IF(K15-J15<0,"Faltan","Sobran"))) -> Correcto | N15: =IF(ISBLANK(K15)," ",IF(K15-J15=0," ",K15-J15)) | O15: =IF(ISBLANK(L15)," ",IF(L15-K15=0,"Correcto ",IF(L15-K15<0,"Faltan por ingresar","Sobran"))) -> Correcto | P15: =IF(ISBLANK(K15)," ",IF(L15-K15=0," ",L15-K15))
C16: Abril | D16: 41730 | E16: 41743 | F16: 15 | G16: 195.274 | H16: 6.09 | I16: =0.02*G16 -> 3.90548 | J16: =G16-H16-I16 -> 185.27852 | K16: 185.4 | L16: =K16 -> 185.4 | M16: =IF(ISBLANK(K16)," ",IF(K16-J16=0,"Correcto ",IF(K16-J16<0,"Faltan","Sobran"))) -> Sobran | N16: =IF(ISBLANK(K16)," ",IF(K16-J16=0," ",K16-J16)) -> 0.12148 | O16: =IF(ISBLANK(L16)," ",IF(L16-K16=0,"Correcto ",IF(L16-K16<0,"Faltan por ingresar","Sobran"))) -> Correcto | P16: =IF(ISBLANK(K16)," ",IF(L16-K16=0," ",L16-K16))
E17: TOTAL | G17: =SUM(G10:G16) -> 2051.854 | H17: =SUM(H10:H16) -> 42.63 | I17: =SUM(I10:I16) -> 41.03708 | J17: =SUM(J10:J16) -> 1968.1833 | K17: =SUM(K10:K16) -> 1967.81 | L17: =SUM(L10:L16) -> 1967.81 | M17: =IF(ISBLANK(K17)," ",IF(K17-J17=0,"Correcto ",IF(K17-J17<0,"Faltan","Sobran"))) -> Faltan | N17: =IF(ISBLANK(K17)," ",IF(K17-J17=0," ",K17-J17)) -> -0.37332 | O17: =IF(ISBLANK(L17)," ",IF(L17-K17=0,"Correcto ",IF(L17-K17<0,"Faltan por ingresar","Sobran"))) -> Correcto | P17: =IF(ISBLANK(L17)," ",IF(L17-K17=0," ",L17-K17))
G18: =G17-H17-I17 -> 1968.1869

Sheet Nómina
C2: Nómina
D9: De | E9: Hasta | F9: Días | G9: Bruto | H9: SS | I9: IRPF (2%) | J9: Sueldo | K9: Ingresado | L9: A LK | M9: Diferencia | O9: A LK
C10: Enero | I10: =0.02*G10 -> 0 | J10: =G10-H10-I10 -> 0 | M10: =IF(ISBLANK(K10)," ",IF(K10-J10=0,"Correcto ",IF(K10-J10<0,"Faltan","Sobran"))) | N10: =IF(ISBLANK(K10)," ",IF(K10-J10=0," ",K10-J10)) | O10: =IF(ISBLANK(L10)," ",IF(L10-K10=0,"Correcto ",IF(L10-K10<0,"Faltan por ingresar","Sobran"))) | P10: =IF(ISBLANK(K10)," ",IF(L10-K10=0," ",L10-K10))
C11: Febrero | I11: =0.02*G11 -> 0 | J11: =G11-H11-I11 -> 0 | M11: =IF(ISBLANK(K11)," ",IF(K11-J11=0,"Correcto ",IF(K11-J11<0,"Faltan","Sobran"))) | N11: =IF(ISBLANK(K11)," ",IF(K11-J11=0," ",K11-J11)) | O11: =IF(ISBLANK(L11)," ",IF(L11-K11=0,"Correcto ",IF(L11-K11<0,"Faltan por ingresar","Sobran"))) | P11: =IF(ISBLANK(K11)," ",IF(L11-K11=0," ",L11-K11))
C12: Marzo | I12: =0.02*G12 -> 0 | J12: =G12-H12-I12 -> 0 | M12: =IF(ISBLANK(K12)," ",IF(K12-J12=0,"Correcto ",IF(K12-J12<0,"Faltan","Sobran"))) | N12: =IF(ISBLANK(K12)," ",IF(K12-J12=0," ",K12-J12)) | O12: =IF(ISBLANK(L12)," ",IF(L12-K12=0,"Correcto ",IF(L12-K12<0,"Faltan por ingresar","Sobran"))) | P12: =IF(ISBLANK(K12)," ",IF(L12-K12=0," ",L12-K12))
C13: Abril | I13: =0.02*G13 -> 0 | J13: =G13-H13-I13 -> 0 | M13: =IF(ISBLANK(K13)," ",IF(K13-J13=0,"Correcto ",IF(K13-J13<0,"Faltan","Sobran"))) | N13: =IF(ISBLANK(K13)," ",IF(K13-J13=0," ",K13-J13)) | O13: =IF(ISBLANK(L13)," ",IF(L13-K13=0,"Correcto ",IF(L13-K13<0,"Faltan por ingresar","Sobran"))) | P13: =IF(ISBLANK(K13)," ",IF(L13-K13=0," ",L13-K13))
C14: Mayo | I14: =0.02*G14 -> 0 | J14: =G14-H14-I14 -> 0 | M14: =IF(ISBLANK(K14)," ",IF(K14-J14=0,"Correcto ",IF(K14-J14<0,"Faltan","Sobran"))) | N14: =IF(ISBLANK(K14)," ",IF(K14-J14=0," ",K14-J14)) | O14: =IF(ISBLANK(L14)," ",IF(L14-K14=0,"Correcto ",IF(L14-K14<0,"Faltan por ingresar","Sobran"))) | P14: =IF(ISBLANK(K14)," ",IF(L14-K14=0," ",L14-K14))
C15: Junio | I15: =0.02*G15 -> 0 | J15: =G15-H15-I15 -> 0 | M15: =IF(ISBLANK(K15)," ",IF(K15-J15=0,"Correcto ",IF(K15-J15<0,"Faltan","Sobran"))) | N15: =IF(ISBLANK(K15)," ",IF(K15-J15=0," ",K15-J15)) | O15: =IF(ISBLANK(L15)," ",IF(L15-K15=0,"Correcto ",IF(L15-K15<0,"Faltan por ingresar","Sobran"))) | P15: =IF(ISBLANK(K15)," ",IF(L15-K15=0," ",L15-K15))
C16: Julio | I16: =0.02*G16 -> 0 | J16: =G16-H16-I16 -> 0 | M16: =IF(ISBLANK(K16)," ",IF(K16-J16=0,"Correcto ",IF(K16-J16<0,"Faltan","Sobran"))) | N16: =IF(ISBLANK(K16)," ",IF(K16-J16=0," ",K16-J16)) | O16: =IF(ISBLANK(L16)," ",IF(L16-K16=0,"Correcto ",IF(L16-K16<0,"Faltan por ingresar","Sobran"))) | P16: =IF(ISBLANK(K16)," ",IF(L16-K16=0," ",L16-K16))
C17: Agosto | I17: =0.02*G17 -> 0 | J17: =G17-H17-I17 -> 0 | M17: =IF(ISBLANK(K17)," ",IF(K17-J17=0,"Correcto ",IF(K17-J17<0,"Faltan","Sobran"))) | N17: =IF(ISBLANK(K17)," ",IF(K17-J17=0," ",K17-J17)) | O17: =IF(ISBLANK(L17)," ",IF(L17-K17=0,"Correcto ",IF(L17-K17<0,"Faltan por ingresar","Sobran"))) | P17: =IF(ISBLANK(K17)," ",IF(L17-K17=0," ",L17-K17))
C18: Septiembre | I18: =0.02*G18 -> 0 | J18: =G18-H18-I18 -> 0 | M18: =IF(ISBLANK(K18)," ",IF(K18-J18=0,"Correcto ",IF(K18-J18<0,"Faltan","Sobran"))) | N18: =IF(ISBLANK(K18)," ",IF(K18-J18=0," ",K18-J18)) | O18: =IF(ISBLANK(L18)," ",IF(L18-K18=0,"Correcto ",IF(L18-K18<0,"Faltan por ingresar","Sobran"))) | P18: =IF(ISBLANK(K18)," ",IF(L18-K18=0," ",L18-K18))
C19: Octubre | I19: =0.02*G19 -> 0 | J19: =G19-H19-I19 -> 0 | M19: =IF(ISBLANK(K19)," ",IF(K19-J19=0,"Correcto ",IF(K19-J19<0,"Faltan","Sobran"))) | N19: =IF(ISBLANK(K19)," ",IF(K19-J19=0," ",K19-J19)) | O19: =IF(ISBLANK(L19)," ",IF(L19-K19=0,"Correcto ",IF(L19-K19<0,"Faltan por ingresar","Sobran"))) | P19: =IF(ISBLANK(K19)," ",IF(L19-K19=0," ",L19-K19))
C20: Noviembre | I20: =0.02*G20 -> 0 | J20: =G20-H20-I20 -> 0 | M20: =IF(ISBLANK(K20)," ",IF(K20-J20=0,"Correcto ",IF(K20-J20<0,"Faltan","Sobran"))) | N20: =IF(ISBLANK(K20)," ",IF(K20-J20=0," ",K20-J20)) | O20: =IF(ISBLANK(L20)," ",IF(L20-K20=0,"Correcto ",IF(L20-K20<0,"Faltan por ingresar","Sobran"))) | P20: =IF(ISBLANK(K20)," ",IF(L20-K20=0," ",L20-K20))
C21: Diciembre | I21: =0.02*G21 -> 0 | J21: =G21-H21-I21 -> 0 | M21: =IF(ISBLANK(K21)," ",IF(K21-J21=0,"Correcto ",IF(K21-J21<0,"Faltan","Sobran"))) | N21: =IF(ISBLANK(K21)," ",IF(K21-J21=0," ",K21-J21)) | O21: =IF(ISBLANK(L21)," ",IF(L21-K21=0,"Correcto ",IF(L21-K21<0,"Faltan por ingresar","Sobran"))) | P21: =IF(ISBLANK(K21)," ",IF(L21-K21=0," ",L21-K21))
E22: TOTAL | G22: =SUM(G10:G21) -> 0 | H22: =SUM(H10:H21) -> 0 | I22: =SUM(I10:I21) -> 0 | J22: =SUM(J10:J21) -> 0 | K22: =SUM(K10:K21) -> 0 | L22: =SUM(L10:L21) -> 0 | M22: =IF(ISBLANK(K22)," ",IF(K22-J22=0,"Correcto ",IF(K22-J22<0,"Faltan","Sobran"))) -> Correcto | N22: =IF(ISBLANK(K22)," ",IF(K22-J22=0," ",K22-J22)) | O22: =IF(ISBLANK(L22)," ",IF(L22-K22=0,"Correcto ",IF(L22-K22<0,"Faltan por ingresar","Sobran"))) -> Correcto | P22: =IF(ISBLANK(K22)," ",IF(L22-K22=0," ",L22-K22))
G23: =G22-H22-I22 -> 0
